Workbook

Sheet Ref
A1: STATUS | B1: Sector | C1: WTR/NTR | D1: COC | F1: Private | G1: Public | I1: Reasons for Program Closure
A2: WTR | B2: Agriculture, Forestry and Fishery | C2: Agricultural Crops Production NC I | D2: Support Agronomic Crop Work Leading to Agricultural Crop Production NC I | F2: TVI | G2: TTI | I2: Due for Migration
A3: WTR | B3: Agriculture, Forestry and Fishery | C3: Agricultural Crops Production NC I | D3: Support Horticultural Crop Work Leading to Agricultural Crops Production NC I | F3: Farm School | G3: LGU | I3: No enrollees
A4: WTR | B4: Agriculture, Forestry and Fishery | C4: Agricultural Crops Production NC I | D4: Support Nursery Work Leading to Agricultural Crop Production NC I | F4: HEI | G4: SUC | I4: No trainings conducted since registration or for the past 2 years
A5: WTR | B5: Agriculture, Forestry and Fishery | C5: Agricultural Crops Production NC I | D5: Not in the list (use the remarks column for the title) | F5: NGO | G5: NGA | I5: Non-migration to updated TR
A6: WTR | B6: Agriculture, Forestry and Fishery | C6: Agricultural Crops Production NC II | D6: Care and Maintain Crops Leading to Agricultural Crops Production NC II | F6: Enterprise | G6: LUC | I6: Transfer of location without re-registration
A7: WTR | B7: Agriculture, Forestry and Fishery | C7: Agricultural Crops Production NC II | D7: Carry-out Harvest and Post-Harvest Operations Leading to Agricultural Crops Production NC II | I7: No qualified trainer
A8: WTR | B8: Agriculture, Forestry and Fishery | C8: Agricultural Crops Production NC II | D8: Control Weeds Leading to Agricultural Crops Production NC II | I8: Non-closure of compliance audit findings
A9: WTR | B9: Agriculture, Forestry and Fishery | C9: Agricultural Crops Production NC II | D9: Perform Nursery Operations Leading to Agricultural Crops Production NC II | I9: No scholarship allocation
A10: WTR | B10: Agriculture, Forestry and Fishery | C10: Agricultural Crops Production NC II | D10: Plant Crops Leading to Agricultural Crops Production NC II | I10: Financial Constraints
A11: WTR | B11: Agriculture, Forestry and Fishery | C11: Agricultural Crops Production NC II | D11: Not in the list (use the remarks column for the title) | I11: TVI cannot be located
A12: WTR | B12: Agriculture, Forestry and Fishery | C12: Agricultural Crops Production NC III | D12: Control Weeds Leading to Agricultural Crops Production NC III | I12: Closed TVI
A13: WTR | B13: Agriculture, Forestry and Fishery | C13: Agricultural Crops Production NC III | D13: Establish Agronomic Crops Leading to Agricultural Crops Production NC III | I13: Management Decision/ Change Focus
A14: WTR | B14: Agriculture, Forestry and Fishery | C14: Agricultural Crops Production NC III | D14: Implement Plant Nutrition Program leading to Agricultural Crops Production NC III | I14: Implementation of TC
A15: WTR | B15: Agriculture, Forestry and Fishery | C15: Agricultural Crops Production NC III | D15: Implement Post-Harest Program Leading to Agricultural Crops Production NC III | G15: January | H15: Lone | J15: New TVI & Program
A16: WTR | B16: Agriculture, Forestry and Fishery | C16: Agricultural Crops Production NC III | D16: Implement Vertebrate Pest Control Program Leading to Agricultural Crops Production NC III | G16: February | H16: Cebu City | J16: Additional Program
A17: WTR | B17: Agriculture, Forestry and Fishery | C17: Agricultural Crops Production NC III | D17: Keep Records for Farm Business Leading to Agricultural Crops Production NC III | G17: March | H17: 1st | J17: Migration
A18: WTR | B18: Agriculture, Forestry and Fishery | C18: Agricultural Crops Production NC III | D18: Prepare Land for Agricultural Crop Production Leading to Agricultural Crop Production NC III | G18: April | H18: 2nd | J18: Re-registration
A19: WTR | B19: Agriculture, Forestry and Fishery | C19: Agricultural Crops Production NC III | D19: Produce Organic Fertilizers Leading to Agricultural Crops Production NC III | G19: May | H19: 3rd | J19: Reissuance
A20: WTR | B20: Agriculture, Forestry and Fishery | C20: Agricultural Crops Production NC III | D20: Save, Prepare and Store Agricultural Seeds Leading to Agricultural Crops Production NC III | G20: June | H20: 4th | J20: Reissued CTPR
A21: WTR | B21: Agriculture, Forestry and Fishery | C21: Agricultural Crops Production NC III | D21: Undertake Agronomic Crop Harvesting Activities Leading to Agricultural Crops Production NC III | G21: July | H21: 5th | J21: CLOSED
A22: WTR | B22: Agriculture, Forestry and Fishery | C22: Agricultural Crops Production NC III | D22: Not in the list (use the remarks column for the title) | G22: August | H22: 6th | J22: Correction
A23: WTR | B23: Agriculture, Forestry and Fishery | C23: Agricultural Machinery Operation NC II | G23: September | H23: 7th | J23: Migrated
A24: WTR | B24: Agriculture, Forestry and Fishery | C24: Agricultural Machinery Servicing (4-Wheel Tractor) NC III | G24: October | H24: 8th | J24: Recognized
A25: WTR | B25: Agriculture, Forestry and Fishery | C25: Agroentrepreneurship NC II | G25: November | H25: 9th
A26: WTR | B26: Agriculture, Forestry and Fishery | C26: Agroentrepreneurship NC III | G26: December | H26: 10th
A27: WTR | B27: Agriculture, Forestry and Fishery | C27: Agroentrepreneurship NC IV | H27: North
A28: WTR | B28: Agriculture, Forestry and Fishery | C28: Animal Health Care and Management NC III | H28: South
A29: WTR | B29: Agriculture, Forestry and Fishery | C29: Animal Production (Poultry-Chicken) NC II | D29: Brood and Grow Chicks Leading to Animal Production (Poultry-Chicken) NC II
A30: WTR | B30: Agriculture, Forestry and Fishery | C30: Animal Production (Poultry-Chicken) NC II | D30: Maintain Poultry house Leading to Animal Production (Poultry-Chicken) NC II
A31: WTR | B31: Agriculture, Forestry and Fishery | C31: Animal Production (Poultry-Chicken) NC II | D31: Perform Pre-Lay and Lay Activities Leading to Animal Production (Poultry-Chicken) NC II
A32: WTR | B32: Agriculture, Forestry and Fishery | C32: Animal Production (Poultry-Chicken) NC II | D32: Trim Beak Leading to Animal Production (Poultry-Chicken) NC II
A33: WTR | B33: Agriculture, Forestry and Fishery | C33: Animal Production (Poultry-Chicken) NC II | D33: Not in the list (use the remarks column for the title)
A34: WTR | B34: Agriculture, Forestry and Fishery | C34: Animal Production (Ruminants) NC II | D34: Maintain Housing, Farm Implements and Surrounding Area Leading to Animal Production (Ruminants) NC II
A35: WTR | B35: Agriculture, Forestry and Fishery | C35: Animal Production (Ruminants) NC II | D35: Perform Breeding of Ruminants Leading to Animal Production (Ruminants) NC II
A36: WTR | B36: Agriculture, Forestry and Fishery | C36: Animal Production (Ruminants) NC II | D36: Provide Forage Leading to Animal Production (Ruminants) NC II
A37: WTR | B37: Agriculture, Forestry and Fishery | C37: Animal Production (Ruminants) NC II | D37: Raise Dairy Animals Leading to Animal Production (Ruminants) NC II
A38: WTR | B38: Agriculture, Forestry and Fishery | C38: Animal Production (Ruminants) NC II | D38: Raise Meat Type Animals Leading to Animal Production (Ruminants) NC II
A39: WTR | B39: Agriculture, Forestry and Fishery | C39: Animal Production (Ruminants) NC II | D39: Not in the list (use the remarks column for the title)
A40: WTR | B40: Agriculture, Forestry and Fishery | C40: Animal Production (Swine) NC II | D40: Apply Bio-diversity Measures Leading to Animal Production (Swine) NC II
... A46: WTR | B46: Agriculture, Forestry and Fishery | C46: Animal Production (Swine) NC II | D46: Not in the list (use the remarks column for the title)
A47: WTR | B47: Agriculture, Forestry and Fishery | C47: Aquaculture (Grow-out Operation) NC II
A48: WTR | B48: Agriculture, Forestry and Fishery | C48: Aquaculture (Hatchery Operation) NC II
A49: WTR | B49: Agriculture, Forestry and Fishery | C49: Aquaculture (Tilapia Culture) NC II
A50: WTR | B50: Agriculture, Forestry and Fishery | C50: Aquaculture NC II (Superseded)
A51: WTR | B51: Agriculture, Forestry and Fishery | C51: Artificial Insemination (Large Ruminants) NC II
A52: WTR | B52: Agriculture, Forestry and Fishery | C52: Artificial Insemination (Swine) NC II
A53: WTR | B53: Agriculture, Forestry and Fishery | C53: Bamboo Processing (Engineered Bamboo) NC II
A54: WTR | B54: Agriculture, Forestry and Fishery | C54: Bamboo Production NC II
A55: WTR | B55: Agriculture, Forestry and Fishery | C55: Beekeeping NC II
A56: WTR | B56: Agriculture, Forestry and Fishery | C56: Biogas Plant Installation NC III
A57: WTR | B57: Agriculture, Forestry and Fishery | C57: Drying and Milling Plant Servicing NC III
A58: WTR | B58: Agriculture, Forestry and Fishery | C58: Fish Capture NC I
... A63: WTR | B63: Agriculture, Forestry and Fishery | C63: Horticulture NC II (Superseded)
A64: WTR | B64: Agriculture, Forestry and Fishery | C64: Horticulture NC III | D64: Coordinate Horticultural Crop Harvesting Leading to Horticulture NC III
A65: WTR | B65: Agriculture, Forestry and Fishery | C65: Horticulture NC III | D65: Coordinate Horticultural Maintenance Program Leading to Horticulture NC III
A66: WTR | B66: Agriculture, Forestry and Fishery | C66: Horticulture NC III | D66: Establish Horticultural Crops Leading to Horticulture NC III
A67: WTR | B67: Agriculture, Forestry and Fishery | C67: Horticulture NC III | D67: Maintain and Monitor Environmental Work Practices Leading to Horticulture NC III
A68: WTR | B68: Agriculture, Forestry and Fishery | C68: Horticulture NC III | D68: Undertake Field Budding and Grafting Leading to Horticulture NC III
A69: WTR | B69: Agriculture, Forestry and Fishery | C69: Horticulture NC III | D69: Undertake Propagation Activities Leading to Horticulture NC III
A70: WTR | B70: Agriculture, Forestry and Fishery | C70: Horticulture NC III | D70: Not in the list (use the remarks column for the title)
A71: WTR | B71: Agriculture, Forestry and Fishery | C71: Landscape Installation and Maintenance (Softscape) NC II
A72: WTR | B72: Agriculture, Forestry and Fishery | C72: Milking Operation NC II
A73: WTR | B73: Agriculture, Forestry and Fishery | C73: Organic Agriculture Production NC II | D73: Manufacture (Produce) Organic Fertilizer Leading to Organic Agriculture Production NC II
A74: WTR | B74: Agriculture, Forestry and Fishery | C74: Organic Agriculture Production NC II | D74: Produce Organic Concoction and Extract leading to Organic Agriculture Production NC II
A75: WTR | B75: Agriculture, Forestry and Fishery | C75: Organic Agriculture Production NC II | D75: Produce Organic Vegetables leading to Organic Agriculture Production NC II
A76: WTR | B76: Agriculture, Forestry and Fishery | C76: Organic Agriculture Production NC II | D76: Produce Various Concoctions Leading to Organic Agriculture Production NC II
A77: WTR | B77: Agriculture, Forestry and Fishery | C77: Organic Agriculture Production NC II | D77: Raise Organic Chicken Leading to Organic Agriculture Production NC II
A78: WTR | B78: Agriculture, Forestry and Fishery | C78: Organic Agriculture Production NC II | D78: Raise Organic Chicken leading to Organic Agriculture Production NC II
A79: WTR | B79: Agriculture, Forestry and Fishery | C79: Organic Agriculture Production NC II | D79: Raise Organic Hogs Leading to Organic Agriculture Production NC II
A80: WTR | B80: Agriculture, Forestry and Fishery | C80: Organic Agriculture Production NC II | D80: Raise Organic Small Ruminants Leading to Organic Agriculture Production NC II
A81: WTR | B81: Agriculture, Forestry and Fishery | C81: Organic Agriculture Production NC II | D81: Not in the list (use the remarks column for the title)
A82: WTR | B82: Agriculture, Forestry and Fishery | C82: Pest Management (Vegetables) NC II | D82: Apply Bio-Control Measures Leading to Pest Management (Vegetables) NC II
A83: WTR | B83: Agriculture, Forestry and Fishery | C83: Pest Management (Vegetables) NC II | D83: Apply Cultural Management Startegies Leading to Pest Management (Vegetables) NC II
A84: WTR | B84: Agriculture, Forestry and Fishery | C84: Pest Management (Vegetables) NC II | D84: Apply Physical Control Measures Leading to Pest Management (Vegetables) NC II
... A87: WTR | B87: Agriculture, Forestry and Fishery | C87: Pest Management (Vegetables) NC II | D87: Not in the list (use the remarks column for the title)
A88: WTR | B88: Agriculture, Forestry and Fishery | C88: Pressurized Irrigation System Installation and Maintenance NC II
A89: WTR | B89: Agriculture, Forestry and Fishery | C89: Rice Machinery Operations NC II
A90: WTR | B90: Agriculture, Forestry and Fishery | C90: Rubber Processing NC II
A91: WTR | B91: Agriculture, Forestry and Fishery | C91: Rubber Production NC II
A92: WTR | B92: Agriculture, Forestry and Fishery | C92: Rubber Production NC II (Superseded)
A93: WTR | B93: Agriculture, Forestry and Fishery | C93: Seaweed Production NC II
A94: WTR | B94: Agriculture, Forestry and Fishery | C94: Sugarcane Production NC II
A95: WTR | B95: Automotive and Land Transportation | C95: Auto Engine Rebuilding NC II
A96: WTR | B96: Automotive and Land Transportation | C96: Automotive Body Painting/Finishing NC I
A97: WTR | B97: Automotive and Land Transportation | C97: Automotive Body Painting/Finishing NC II (Superseded)
A98: WTR | B98: Automotive and Land Transportation | C98: Automotive Body Painting/Finishing NC III
A99: WTR | B99: Automotive and Land Transportation | C99: Automotive Body Repairing NC II
... A130: WTR | B130: Automotive and Land Transportation | C130: Moldmaking NC II
A131: WTR | B131: Automotive and Land Transportation | C131: Motorcycle/Small Engine Servicing NC II | D131: Service Motorcycle/ Small Engine System Leading to Motorcycle/Small Engine Servicing NC II
A132: WTR | B132: Automotive and Land Transportation | C132: Motorcycle/Small Engine Servicing NC II | D132: Not in the list (use the remarks column for the title)
A133: WTR | B133: Automotive and Land Transportation | C133: Motorcycle/Small Engine Servicing NC II (Superseded) | D133: Service Motorcycle/ Small Engine System Leading to Motorcycle/Small Engine Servicing NC II
A134: WTR | B134: Automotive and Land Transportation | C134: Motorcycle/Small Engine Servicing NC II (Superseded) | D134: Not in the list (use the remarks column for the title)
A135: WTR | B135: Automotive and Land Transportation | C135: Painting Machine Operation NC II
A136: WTR | B136: Automotive and Land Transportation | C136: Plastic Machine Operation NC II
A137: WTR | B137: Automotive and Land Transportation | C137: Plastic Machine Operation NC III
A138: WTR | B138: Automotive and Land Transportation | C138: Process Inspection NC II
A139: WTR | B139: Automotive and Land Transportation | C139: Process Inspection NC III
A140: WTR | B140: Automotive and Land Transportation | C140: Speed Limitation Device Servicing NC II
A141: WTR | B141: Automotive and Land Transportation | C141: Tinsmithing (Automotive Manufacturing) NC II
...

Sheet Ref2
A1: Agriculture, Forestry and Fishery | B1: Automotive and Land Transportation | C1: Chemicals/ Plastics/ Petrochemicals | D1: Construction | E1: Creative Sector | F1: Decorative Crafts | G1: Electrical and Electronics | H1: Footwear and Leathergoods | I1: Furniture and Fixtures | J1: Garments | K1: Heating, Ventilation, Airconditioning and Refrigeration | L1: Human Health/ Health Care | M1: Information and Communication Technology | N1: Logistics | O1: Maritime | P1: Metals and Engineering | Q1: Others (Languages) | R1: Processed Food and Beverages | S1: Pyrotechnics | T1: Social, Community Development and Other Services | U1: Tourism | V1: TVET | W1: Utilities | X1: Visual Arts | Y1: Wholesale and Retail Trading
A2: Agricultural Crops Production NC I | B2: Auto Engine Rebuilding NC II | C2: Chemical Process Operations NC III | D2: Carpentry NC II | E2: Audio Production Services NC I | F2: Jewelry Making (Fine Jewelry) NC II | G2: Computer Systems Servicing NC II | H2: Shoemaking NC I | I2: Furniture Making (Finishing) NC II | J2: Dressmaking NC II | K2: Air Duct Servicing NC II | L2: Assistive Rehabilitation Technology Services (Orthotics) NC II | M2: 2D Animation NC III | N2: Multimodal Transport Operations and Logistics (Seafreight Import) Services NC II | O2: Marine Electricity NC II | P2: 5-Axis CNC Machine Operation NC III | R2: Fish Products Packaging NC II | S2: Pyrotechnics NC II | T2: Barbering NC II | U2: Attractions and Theme Parks Operations NC II | V2: Trainers Methodology Level I (In-Company Trainer) | W2: Diesel Power Plant Maintenance NC III | X2: Illustration NC II | Y2: Customer Services NC II
A3: Agricultural Crops Production NC I - Mobile Training Program | B3: Auto Engine Rebuilding NC II - Mobile Training Program | C3: Chemical Process Operations NC III - Mobile Training Program | D3: Carpentry NC II - Mobile Training Program | E3: Audio Production Services NC I - Mobile Training Program | F3: Jewelry Making (Fine Jewelry) NC II - Mobile Training Program | G3: Computer Systems Servicing NC II - Mobile Training Program | H3: Shoemaking NC I - Mobile Training Program | I3: Furniture Making (Finishing) NC II - Mobile Training Program | J3: Dressmaking NC II - Mobile Training Program | K3: Air Duct Servicing NC II - Mobile Training Program | L3: Assistive Rehabilitation Technology Services (Orthotics) NC II - Mobile Training Program | M3: 2D Animation NC III - Mobile Training Program | N3: Multimodal Transport Operations and Logistics (Seafreight Import) Services NC II - Mobile Training Program | O3: Marine Electricity NC II - Mobile Training Program | P3: 5-Axis CNC Machine Operation NC III - Mobile Training Program | R3: Fish Products Packaging NC II - Mobile Training Program | S3: Pyrotechnics NC II - Mobile Training Program | T3: Barbering NC II - Mobile Training Program | U3: Attractions and Theme Parks Operations NC II - Mobile Training Program | V3: Trainers Methodology Level I (In-Company Trainer) - Mobile Training Program | W3: Diesel Power Plant Maintenance NC III - Mobile Training Program | X3: Illustration NC II - Mobile Training Program | Y3: Customer Services NC II - Mobile Training Program
A4: Agricultural Crops Production NC II | B4: Automotive Body Painting/Finishing NC I | D4: Carpentry NC III | E4: Film and Video Postproduction NC III | F4: Jewelry Making (Fine Jewelry) NC III | G4: Consumer Electronics Servicing NC III | H4: Shoemaking NC II | J4: Fashion Design (Apparel) NC III | K4: Commercial Air-conditioning Installation and Servicing NC III | L4: Assistive Rehabilitation Technology Services (Prosthetics) NC II | M4: 2D Game Art Development NC III | N4: Multimodal Transport Operations and Logistics (Seafreight Import) Services NC III | O4: Ship's Catering Services NC I | P4: CAD/CAM Operation NC III | R4: Food Processing NC I | T4: Beauty Care (Nail Care) Services NC II | U4: Barista NC II | V4: Trainers Methodology Level I (Trainer/Assessor) | W4: Diesel Power Plant Operation and Maintenance NC II | X4: Photography NC II
A5: Agricultural Crops Production NC II - Mobile Training Program | B5: Automotive Body Painting/Finishing NC III | D5: Carpentry NC III - Mobile Training Program | E5: Film and Video Postproduction NC III - Mobile Training Program | F5: Jewelry Making (Fine Jewelry) NC III - Mobile Training Program | G5: Consumer Electronics Servicing NC III - Mobile Training Program | H5: Shoemaking NC II - Mobile Training Program | J5: Fashion Design (Apparel) NC III - Mobile Training Program | K5: Commercial Air-conditioning Installation and Servicing NC III - Mobile Training Program | L5: Assistive Rehabilitation Technology Services (Prosthetics) NC II - Mobile Training Program | M5: 2D Game Art Development NC III - Mobile Training Program | N5: Multimodal Transport Operations and Logistics (Seafreight Import) Services NC III - Mobile Training Program | O5: Ship's Catering Services NC I - Mobile Training Program | P5: CAD/CAM Operation NC III - Mobile Training Program | R5: Food Processing NC I - Mobile Training Program | T5: Beauty Care (Nail Care) Services NC II - Mobile Training Program | U5: Barista NC II - Mobile Training Program | V5: Trainers Methodology Level I (Trainer/Assessor) - Mobile Training Program | W5: Diesel Power Plant Operation and Maintenance NC II - Mobile Training Program | X5: Photography NC II - Mobile Training Program
A6: Agricultural Crops Production NC III | B6: Automotive Body Painting/Finishing NC III - Mobile Training Program | D6: Construction Lift Passenger/Material Elevator Operation NC II | E6: Handloom Weaving (Upright) NC II | G6: Consumer Electronics Servicing NC IV | J6: Tailoring NC II | K6: Commercial Refrigeration Installation and Servicing NC III | L6: Assistive Rehabilitation Technology Services (Wheelchair) NC II | M6: 3D Animation NC III | N6: Multimodal Transport Operations and Logistics (Seafreight Import) Services NC IV | O6: Ships' Catering NC III (Ships' Cooks) | P6: CNC Electric Discharge Machine (EDM) Wire Cut Operation NC III | R6: Food Processing NC II | T6: Beauty Care (Nail Enhancement Technology) Services NC III | U6: Bartending NC II | V6: Trainers Methodology Level II (Training Designer/Developer) | W6: Diesel Power Plant Operation and Maintenance NC III
A7: Agricultural Crops Production NC III - Mobile Training Program | B7: Automotive Body Repairing NC II | D7: Construction Lift Passenger/Material Elevator Operation NC II - Mobile Training Program | E7: Handloom Weaving (Upright) NC II - Mobile Training Program | G7: Consumer Electronics Servicing NC IV - Mobile Training Program | J7: Tailoring NC II - Mobile Training Program | K7: Commercial Refrigeration Installation and Servicing NC III - Mobile Training Program | L7: Assistive Rehabilitation Technology Services (Wheelchair) NC II - Mobile Training Program | M7: 3D Animation NC III - Mobile Training Program | N7: Multimodal Transport Operations and Logistics (Seafreight Import) Services NC IV - Mobile Training Program | O7: Ships' Catering NC III (Ships' Cooks) - Mobile Training Program | P7: CNC Electric Discharge Machine (EDM) Wire Cut Operation NC III - Mobile Training Program | R7: Food Processing NC II - Mobile Training Program | T7: Beauty Care (Nail Enhancement Technology) Services NC III - Mobile Training Program | U7: Bartending NC II - Mobile Training Program | V7: Trainers Methodology Level II (Training Designer/Developer) - Mobile Training Program | W7: Diesel Power Plant Operation and Maintenance NC III - Mobile Training Program
A8: Agricultural Machinery Operation NC II | B8: Automotive Body Repairing NC II - Mobile Training Program | D8: Construction Painting NC II | E8: Beadwork Accessories and Diversified Beadwork Products Making NC II | G8: Biomedical Equipment Servicing NC II | K8: Ice Plant Refrigeration Servicing NC III | L8: Barangay Health Services NC II | M8: 3D Game Art Development NC III | N8: Warehousing Services NC II | P8: CNC Lathe Machine Operation NC II | R8: Food Processing NC III | T8: Beauty Care (Skin Care) Services NC II | U8: Bread and Pastry Production NC II | V8: Develop Learning Materials for E-Learning leading to Trainer Methodology Level II | W8: Electric Power Distribution Line Construction NC II
A9: Agricultural Machinery Operation NC II - Mobile Training Program | B9: Automotive Electrical Assembly NC II | D9: Construction Painting NC II - Mobile Training Program | E9: Beadwork Accessories and Diversified Beadwork Products Making NC II - Mobile Training Program | G9: Biomedical Equipment Servicing NC II - Mobile Training Program | K9: Ice Plant Refrigeration Servicing NC III - Mobile Training Program | L9: Barangay Health Services NC II - Mobile Training Program | M9: 3D Game Art Development NC III - Mobile Training Program | N9: Warehousing Services NC II - Mobile Training Program | P9: CNC Lathe Machine Operation NC II - Mobile Training Program | R9: Food Processing NC III - Mobile Training Program | T9: Beauty Care (Skin Care) Services NC II - Mobile Training Program | U9: Bread and Pastry Production NC II - Mobile Training Program | V9: Develop Learning Materials for E-Learning leading to Trainer Methodology Level II - Mobile Training Program | W9: Electric Power Distribution Line Construction NC II - Mobile Training Program
A10: Agricultural Machinery Servicing (4-Wheel Tractor) NC III | B10: Automotive Electrical Assembly NC II - Mobile Training Program | D10: Construction Painting NC III | E10: Handloom Weaving (Backstrap) NC II | G10: Electrical Installation and Maintenance NC II | K10: Land-Based Transport Mobile Air-conditioning (MAC) NC II | L10: Biomedical Equipment Servicing NC II (Superseded) | M10: Animation NC II | N10: Warehousing Services NC III | P10: CNC Lathe Machine Operation NC III | R10: Food Processing NC IV | T10: Beauty Care Services (Nail Care) NC III (Superseded) | U10: Commercial Cooking NC II (Amended) | V10: Develop Learning Materials Leading to Trainers Methodology Level II | W10: Electric Power Distribution Operation and Maintenance NC III
A11: Agricultural Machinery Servicing (4-Wheel Tractor) NC III - Mobile Training Program | B11: Automotive Electrical Assembly NC III | D11: Construction Painting NC III - Mobile Training Program | E11: Handloom Weaving (Backstrap) NC II - Mobile Training Program | G11: Electrical Installation and Maintenance NC II - Mobile Training Program | K11: Land-Based Transport Mobile Air-conditioning (MAC) NC II - Mobile Training Program | L11: Biomedical Equipment Servicing NC II (Superseded) - Mobile Training Program | M11: Animation NC II - Mobile Training Program | N11: Warehousing Services NC III - Mobile Training Program | P11: CNC Lathe Machine Operation NC III - Mobile Training Program | R11: Food Processing NC IV - Mobile Training Program | T11: Bookkeeping NC III | U11: Commercial Cooking NC II (Amended) - Mobile Training Program | V11: Develop Learning Materials Leading to Trainers Methodology Level II - Mobile Training Program | W11: Electric Power Distribution Operation and Maintenance NC III - Mobile Training Program
A12: Agroentrepreneurship NC II | B12: Automotive Electrical Assembly NC III - Mobile Training Program | D12: Heavy Equipment Operation (Articulated Off-Highway Dump Truck) NC II | E12: Paper Mache Making NC II | G12: Electrical Installation and Maintenance NC III | K12: Land-based Transport Refrigeration Servicing NC II | L12: Caregiving (Clients with Special Needs) NC II | M12: Broadband Installation (Fixed Wireless Systems) NC II | N12: Warehousing Services NC IV | P12: CNC Milling Machine Operation NC II | R12: Slaughtering Operations (Large Animal) NC II | T12: Bookkeeping NC III - Mobile Training Program | U12: Commercial Cooking NC III (Superseded) | V12: Develop Training Curriculum, Develop Training Materials, Develop Competency Assessment Tools Leading to Trainers Methodology Level II | W12: Electric Power Distribution Operation and Maintenance NC IV
A13: Agroentrepreneurship NC II - Mobile Training Program | B13: Automotive Mechanical Assembly NC II | D13: Heavy Equipment Operation (Articulated Off-Highway Dump Truck) NC II - Mobile Training Program | E13: Paper Mache Making NC II - Mobile Training Program | G13: Electrical Installation and Maintenance NC III - Mobile Training Program | K13: Land-based Transport Refrigeration Servicing NC II - Mobile Training Program | L13: Caregiving (Clients with Special Needs) NC II - Mobile Training Program | M13: Broadband Installation (Fixed Wireless Systems) NC II - Mobile Training Program | N13: Warehousing Services NC IV - Mobile Training Program | P13: CNC Milling Machine Operation NC II - Mobile Training Program | R13: Slaughtering Operations (Large Animal) NC II - Mobile Training Program | T13: Domestic Work NC II | U13: Commercial Cooking NC III (Superseded) - Mobile Training Program | V13: Develop Training Curriculum, Develop Training Materials, Develop Competency Assessment Tools Leading to Trainers Methodology Level II - Mobile Training Program | W13: Electric Power Distribution Operation and Maintenance NC IV - Mobile Training Program
A14: Agroentrepreneurship NC III | B14: Automotive Mechanical Assembly NC II - Mobile Training Program | D14: Heavy Equipment Operation (Backhoe Loader) NC II | E14: Head Embroidery NC II | G14: Electrical Installation and Maintenance NC IV | K14: RAC Servicing (DomRAC) NC II | L14: Caregiving (Elderly) NC II | M14: Cable TV Installation NC II | P14: CNC Milling Machine Operation NC III | R14: Slaughtering Operations (Swine) NC II | T14: Domestic Work NC II - Mobile Training Program | U14: Commercial Cooking NC IV (Superseded) | V14: Online Program for Developing Training Curriculum Leading to Trainers Methodology Level II | W14: Garbage Collection NC I
A15: Agroentrepreneurship NC III - Mobile Training Program | B15: Automotive Mechanical Assembly NC III | D15: Heavy Equipment Operation (Backhoe Loader) NC II - Mobile Training Program | E15: Head Embroidery NC II - Mobile Training Program | G15: Electrical Installation and Maintenance NC IV - Mobile Training Program | K15: RAC Servicing (DomRAC) NC II - Mobile Training Program | L15: Caregiving (Elderly) NC II - Mobile Training Program | M15: Cable TV Installation NC II - Mobile Training Program | P15: CNC Milling Machine Operation NC III - Mobile Training Program | R15: Slaughtering Operations (Swine) NC II - Mobile Training Program | T15: Hairdressing NC II | U15: Cookery NC II | V15: Online Program for Developing Training Curriculum Leading to Trainers Methodology Level II - Mobile Training Program | W15: Garbage Collection NC I - Mobile Training Program
A16: Agroentrepreneurship NC IV | B16: Automotive Mechanical Assembly NC III - Mobile Training Program | D16: Heavy Equipment Operation (Bulldozer) NC II | E16: Mat Weaving and Diversified Mat Products Making NC II | G16: Electronic Products Assembly and Servicing NC II | K16: RAC Servicing (PACU-CRE) NC III (Amended) | L16: Caregiving (Grade Schooler to Adolescent) NC II | M16: Cable TV Operation and Maintenance NC III | P16: Die Designing NC IV | R16: Process Food by Fermentation and Pickling leading to Food Processing NC II | T16: Hairdressing NC II - Mobile Training Program | U16: Cookery NC II - Mobile Training Program | W16: Line Construction (Electric Power Distribution) NC II (Amended)
A17: Agroentrepreneurship NC IV - Mobile Training Program | B17: Automotive Painting NC II | D17: Heavy Equipment Operation (Bulldozer) NC II - Mobile Training Program | E17: Mat Weaving and Diversified Mat Products Making NC II - Mobile Training Program | G17: Electronic Products Assembly and Servicing NC II - Mobile Training Program | K17: RAC Servicing (PACU-CRE) NC III (Amended) - Mobile Training Program | L17: Caregiving (Grade Schooler to Adolescent) NC II - Mobile Training Program | M17: Cable TV Operation and Maintenance NC III - Mobile Training Program | P17: Die Designing NC IV - Mobile Training Program | R17: Process Food by Fermentation and Pickling leading to Food Processing NC II - Mobile Training Program | T17: Hairdressing NC III | U17: Events Management Services NC III | W17: Sanitary Landfill Operations NC II
A18: Animal Health Care and Management NC III | B18: Automotive Painting NC II - Mobile Training Program | D18: Heavy Equipment Operation (Concrete Pump) NC II | E18: Wood Carving NC II | G18: Electronics Back-End Operation NC II | K18: Transport RAC Servicing NC II (Amended) | L18: Caregiving (Newborn to Pre-Schooler) NC II | M18: Contact Center Services NC II | P18: Electric Discharge Machine (EDM) Sinking Operation NC II | R18: Process Food by Sugar Concentration leading to Food Processing NC II | T18: Hairdressing NC III - Mobile Training Program | U18: Events Management Services NC III - Mobile Training Program | W18: Sanitary Landfill Operations NC II - Mobile Training Program
A19: Animal Health Care and Management NC III - Mobile Training Program | B19: Automotive Servicing (Chassis Repair) NC II | D19: Heavy Equipment Operation (Concrete Pump) NC II - Mobile Training Program | E19: Wood Carving NC II - Mobile Training Program | G19: Electronics Back-End Operation NC II - Mobile Training Program | K19: Transport RAC Servicing NC II (Amended) - Mobile Training Program | L19: Caregiving (Newborn to Pre-Schooler) NC II - Mobile Training Program | M19: Contact Center Services NC II - Mobile Training Program | P19: Electric Discharge Machine (EDM) Sinking Operation NC II - Mobile Training Program | R19: Process Food by Sugar Concentration leading to Food Processing NC II - Mobile Training Program | T19: Lifeguard Services NC II | U19: Food and Beverage Services NC II | W19: Sanitary Landfill Operations NC III
A20: Animal Production (Poultry-Chicken) NC II | B20: Automotive Servicing (Chassis Repair) NC II - Mobile Training Program | D20: Heavy Equipment Operation (Container Stacker) NC II | E20: Basket Weaving NC II | G20: Electronics Front-of-Line Operation NC II | L20: Caregiving NC II | M20: Game Programming NC III | P20: Flux-Cored Arc Welding (FCAW) NC I | R20: Process Food by Salting and Curing leading to Food Processing NC II | T20: Lifeguard Services NC II - Mobile Training Program | U20: Food and Beverage Services NC II - Mobile Training Program | W20: Sanitary Landfill Operations NC III - Mobile Training Program
A21: Animal Production (Poultry-Chicken) NC II - Mobile Training Program | B21: Automotive Servicing (Electrical Repair) NC II | D21: Heavy Equipment Operation (Container Stacker) NC II - Mobile Training Program | E21: Basket Weaving NC II - Mobile Training Program | G21: Electronics Front-of-Line Operation NC II - Mobile Training Program | L21: Caregiving NC II - Mobile Training Program | M21: Game Programming NC III - Mobile Training Program | P21: Flux-Cored Arc Welding (FCAW) NC I - Mobile Training Program | R21: Process Food by Salting and Curing leading to Food Processing NC II - Mobile Training Program | T21: Lifeguard Services NC III | U21: Food and Beverage Services NC III (Amended) | W21: Transmission Line Installation and Maintenance NC II
A22: Animal Production (Ruminants) NC II | B22: Automotive Servicing (Electrical Repair) NC II - Mobile Training Program | D22: Heavy Equipment Operation (Crawler Crane) NC III | E22: Lighting for Live Performances NC II | G22: Electronics/Semiconductor Production Line Machine Servicing NC III | L22: Contact Tracing NC II | M22: Medical Coding and Claims Processing NC III | P22: Flux-Cored Arc Welding (FCAW) NC II | R22: Process Food by Salting, Curing and Smoking Leading to Food Processing NC II | T22: Lifeguard Services NC III - Mobile Training Program | U22: Food and Beverage Services NC III (Amended) - Mobile Training Program | W22: Transmission Line Installation and Maintenance NC II - Mobile Training Program
A23: Animal Production (Ruminants) NC II - Mobile Training Program | B23: Automotive Servicing (Engine Repair) NC II | D23: Heavy Equipment Operation (Crawler Crane) NC III - Mobile Training Program | E23: Lighting for Live Performances NC II - Mobile Training Program | G23: Electronics/Semiconductor Production Line Machine Servicing NC III - Mobile Training Program | L23: Contact Tracing NC II - Mobile Training Program | M23: Medical Coding and Claims Processing NC III - Mobile Training Program | P23: Flux-Cored Arc Welding (FCAW) NC II - Mobile Training Program | R23: Process Food by Salting, Curing and Smoking Leading to Food Processing NC II - Mobile Training Program | T23: Microfinance Technology NC II | U23: Food and Beverage Services NC III | W23: Transmission Line Installation and Maintenance NC III
A24: Animal Production (Swine) NC II | B24: Automotive Servicing (Engine Repair) NC II - Mobile Training Program | D24: Heavy Equipment Operation (Forklift) NC II (Superseded) | G24: Hard Disk Drive (HDD) Front-of-line (FOL) Operations NC II | L24: Dental Hygiene Level IV | M24: Medical Transcription NC II | P24: Flux-Cored Arc Welding (FCAW) NC III | R24: Slaughtering Operations NC II (Amended) | T24: Microfinance Technology NC II - Mobile Training Program | U24: Food and Beverage Services NC III - Mobile Training Program | W24: Transmission Line Installation and Maintenance NC III - Mobile Training Program
A25: Animal Production (Swine) NC II - Mobile Training Program | B25: Automotive Servicing NC I | D25: Heavy Equipment Operation (Forklift) NC II (Superseded) - Mobile Training Program | G25: Hard Disk Drive (HDD) Front-of-line (FOL) Operations NC II - Mobile Training Program | L25: Dental Hygiene Level IV - Mobile Training Program | M25: Medical Transcription NC II - Mobile Training Program | P25: Flux-Cored Arc Welding (FCAW) NC III - Mobile Training Program | T25: Microfinance Technology NC IV | U25: Food and Beverage Services NC IV | W25: Transmission Line Installation and Maintenance NC IV
A26: Aquaculture NC II (Superseded) | B26: Automotive Servicing NC I - Mobile Training Program | D26: Heavy Equipment Operation (Forklift) NC II | G26: Instrumentation and Control Servicing NC II | L26: Dental Laboratory Technology Services (Fixed Dentures/Restorations) NC II | M26: Programming (.Net Technology) NC III | P26: Gas Metal Arc Welding (GMAW) NC I | T26: Microfinance Technology NC IV - Mobile Training Program | U26: Food and Beverage Services NC IV - Mobile Training Program | W26: Transmission Line Installation and Maintenance NC IV - Mobile Training Program
A27: Aquaculture NC II (Superseded) - Mobile Training Program | B27: Automotive Servicing NC III | D27: Heavy Equipment Operation (Forklift) NC II - Mobile Training Program | G27: Instrumentation and Control Servicing NC II - Mobile Training Program | L27: Dental Laboratory Technology Services (Fixed Dentures/Restorations) NC II - Mobile Training Program | M27: Programming (.Net Technology) NC III - Mobile Training Program | P27: Gas Metal Arc Welding (GMAW) NC I - Mobile Training Program | T27: Microinsurance Services (Mutual Benefit) NC II | U27: Food Production (Professional Cookery) NC III
A28: Aquaculture (Grow-out Operation) NC II | B28: Automotive Servicing NC III - Mobile Training Program | D28: Heavy Equipment Operation (Hydraulic Excavator) NC II | G28: Instrumentation and Control Servicing NC III | L28: Dental Laboratory Technology Services (Removable Dentures/Appliances) NC II | M28: Programming (Java) NC III | P28: Gas Metal Arc Welding (GMAW) NC II | T28: Microinsurance Services (Mutual Benefit) NC II - Mobile Training Program | U28: Food Production (Professional Cookery) NC III - Mobile Training Program
A29: Aquaculture (Grow-out Operation) NC II - Mobile Training Program | B29: Automotive Servicing NC IV | D29: Heavy Equipment Operation (Hydraulic Excavator) NC II - Mobile Training Program | G29: Instrumentation and Control Servicing NC III - Mobile Training Program | L29: Dental Laboratory Technology Services (Removable Dentures/Appliances) NC II - Mobile Training Program | M29: Programming (Java) NC III - Mobile Training Program | P29: Gas Metal Arc Welding (GMAW) NC II - Mobile Training Program | T29: Performing Arts (Ballroom Dancing) NC II | U29: Food Production (Professional Cookery) NC IV
A30: Aquaculture (Hatchery Operation) NC II | B30: Automotive Servicing NC IV - Mobile Training Program | D30: Heavy Equipment Operation (Motor Grader) NC II | G30: Instrumentation and Control Servicing NC IV | L30: Dental Laboratory Technology Services NC I | M30: Programming (Oracle Database) NC III | P30: Gas Metal Arc Welding (GMAW) NC III | T30: Performing Arts (Ballroom Dancing) NC II - Mobile Training Program | U30: Food Production (Professional Cookery) NC IV - Mobile Training Program
A31: Aquaculture (Hatchery Operation) NC II - Mobile Training Program | B31: Automotive Wiring Harness Assembly NC II | D31: Heavy Equipment Operation (Motor Grader) NC II - Mobile Training Program | G31: Instrumentation and Control Servicing NC IV - Mobile Training Program | L31: Dental Laboratory Technology Services NC I - Mobile Training Program | M31: Programming (Oracle Database) NC III - Mobile Training Program | P31: Gas Metal Arc Welding (GMAW) NC III - Mobile Training Program | T31: Performing Arts (Dance) NC II | U31: Front Office Services NC II
A32: Aquaculture (Tilapia Culture) NC II | B32: Automotive Wiring Harness Assembly NC II - Mobile Training Program | D32: Heavy Equipment Operation (Overhead and Gantry Crane) NC III | G32: Mechatronics Servicing NC II | L32: Dental Technology NC IV | M32: Telecom OSP and Subscriber Line Installation (Copper Cable/POTS and DSL) NC II | P32: Gas Tungsten Arc Welding (GTAW) NC II | T32: Performing Arts (Dance) NC II - Mobile Training Program | U32: Front Office Services NC II - Mobile Training Program
A33: Aquaculture (Tilapia Culture) NC II - Mobile Training Program | B33: Driving (Articulated Vehicle) NC III | D33: Heavy Equipment Operation (Overhead and Gantry Crane) NC III - Mobile Training Program | G33: Mechatronics Servicing NC II - Mobile Training Program | L33: Dental Technology NC IV - Mobile Training Program | M33: Telecom OSP and Subscriber Line Installation (Copper Cable/POTS and DSL) NC II - Mobile Training Program | P33: Gas Tungsten Arc Welding (GTAW) NC II - Mobile Training Program | T33: Performing Arts (Magician) NC II | U33: Front Office Services NC III
A34: Artificial Insemination (Large Ruminants) NC II | B34: Driving (Articulated Vehicle) NC III - Mobile Training Program | D34: Heavy Equipment Operation (Paver) NC II | G34: Mechatronics Servicing NC III | L34: Emergency Medical Services NC II | M34: Telecom OSP Installation (Fiber Optic Cable) NC II | P34: Gas Tungsten Arc Welding (GTAW) NC IV | T34: Performing Arts (Magician) NC II - Mobile Training Program | U34: Front Office Services NC III - Mobile Training Program
A35: Artificial Insemination (Large Ruminants) NC II - Mobile Training Program | B35: Driving (Passenger Bus/Straight Truck) NC III | D35: Heavy Equipment Operation (Paver) NC II - Mobile Training Program | G35: Mechatronics Servicing NC III - Mobile Training Program | L35: Emergency Medical Services NC II - Mobile Training Program | M35: Telecom OSP Installation (Fiber Optic Cable) NC II - Mobile Training Program | P35: Gas Tungsten Arc Welding (GTAW) NC IV - Mobile Training Program | T35: Performing Arts (Song) NC II | U35: Front Office Services NC IV
A36: Artificial Insemination (Swine) NC II | B36: Driving (Passenger Bus/Straight Truck) NC III - Mobile Training Program | D36: Heavy Equipment Operation (Rigid Off-Highway Dump Truck) NC II | G36: Mechatronics Servicing NC IV | L36: Emergency Medical Services NC III | M36: Visual Graphic Design NC III | P36: Gas Welding NC I | T36: Performing Arts (Song) NC II - Mobile Training Program | U36: Front Office Services NC IV - Mobile Training Program
A37: Artificial Insemination (Swine) NC II - Mobile Training Program | B37: Driving NC II | D37: Heavy Equipment Operation (Rigid Off-Highway Dump Truck) NC II - Mobile Training Program | G37: Mechatronics Servicing NC IV - Mobile Training Program | L37: Emergency Medical Services NC III - Mobile Training Program | M37: Visual Graphic Design NC III - Mobile Training Program | P37: Gas Welding NC I - Mobile Training Program | T37: Public Employment Services NC IV | U37: Housekeeping NC II
A38: Bamboo Processing (Engineered Bamboo) NC II | B38: Driving NC II - Mobile Training Program | D38: Heavy Equipment Operation (Rigid On-Highway Dump Truck) NC II | G38: Mobile Phones and Handheld Gadgets Servicing NC III | L38: Health Care Services NC II | M38: Web Development NC III | P38: Gas Welding NC II | T38: Public Employment Services NC IV - Mobile Training Program | U38: Housekeeping NC II - Mobile Training Program
... A40: Bamboo Production NC II | B40: Forging NC II - Mobile Training Program | D40: Heavy Equipment Operation (Road Roller) NC II | G40: Semiconductor Back-End Operation NC II | L40: Hilot (Wellness Massage) NC II | M40: Develop Responsive Web Design Leading to Web Development NC III | P40: Machining NC I | T40: Real Estate Services NC II - Mobile Training Program | U40: Housekeeping NC III - Mobile Training Program
A41: Bamboo Production NC II - Mobile Training Program | B41: Forging NC III | D41: Heavy Equipment Operation (Road Roller) NC II - Mobile Training Program | G41: Semiconductor Back-End Operation NC II - Mobile Training Program | L41: Hilot (Wellness Massage) NC II - Mobile Training Program | P41: Machining NC I - Mobile Training Program | T41: Security Services NC I | U41: Housekeeping NC IV
A42: Beekeeping NC II | B42: Forging NC III - Mobile Training Program | D42: Heavy Equipment Operation (Rough Terrain Crane) NC III | G42: Semiconductor Front-of-Line Operation NC II | L42: Massage Therapy NC II | P42: Machining NC II | T42: Security Services NC I - Mobile Training Program | U42: Housekeeping NC IV - Mobile Training Program
A43: Beekeeping NC II - Mobile Training Program | B43: Foundry Melting/Casting NC II | D43: Heavy Equipment Operation (Rough Terrain Crane) NC III - Mobile Training Program | G43: Semiconductor Front-of-Line Operation NC II - Mobile Training Program | L43: Massage Therapy NC II - Mobile Training Program | P43: Machining NC II - Mobile Training Program | T43: Security Services NC II | U43: Local Guiding Services NC II
A44: Biogas Plant Installation NC III | B44: Foundry Melting/Casting NC II - Mobile Training Program | D44: Heavy Equipment Operation (Screed) NC I | G44: Maintain and Repair Computer Systems and Networks leading to Computer Systems Servicing NC II | L44: Ophthalmic Lens Services NC II | P44: Machining NC III | T44: Security Services NC II - Mobile Training Program | U44: Local Guiding Services NC II - Mobile Training Program
A45: Biogas Plant Installation NC III - Mobile Training Program | B45: Foundry Melting/Casting NC III | D45: Heavy Equipment Operation (Screed) NC I - Mobile Training Program | G45: Maintain and Repair Computer Systems and Networks leading to Computer Systems Servicing NC II - Mobile Training Program | L45: Ophthalmic Lens Services NC II - Mobile Training Program | P45: Machining NC III - Mobile Training Program | T45: Hair Coloring (Hair Dye) Leading to Hairdressing NC II | U45: Tour Guiding Services NC II (Amended)
A46: Drying and Milling Plant Servicing NC III | B46: Foundry Melting/Casting NC III - Mobile Training Program | D46: Heavy Equipment Operation (Tower Crane) NC III | G46: Mechatronics Device Configuration and Testing Leading to Mechatronics Servicing NC II | L46: Pharmacy Services NC III | P46: Manual Metal Arc Welding (MMAW) NC I | T46: Hair Coloring (Hair Dye) Leading to Hairdressing NC II - Mobile Training Program | U46: Tour Guiding Services NC III
A47: Drying and Milling Plant Servicing NC III - Mobile Training Program | B47: Foundry Molding NC II | D47: Heavy Equipment Operation (Tower Crane) NC III - Mobile Training Program | G47: Mechatronics Device Configuration and Testing Leading to Mechatronics Servicing NC II - Mobile Training Program | L47: Pharmacy Services NC III - Mobile Training Program | P47: Manual Metal Arc Welding (MMAW) NC I - Mobile Training Program | T47: Perform Pre and Post Beauty Care Services Leading to Beauty Care NC II | U47: Tour Guiding Services NC III - Mobile Training Program
A48: Fish Capture NC I | B48: Foundry Molding NC II - Mobile Training Program | D48: Heavy Equipment Operation (Transit Mixer) NC II | G48: Mechatronics Control Circuits and Software Application Programs Development Leading to Mechatronics Servicing NC III | L48: Community Nutrition Services NC II | P48: Manual Metal Arc Welding (MMAW) NC II | T48: Clean living room, dining room, bedroom, bathroom and kitchen Leading to Domestic Work NC II | U48: Tour Packaging (FIT AD HOC DOMESTIC) Services NC II
A49: Fish Capture NC I - Mobile Training Program | B49: Foundry Molding NC III | D49: Heavy Equipment Operation (Transit Mixer) NC II - Mobile Training Program | G49: Mechatronics Control Circuits and Software Application Programs Development Leading to Mechatronics Servicing NC III - Mobile Training Program | L49: Community Nutrition Services NC II - Mobile Training Program | P49: Manual Metal Arc Welding (MMAW) NC II - Mobile Training Program | T49: Early Childhood Care and Development Services NC III | U49: Tour Packaging (FIT AD HOC DOMESTIC) Services NC II - Mobile Training Program
A50: Fish Capture NC II | B50: Foundry Molding NC III - Mobile Training Program | D50: Heavy Equipment Operation (Truck Mounted Crane) NC III | P50: Manual Metal Arc Welding (MMAW) NC III | T50: Early Childhood Care and Development Services NC III - Mobile Training Program | U50: Tourism Promotion Services NC II
A51: Fish Capture NC II - Mobile Training Program | B51: Foundry Pattern Making NC II | D51: Heavy Equipment Operation (Truck Mounted Crane) NC III - Mobile Training Program | P51: Manual Metal Arc Welding (MMAW) NC III - Mobile Training Program | U51: Tourism Promotion Services NC II - Mobile Training Program
A52: Fishing Gear Repair and Maintenance NC III | B52: Foundry Pattern Making NC II - Mobile Training Program | D52: Heavy Equipment Operation (Wheel Loader) NC II | P52: Manual Metal Arc Welding (MMAW) NC IV | U52: Travel Services NC II
A53: Fishing Gear Repair and Maintenance NC III - Mobile Training Program | B53: Foundry Pattern Making NC III | D53: Heavy Equipment Operation (Wheel Loader) NC II - Mobile Training Program | P53: Manual Metal Arc Welding (MMAW) NC IV - Mobile Training Program | U53: Travel Services NC II - Mobile Training Program
A54: Fishport/Wharf Operation NC I | B54: Foundry Pattern Making NC III - Mobile Training Program | D54: Heavy Equipment Servicing (Mechanical) NC II | P54: Mechanical Drafting NC I | U54: Travel Services NC II (Superseded)
A55: Fishport/Wharf Operation NC I - Mobile Training Program | B55: Heat Treatment NC II | D55: Heavy Equipment Servicing (Mechanical) NC II - Mobile Training Program | P55: Mechanical Drafting NC I - Mobile Training Program | U55: Travel Services NC II (Superseded) - Mobile Training Program
A56: Grains Production NC II | B56: Heat Treatment NC II - Mobile Training Program | D56: Masonry NC I | P56: Mold Designing NC IV | U56: Prepare Sweets leading to Cookery NC II
A57: Grains Production NC II - Mobile Training Program | B57: Laboratory and Metrology/Calibration Services NC II | D57: Masonry NC I - Mobile Training Program | P57: Mold Designing NC IV - Mobile Training Program | U57: Prepare and Produce Bakery Products Leading to Bread and Pastry Production NC II
A58: Horticulture NC III | B58: Laboratory and Metrology/Calibration Services NC II - Mobile Training Program | D58: Masonry NC II | P58: Mold Making NC III
A59: Horticulture NC III - Mobile Training Program | B59: Laboratory and Metrology/Calibration Services NC III | D59: Masonry NC II - Mobile Training Program | P59: Mold Making NC III - Mobile Training Program
A60: Landscape Installation and Maintenance (Softscape) NC II | B60: Laboratory and Metrology/Calibration Services NC III - Mobile Training Program | D60: Masonry NC III | P60: Plant Maintenance NC I
A61: Landscape Installation and Maintenance (Softscape) NC II - Mobile Training Program | B61: Metal Stamping NC II | D61: Masonry NC III - Mobile Training Program | P61: Plant Maintenance NC I - Mobile Training Program
A62: Milking Operation NC II | B62: Metal Stamping NC II - Mobile Training Program | D62: Pipefitting (Metallic) NC II | P62: Press Machine Operation NC I
A63: Milking Operation NC II - Mobile Training Program | B63: Moldmaking NC II | D63: Pipefitting (Metallic) NC II - Mobile Training Program | P63: Press Machine Operation NC I - Mobile Training Program
A64: Organic Agriculture Production NC II | B64: Moldmaking NC II - Mobile Training Program | D64: Plumbing NC I | P64: Shielded Metal Arc Welding (SMAW) NC I
A65: Organic Agriculture Production NC II - Mobile Training Program | B65: Motorcycle/Small Engine Servicing NC II | D65: Plumbing NC I - Mobile Training Program | P65: Shielded Metal Arc Welding (SMAW) NC I - Mobile Training Program
A66: Pest Management (Vegetables) NC II | B66: Motorcycle/Small Engine Servicing NC II - Mobile Training Program | D66: Plumbing NC II | P66: Shielded Metal Arc Welding (SMAW) NC II
A67: Pest Management (Vegetables) NC II - Mobile Training Program | B67: Painting Machine Operation NC II | D67: Plumbing NC II - Mobile Training Program | P67: Shielded Metal Arc Welding (SMAW) NC II - Mobile Training Program
A68: Pressurized Irrigation System Installation and Maintenance NC II | B68: Painting Machine Operation NC II - Mobile Training Program | D68: Plumbing NC III | P68: Shielded Metal Arc Welding (SMAW) NC III
A69: Pressurized Irrigation System Installation and Maintenance NC II - Mobile Training Program | B69: Plastic Machine Operation NC II | D69: Plumbing NC III - Mobile Training Program | P69: Shielded Metal Arc Welding (SMAW) NC III - Mobile Training Program
... A77: Seaweed Production NC II - Mobile Training Program | B77: Speed Limitation Device Servicing NC II | D77: Reinforcing Steel Works NC II - Mobile Training Program | P77: Tool and Die Making NC II - Mobile Training Program
A78: Sugarcane Production NC II | B78: Speed Limitation Device Servicing NC II - Mobile Training Program | D78: Rigging NC I
A79: Sugarcane Production NC II - Mobile Training Program | B79: Tinsmithing (Automotive Manufacturing) NC II | D79: Rigging NC I - Mobile Training Program
A80: Support Agronomic Crop Work Leading to Agricultural Crops Production NC I | B80: Tinsmithing (Automotive Manufacturing) NC II - Mobile Training Program | D80: Scaffolding Works NC II (Supported Type Scaffold)
A81: Support Agronomic Crop Work Leading to Agricultural Crops Production NC I - Mobile Training Program | B81: Service Motorcycle/ Small Engine System Leading to Motorcycle/Small Engine Servicing NC II | D81: Scaffolding Works NC II (Supported Type Scaffold) - Mobile Training Program
A82: Support Horticultural Crop Work Leading to Agricultural Crops Production NC I | B82: Service Motorcycle/ Small Engine System Leading to Motorcycle/Small Engine Servicing NC II - Mobile Training Program | D82: Structural Erection NC II
A83: Support Horticultural Crop Work Leading to Agricultural Crops Production NC I - Mobile Training Program | B83: Automotive Servicing NC II (Superseded) - Mobile Training Program | D83: Structural Erection NC II - Mobile Training Program
A84: Support Irrigation Work Leading to Agricultural Crops Production NC I | B84: Service Automotive Electrical Component Leading to Automotive Servicing NC II | D84: System Formworks Installation NC II
A85: Support Irrigation Work Leading to Agricultural Crops Production NC I - Mobile Training Program | D85: System Formworks Installation NC II - Mobile Training Program
A86: Support Nursery Work Leading to Agricultural Crops Production NC I | D86: Technical Drafting NC II
A87: Support Nursery Work Leading to Agricultural Crops Production NC I - Mobile Training Program | D87: Technical Drafting NC II - Mobile Training Program
A88: Care and Maintain Crops Leading to Agricultural Crops Production NC II | D88: Tile Setting NC II
A89: Care and Maintain Crops Leading to Agricultural Crops Production NC II - Mobile Training Program | D89: Tile Setting NC II - Mobile Training Program
A90: Carry-out Harvest and Post-Harvest Operations Leading to Agricultural Crops Production NC II | D90: Draft Architectural Lay-out & Details Leading to Technical Drafting
A91: Carry-out Harvest and Post-Harvest Operations Leading to Agricultural Crops Production NC II - Mobile Training Program | D91: Draft Architectural Lay-out & Details Leading to Technical Drafting - Mobile Training Program
A92: Perform Nursery Operations Leading to Agricultural Crops Production NC II | D92: Draft Structural Lay-out & Details Leading to Technical Drafting
A93: Perform Nursery Operations Leading to Agricultural Crops Production NC II - Mobile Training Program | D93: Draft Structural Lay-out & Details Leading to Technical Drafting - Mobile Training Program
A94: Plant Crops Leading to Agricultural Crops Production NC II | D94: Heavy Equipment Operation (Truck Mounted Crane) NC II (Superseded)
A95: Plant Crops Leading to Agricultural Crops Production NC II - Mobile Training Program | D95: Heavy Equipment Operation (Crawler Crane) NC II (Superseded)
A96: Control Weeds Leading to Agricultural Crops Production NC III | D96: Heavy Equipment Operation (Rough Terrain Crane) NC II (Superseded)
... A99: Establish Agronomic Crops Leading to Agricultural Crops Production NC III - Mobile Training Program | D99: Heavy Equipment Operation (Rough Terrain Crane) NC II (Superseded) - Mobile Training Program
A100: Implement Plant Nutrition Program leading to Agricultural Crops Production NC III
A101: Implement Plant Nutrition Program leading to Agricultural Crops Production NC III - Mobile Training Program
A102: Implement Post-Harest Program Leading to Agricultural Crops Production NC III
A103: Implement Post-Harest Program Leading to Agricultural Crops Production NC III - Mobile Training Program
A104: Implement Vertebrate Pest Control Program Leading to Agricultural Crops Production NC III
A105: Implement Vertebrate Pest Control Program Leading to Agricultural Crops Production NC III - Mobile Training Program
A106: Prepare and Apply Chemicals Leading to Agricultural Crops Production NC III
A107: Prepare and Apply Chemicals Leading to Agricultural Crops Production NC III - Mobile Training Program
A108: Prepare Land for Agricultural Crop Production Leading to Agricultural Crop Production NC III
A109: Prepare Land for Agricultural Crop Production Leading to Agricultural Crop Production NC III - Mobile Training Program
A110: Undertake Agronomic Crop Maintenance Activities Leading to Agricultural Crops Production NC III
...

Sheet 2024 F08
A1: PROVINCE | B1: Name of TVI/Company (a) | C1: Qualification Title (b) | D1: Conducts Orientation on Program Registration (c) | E1: Conducts Site Inspection and Submitts Site Inspection Report (d) | F1: Reviews and Evaluates Program Registration Application Documents (Day 1) (e) | G1: Prepares Recommendation and Submits Complete Documents to RO (Day 2) (f) | H1: Transmits the Application Documents, and Recommendations to RO (1-2 days) (g) | I1: Approved/Disapproves Program Registration Application Documents and Issues/Transmits CTPR/Letter of Denial (Day 3) (h) | J1: Transmits the CTPR and Complete Documents to Provincial Office/TVIs and conducts Post Orientation (1-2 days) (i) | K1: TOTAL NUMBER OF DAYS (3 DAYS) | L1: RO REMARKS
A2: Cebu | B2: Don Bosco Technical Vocational Education & Training Center - Balamban, Inc. | C2: Electrical Installation and Maintenance NC II-MTP | D2: 45040 | E2: 45299 | F2: 45300 | G2: N/A | H2: N/A | I2: 45301 | J2: 45302
A3: Cebu | B3: Don Bosco Technical Vocational Education & Training Center - Balamban, Inc. | C3: Driving NC II-MTP | D3: 45040 | E3: 45299 | F3: 45300 | G3: N/A | H3: N/A | I3: 45301 | J3: 45302
A4: Cebu | B4: Don Bosco Technical Vocational Education & Training Center - Balamban, Inc. | C4: Shielded Metal Arc Welding (SMAW) NC I-MTP | D4: 45040 | E4: 45299 | F4: 45300 | G4: N/A | H4: N/A | I4: 45301 | J4: 45302
A5: Cebu | B5: Don Bosco Technical Vocational Education & Training Center - Balamban, Inc. | C5: Shielded Metal Arc Welding (SMAW) NC II-MTP | D5: 45040 | E5: 45299 | F5: 45300 | G5: N/A | H5: N/A | I5: 45301 | J5: 45302
A6: Cebu | B6: University of the Visayas, Inc. | C6: Hosuekeeping NC II-MTP | D6: 45040 | E6: 45267 | F6: 45301 | G6: N/A | H6: N/A | I6: 45302 | J6: 45303
A7: Cebu | B7: University of the Visayas, Inc. | C7: Food and Beverage Services NC II-MTP | D7: 45040 | E7: 45267 | F7: 45303 | G7: N/A | H7: N/A | I7: 45306 | J7: 45307
A8: Cebu | B8: Sto. Nino Skills Development and Assessment Center | C8: Hairdressing NC II-MTP | D8: 45030 | E8: 45306 | F8: 45308 | G8: N/A | H8: N/A | I8: 45309 | J8: 45310
A9: Cebu | B9: Sto. Nino Skills Development and Assessment Center | C9: Housekeeping NC II-MTP | D9: 45030 | E9: 45306 | F9: 45308 | G9: N/A | H9: N/A | I9: 45309 | J9: 45310
A10: Cebu | B10: 3A Prime Hospitality Trianing and Assessment Center Inc. | C10: Computer Systems Servicing NC II-MTP | D10: 45040 | E10: 45314 | F10: 45314 | G10: N/A | H10: N/A | I10: 45315 | J10: 45316
A11: Negros Oriental | B11: Sto. Nino Skills Training and Assessment Center | C11: Driving NC II-MTP | D11: 45040 | E11: 45308 | F11: 45316 | G11: N/A | H11: N/A | I11: 45317 | J11: 45320
A12: Cebu | B12: Primordial Training Center Inc. | C12: Hilot (Wellness Massage) NC II-MTP | D12: 45310 | E12: 45320 | F12: 45321 | G12: N/A | H12: N/A | I12: 45322 | J12: 45322
A13: Cebu | B13: Seabreeze Technical Education Training & Assessment Center Inc. | C13: Housekeeping NC II | D13: 45246 | E13: 45317 | F13: 45320 | G13: 45321 | H13: 45321 | I13: 45322 | J13: 45322
A14: Cebu | B14: Cebu Southwest Technical College, Inc. | C14: Shielded Metal Arc Welding (SMAW) NC I | D14: 45309 | E14: 45307 | F14: 45324 | G14: 45327 | H14: 45327 | I14: 45328 | J14: 45328
A15: Cebu | B15: Saint Homobonus Academy Inc. | C15: Contact Center Services NC II | D15: 45309 | E15: 45324 | F15: 45327 | G15: 45328 | H15: 45328 | I15: 46425 | J15: 45329
A16: Cebu | B16: Skillsbuild Training and Assessment Center, Corp | C16: Housekeeping NC II | D16: 45246 | E16: 45330 | F16: 45330 | G16: 45334 | H16: 45334 | I16: 45335 | J16: 45336
A17: Bohol | B17: Cloa Technical Institute | C17: Driving NC II | D17: 45019 | E17: 45331 | F17: 45334 | G17: 45335 | H17: 45335 | I17: 45336 | J17: 45336
A18: Bohol | B18: Cloa Technical Institute | C18: Driving (Articulated Vehicle) NC III | D18: 45019 | E18: 45331 | F18: 45334 | G18: 45335 | H18: 45335 | I18: 45336 | J18: 45336
A19: Bohol | B19: Cloa Technical Institute | C19: Heavy Equipment Operation (Rigid On-Highway Dump Truck) NC II | D19: 45019 | E19: 45331 | F19: 45334 | G19: 45335 | H19: 45335 | I19: 45336 | J19: 45336
A20: Bohol | B20: Cloa Technical Institute | C20: Heavy Equipment Operation (Transit Mixer) NC II | D20: 45019 | E20: 45331 | F20: 45334 | G20: 45335 | H20: 45335 | I20: 45336 | J20: 45336
A21: Cebu | B21: School of Knowledge for Industrial Labor, Leadership and Service Inc. | C21: Construction Painting NC II | D21: 44854 | E21: 45335 | F21: 45335 | G21: 45336 | H21: 45336 | I21: 45337 | J21: 45337
A22: Cebu | B22: School of Knowledge for Industrial Labor, Leadership and Service Inc. | C22: Emergency Medical Services NC II | D22: 44854 | E22: 45335 | F22: 45335 | G22: 45336 | H22: 45336 | I22: 45337 | J22: 45337
A23: Cebu | B23: School of Knowledge for Industrial Labor, Leadership and Service Inc. | C23: Masonry NC I | D23: 44854 | E23: 45335 | F23: 45335 | G23: 45336 | H23: 45336 | I23: 45337 | J23: 45337
A24: Negros Oriental | B24: Upfuture Technical Vocational Institute Inc. | C24: Scaffolding Works NC II (Supported Type Scaffold) | D24: 45215 | E24: 45327 | F24: 45336 | G24: 45336 | H24: 45336 | I24: 45337 | J24: 45338
A25: Negros Oriental | B25: Upfuture Technical Vocational Institute Inc. | C25: Electrical Installation and Maintenance NC II | D25: 45215 | E25: 45334 | F25: 45338 | G25: 45338 | H25: 45338 | I25: 45341 | J25: 45342
A26: Bohol | B26: Eastern Heights School of Excellence, Inc. | C26: Food and Beverage Services NC II-MTP | D26: 45030 | E26: 45323 | F26: 45341 | G26: N/A | H26: N/A | I26: 45342 | J26: 45343
A27: Cebu | B27: 3A Prime Hospitality Training and Assessment Center Inc.-Cebu City | C27: Bread and Pastry Production NC II-MTP | D27: 45030 | E27: 45347 | F27: 45341 | G27: N/A | H27: N/A | I27: 45342 | J27: 45343
A28: Cebu | B28: Provincial Training Center - Cebu (Daanbantayan) | C28: Trainers Methodology Level I (Trainer/Assessor) | D28: 44844 | E28: 45338 | F28: 45342 | G28: 45343 | H28: 45343 | I28: 45344 | J28: 45344
A29: Negros Oriental | B29: Armstrong Career and Technical Education Institute Inc. | C29: Organic Agriculture Production NC II | D29: 45139 | E29: 45330 | F29: 45343 | G29: 45343 | H29: 45343 | I29: 45344 | J29: 45345
A30: Bohol | B30: St. Pedro Calungsod College Inc. | C30: Electrical Installation and Maintenance NC II | D30: 44986 | E30: 45342 | F30: 45343 | G30: 45344 | H30: 45344 | I30: 45345 | J30: 45345
A31: Cebu | B31: Cebu Southwest Technical College Inc. | C31: Shielded Metal Arc Welding (SMAW) NC II-MTP | D31: 45030 | E31: 45344 | F31: 45345 | G31: N/A | H31: N/A | I31: 45348 | J31: 45349
A32: Cebu | B32: Metrologyx Training & Assessment Center Inc. | C32: Instrumentation and Control Servicing NC II-MTP | D32: 45303 | E32: 45330 | F32: 45349 | G32: N/A | H32: N/A | I32: 45350 | J32: 45351
A33: Cebu | B33: Metrologyx Training & Assessment Center Inc. | C33: Mechatronics Servicing NC II-MTP | D33: 45303 | E33: 45330 | F33: 45349 | G33: N/A | H33: N/A | I33: 45350 | J33: 45351
A34: Negros Oriental | B34: Upfuture Technical Vocational Institute Inc. | C34: Driving NC II | D34: 45215 | E34: 45344 | F34: 45349 | G34: 45350 | H34: 45350 | I34: 45351 | J34: 45351
A35: Bohol | B35: Provincial Training Center - Bilar | C35: Bread and Pastry Production NC II-MTP | D35: 45030 | E35: 45281 | F35: 45287 | G35: N/A | H35: N/A | I35: 45287 | J35: 45288
A36: Bohol | B36: Provincial Training Center - Bilar | C36: Cookery NC II-MTP | D36: 45030 | E36: 45281 | F36: 45287 | G36: N/A | H36: N/A | I36: 45287 | J36: 45288
A37: Bohol | B37: Provincial Training Center - Bilar | C37: Carpentry NC II-MTP | D37: 45030 | E37: 45281 | F37: 45287 | G37: N/A | H37: N/A | I37: 45287 | J37: 45288
A38: Cebu | B38: Hanas Training and Asssessment Center Incorporated | C38: Hilot (Wellness Massage) NC II | D38: 45309 | E38: 45352 | F38: 45352 | G38: 45355 | H38: 45355 | I38: 45356 | J38: 45356
A39: Cebu | B39: Hanas Training and Asssessment Center Incorporated | C39: Housekeeping NC II | D39: 45309 | E39: 45352 | F39: 45352 | G39: 45355 | H39: 45355 | I39: 45356 | J39: 45356
A40: Cebu | B40: R & K Watanabe Skills Training Institute Inc. | C40: Food and Beverage Services NC II | D40: 44706 | E40: 45322 | F40: 45355 | G40: 45356 | H40: 45356 | I40: 45357 | J40: 45357
A41: Bohol | B41: Eastern Heights School of Excellence Inc. | C41: Housekeeping NC II | D41: 45245 | E41: 45355 | F41: 45356 | G41: 45357 | H41: 45357 | I41: 45358 | J41: 45358
A42: Siquijor | B42: Lazi Technical Institute | C42: Agroentrepreneurship NC II | D42: 45352 | E42: 45363 | F42: 45363 | G42: 45364 | H42: 45364 | I42: 45365 | J42: 45365
A43: Bohol | B43: Treetopz Farm Escapade Diversified Farm | C43: Organic Agriculture Production NC II-MTP | D43: 45040 | E43: 45345 | F43: 45362 | G43: N/A | H43: N/A | I43: 45363 | J43: 45364
A44: Cebu | B44: 3A Prime Hospitality Training and Assessment Center Inc.-Cebu City | C44: Cookery NC II-MTP | D44: 45030 | E44: 45371 | F44: 45371 | G44: N/A | H44: N/A | I44: 45372 | J44: 45373
A45: Cebu | B45: Seabreeze Technical Education Training and Assessment Center Inc. | C45: Housekeeping NC II-MTP | D45: 45335 | E45: 45372 | F45: 45372 | G45: N/A | H45: N/A | I45: 45373 | J45: 45376
A46: Negros Oriental | B46: Silliman University | C46: Animal Production (Poultry-Chicken) NC II-MTP | D46: 45030 | E46: 45369 | F46: 45372 | G46: N/A | H46: N/A | I46: 45373 | J46: 45376
A47: Negros Oriental | B47: Silliman University | C47: Animal Production (Swine) NC II-MTP | D47: 45030 | E47: 45369 | F47: 45372 | G47: N/A | H47: N/A | I47: 45373 | J47: 45376
A48: Cebu | B48: Gentle Family Home Training Center Inc. | C48: Caregiving NC II-MTP | D48: 45040 | E48: 45373 | F48: 45376 | G48: N/A | H48: N/A | I48: 46472 | J48: 45378
A49: Negros Oriental | B49: LK Farms Assessment and Training Center Inc. | C49: Driving NC II | D49: 45208 | E49: 45369 | F49: 45376 | G49: 45376 | H49: 45376 | I49: 45377 | J49: 45378
A50: Cebu | B50: Provincial Training Center - Cebu (Carmen) | C50: Trainers Methodology Level I (Trainer/Assessor) | D50: 44984 | E50: 45370 | F50: 45373 | G50: 45376 | H50: 45376 | I50: 45377 | J50: 45377
A51: Negros Oriental | B51: World Maritime Academy & Training Center Inc. | C51: Hilot (Wellness Massage) NC II | D51: 45181 | E51: 45364 | F51: 45377 | G51: 45377 | H51: 45377 | I51: 45378 | J51: 45383
A52: Cebu | B52: Provincial Training Center - Cebu (Toledo) | C52: Bookkeeping NC III | D52: 45372 | E52: 45383 | F52: 45387 | G52: 45390 | H52: 45390 | I52: 45393 | J52: 45393
A53: Cebu | B53: Provincial Training Center - Cebu (Toledo) | C53: Trainers Methodology Level I (Trainer/Assessor) | D53: 45372 | E53: 45383 | F53: 45387 | G53: 45390 | H53: 45390 | I53: 45393 | J53: 45393
A54: Negros Oriental | B54: Silliman University | C54: Organic Agriculture Production NC II-MTP | D54: 45040 | E54: 45386 | F54: 45390 | G54: N/A | H54: N/A | I54: 45393 | J54: 45394
A55: Bohol | B55: CDS Capt. Dan Salas Training Center Inc. | C55: Computer Systems Servicing NC II | D55: 45337 | E55: 45387 | F55: 45390 | G55: 45391 | H55: 45391 | I55: 45393 | J55: 45393
A56: Cebu | B56: Mandaue City College Technological and Entrepreneurship Skills Training (MCCTEST) | C56: Hilot (Wellness Massage) NC II | D56: 45337 | E56: 45390 | F56: 45390 | G56: 45393 | H56: 45393 | I56: 45394 | J56: 45394
A57: Cebu | B57: P5 Assessment and Training Center, Inc. | C57: Bread and Pastry Production NC II | D57: 45036 | E57: 45387 | F57: 45393 | G57: 45394 | H57: 45394 | I57: 45397 | J57: 45397
A58: Cebu | B58: P5 Assessment and Training Center, Inc. | C58: Driving NC II | D58: 45036 | E58: 45387 | F58: 45393 | G58: 45394 | H58: 45394 | I58: 45397 | J58: 45397
A59: Cebu | B59: P5 Assessment and Training Center, Inc. | C59: Shielded Metal Arc Welding (SMAW) NC II | D59: 45036 | E59: 45387 | F59: 45393 | G59: 45394 | H59: 45394 | I59: 45397 | J59: 45397
A60: Cebu | B60: Intellisense Institute of Technology, Inc. | C60: Contact Center Services NC II | D60: 45064 | E60: 45391 | F60: 45393 | G60: 45394 | H60: 45394 | I60: 45397 | J60: 45397
A61: Siquijor | B61: CMC Institute of Business Management, Skills Training and Assessment Center Inc. | C61: Computer Systems Servicing NC II | D61: 45399 | E61: 45401 | F61: 45401 | G61: 45401 | H61: 45401 | I61: 45404 | J61: 45405
A62: Bohol | B62: St. Martha Skills Training and Assessment Center Inc. | C62: Bookkeeping NC III | D62: 45335 | E62: 45400 | F62: 45401 | G62: 45404 | H62: 45404 | I62: 45405 | J62: 45405
A63: Bohol | B63: St. Martha Skills Training and Assessment Center Inc. | C63: Massage Therapy NC II | D63: 45335 | E63: 45400 | F63: 45401 | G63: 45404 | H63: 45404 | I63: 45405 | J63: 45405
A64: Negros Oriental | B64: ZN Global Knowledge and Skills Inc. | C64: Hilot (Wellness Massage) NC II-MTP | E64: 45400 | F64: 45404 | G64: N/A | H64: N/A | I64: 45405 | J64: 45406
A65: Siquijor | B65: Provincial Training Center - Siquijor | C65: Tile Setting NC II | D65: 45393 | E65: 45401 | F65: 45404 | G65: 45405 | H65: 45405 | I65: 45406 | J65: 45406
A66: Negros Oriental | B66: Provincial Training Center - Dumaguete | C66: Bookkeeping NC III | D66: 45278 | E66: 45399 | F66: 45405 | G66: 45406 | H66: 45406 | I66: 45772 | J66: 45407
A67: Siquijor | B67: Provincial Training Center - Siquijor | C67: Shielded Metal Arc Welding (SMAW) NC I | D67: 45393 | E67: 45405 | F67: 45405 | G67: 45405 | H67: 45406 | I67: 45407 | J67: 45407
A68: Siquijor | B68: Provincial Training Center - Siquijor | C68: Shielded Metal Arc Welding (SMAW) NC II | D68: 45393 | E68: 45405 | F68: 45405 | G68: 45405 | H68: 45406 | I68: 45407 | J68: 45407
A69: Cebu | B69: St. Eufemia Skills Academy Inc. | C69: Electrical Installation and Maintenance NC II-MTP | D69: 45040 | E69: 45401 | F69: 45404 | G69: N/A | H69: N/A | I69: 45405 | J69: 45406
A70: Cebu | B70: St. Eufemia Skills Academy Inc. | C70: Shielded Metal Arc Welding (SMAW) NC I-MTP | D70: 45040 | E70: 45401 | F70: 45404 | G70: N/A | H70: N/A | I70: 45405 | J70: 45406
A71: Cebu | B71: St. Eufemia Skills Academy Inc. | C71: Shielded Metal Arc Welding (SMAW) NC II-MTP | D71: 45040 | E71: 45401 | F71: 45404 | G71: N/A | H71: N/A | I71: 45405 | J71: 45406
A72: Siquijor | B72: PSP Technological Institute Inc. | C72: Carpentry NC II | D72: 45419 | E72: 45421 | F72: 45421 | G72: 45421 | H72: 45421 | I72: 45422 | J72: 45425
A73: Cebu | B73: University of San Jose - Recoletos Inc. | C73: Emergency Medical Services NC II | D73: 44984 | E73: 45426 | F73: 45427 | G73: 45428 | H73: 45428 | I73: 45429 | J73: 45429
A74: Cebu | B74: CleverCare Training Center Inc. | C74: Caregiving NC II | D74: 45337 | E74: 45429 | F74: 45432 | G74: 45433 | H74: 45433 | I74: 45434 | J74: 45434
A75: Bohol | B75: Global Voyage Assessment and Learning Center Inc. | C75: Cookery NC II | D75: 45310 | E75: 45432 | F75: 45433 | G75: 45434 | H75: 45434 | I75: 45435 | J75: 45435
A76: Bohol | B76: Global Voyage Assessment and Learning Center Inc. | C76: Food and Beverage Services NC II | D76: 45310 | E76: 45432 | F76: 45433 | G76: 45434 | H76: 45434 | I76: 45435 | J76: 45435
A77: Cebu | B77: The Foundation for Professional Training, Inc. doing business under the names and styles of Anihan Technical School; Banilad Center for Professional Development; Habihan School; Manila Institute for Culinary Arts and Residential Services; and Punlaan School | C77: Contact Center Services NC II | D77: 44854 | E77: 45432 | F77: 45433 | G77: 45434 | H77: 45434 | I77: 45435 | J77: 45435
A78: Cebu | B78: Mandaue City College Technological and Entrepreneurial Skills Training (MCCTEST) Center | C78: bread and Pastry Production NC II | D78: 45337 | E78: 45436 | F78: 45436 | G78: 45439 | H78: 45439 | I78: 45440 | J78: 45440
A79: Cebu | B79: Mandaue City College Technological and Entrepreneurial Skills Training (MCCTEST) Center | C79: Electrical Installation and Maintenance NC II | D79: 45337 | E79: 45436 | F79: 45436 | G79: 45439 | H79: 45439 | I79: 45440 | J79: 45440
A80: Negros Oriental | B80: Aspire Learning English Institute Inc. | C80: English as a Second Language Beginner (A1 and A2) Level | D80: 45323 | E80: 45440 | F80: 45442 | G80: 45442 | H80: 45442 | I80: 45443 | J80: 45444
A81: Cebu | B81: University of San Jose Recoletos, Inc. | C81: Emergency Medical Services NC II-MTP | D81: 45436 | E81: 45448 | F81: 45448 | G81: N/A | H81: N/A | I81: 45449 | J81: 45450
A82: Negros Oriental | B82: Teamskills Technological Institute Inc. | C82: Barista NC II-MTP | D82: 45030 | E82: 45435 | F82: 45448 | G82: N/A | H82: N/A | I82: 45449 | J82: 45450
A83: Bohol | B83: Bohol English Study and Training Academy-BESTA Inc. | C83: English as a Second Language Beginner (A1 and A2) Level | D83: 45083 | E83: 45450 | F83: 45453 | G83: 45454 | H83: 45454 | I83: 45456 | J83: 45456
A84: Cebu | B84: Cebu Call Center Academy Inc. | C84: Computer Systems Servicing NC II-MTP | D84: 45429 | E84: 45454 | F84: 45454 | G84: N/A | H84: N/A | I84: 45456 | J84: 45457
A85: Cebu | B85: MICS Culinary Training Services Incorporated | C85: Bread and Pastry Production NC II-MTP | D85: 45439 | E85: 45456 | F85: 45461 | G85: N/A | H85: N/A | I85: 45462 | J85: 45463
A86: Cebu | B86: Arriba Technical Skills Training and Assessment Center Corp. | C86: Electrical Installation and Maintenance NC II | D86: 45367 | E86: 45440 | F86: 45464 | G86: 45467 | H86: 45467 | I86: 45468 | J86: 45468
A87: Bohol | B87: Bohol English Study and Training Academy-BESTA Inc. | C87: English as a Second Language Intermediate (B1 and B2) Level | D87: 45083 | E87: 45450 | F87: 45467 | G87: 45468 | H87: 45468 | I87: 45469 | J87: 45469
A88: Cebu | B88: Cebu Call Center Academy Inc. | C88: Social Media (Content Creator) PQF Leve III | D88: 45064 | E88: 45407 | F88: 45408 | G88: 45411 | H88: 45411 | I88: 45412 | J88: 45412
A89: Cebu | B89: Cebu Call Center Academy Inc. | C89: Data Analytics Level III | D89: 45064 | E89: 45407 | F89: 45408 | G89: 45411 | H89: 45411 | I89: 45412 | J89: 45412
A90: Cebu | B90: TechCity Academy School Institute Corporation | C90: Digital Marketing PQF Level III | D90: 45428 | E90: 45470 | F90: 45474 | G90: 45475 | H90: 45475 | I90: 45476 | J90: 45476
A91: Negros Oriental | B91: Aspire Learning English Institute, Inc. | C91: English as a Second Language Intermediate (B1 and B2) Level | D91: 45323 | E91: 45440 | F91: 45477 | G91: 45477 | H91: 45477 | I91: 45478 | J91: 45481
A92: Bohol | B92: Provincial Training Center - Bilar | C92: Trainers Methodology Level 1 (Trainer/Assessor) | D92: 45433 | E92: 45481 | F92: 45482 | G92: 45483 | H92: 45483 | I92: 45484 | J92: 45484
A93: Cebu | B93: Assemble Training and Assessment Center Inc. | C93: Housekeeping NC II | D93: 45463 | E93: 45485 | F93: 45488 | G93: 45488 | H93: 45488 | I93: 45489 | J93: 45490
A94: Bohol | B94: Bohol English Study and Training Academy-BESTA Inc. | C94: English as a Second Language Advamced (C1) Level | D94: 45083 | E94: 45450 | F94: 45491 | G94: 45492 | H94: 45492 | I94: 45495 | J94: 45495
A95: Cebu | B95: Anzas Global Education Inc. | C95: English as a Second Language Beginner (A1 and A2) Level | D95: 45160 | E95: 45497 | F95: 45497 | G95: 45498 | H95: 45498 | I95: 45499 | J95: 45499
A96: Negros Oriental | B96: Aspire Learning English Institute, Inc. | C96: English as a Second Language Advanced (C1) Level | D96: 45323 | E96: 45440 | F96: 45498 | G96: 45499 | H96: 45499 | I96: 45502 | J96: 45502
A97: Cebu | B97: Cebu Call Center Academy Inc. | C97: Contact Center Services NC II-MTP | D97: 45436 | E97: 45485 | F97: 45490 | G97: N/A | H97: N/A | I97: 45491 | J97: 45492
A98: Bohol | B98: Philippine Call Center Institute Inc. | C98: Computer Systems Servicing NC II | D98: 45432 | E98: 45475 | F98: 45503 | G98: 45504 | H98: 45504 | I98: 45505 | J98: 45505
A99: Cebu | B99: Cebu Southwest Technical College Inc. | C99: Shielded Metal Arc Welding (SMAW) NC I-MTP | D99: 45030 | E99: 45499 | F99: 45511 | G99: N/A | H99: N/A | I99: 45512 | J99: 45516
A100: Bohol | B100: Provincial Training Center - Tubigon | C100: Trainers Methodology Level I (Trainer/Assessor) | E100: 45509 | F100: 45510 | G100: 45511 | H100: 45511 | I100: 45512 | J100: 45512
...

Sheet 2025 F08
A1: PROVINCE | B1: Name of TVI/Company (a) | C1: Qualification Title (b) | D1: Conducts Orientation on Program Registration (c) | E1: Conducts Site Inspection and Submitts Site Inspection Report (d) | F1: Reviews and Evaluates Program Registration Application Documents (Day 1) (e) | G1: Prepares Recommendation and Submits Complete Documents to RO (Day 2) (f) | H1: Transmits the Application Documents, and Recommendations to RO (1-2 days) (g) | I1: Approved/Disapproves Program Registration Application Documents and Issues/Transmits CTPR/Letter of Denial (Day 3) (h) | J1: Transmits the CTPR and Complete Documents to Provincial Office/TVIs and conducts Post Orientation (1-2 days) (i) | K1: TOTAL NUMBER OF DAYS (3 DAYS) | L1: RO REMARKS
A2: Cebu | B2: Canetech Training and Assessment Center Inc. | C2: Hilot (Wellness Massage) NC II | D2: 45337 | E2: 45652 | F2: 45653 | G2: 45659 | H2: 45659 | I2: 45660 | J2: 45660
A3: Bohol | B3: CMC Institute of Business Management, Skills Training and Assessment Center Inc. | C3: Tourism Promotion Services NC II | D3: 45399 | E3: 45653 | F3: 45659 | G3: 45660 | H3: 45660 | I3: 45663 | J3: 45663
A4: Cebu | B4: Jacob Institute of Science and Technology Inc. | C4: Beauty Care (Nail Care) Services NC II | D4: 45463 | E4: 45663 | F4: 45664 | G4: 45665 | H4: 45665 | I4: 45666 | J4: 45666
A5: Cebu | B5: Jacob Institute of Science and Technology Inc. | C5: Hilot (Wellness Massage) NC II | D5: 45463 | E5: 45663 | F5: 45664 | G5: 45665 | H5: 45665 | I5: 45666 | J5: 45666
A6: Bohol | B6: TFK Elite 888 Corp. | C6: Organic Agriculture Production NC II | D6: 45491 | E6: 45667 | F6: 45670 | G6: 45671 | H6: 45671 | I6: 45672 | J6: 45672
A7: Cebu | B7: Sto. Niño Skills Development and Assessment Center Inc. | C7: Trainers Methodology Level I (Trainer/Assessor) | D7: 45575 | E7: 45668 | F7: 45670 | G7: 45671 | H7: 45671 | I7: 45672 | J7: 45672
A8: Cebu | B8: Arriba Technical Skills Training and Assessment Center Corp. | C8: Electrical Installation and Maintenance NC II-MTP | D8: 45636 | E8: 45672 | F8: 45672 | G8: N/A | H8: N/A | I8: 45673 | J8: 45674
A9: Negros Oriental | B9: Sto. Niño Skills Training & Assessment Center Incorporated | C9: Caregiving NC II-MTP | D9: 45040 | E9: 45652 | F9: 45673 | G9: N/A | H9: N/A | I9: 45674 | J9: 45677
A10: Bohol | B10: Collegio De Loboc | C10: Driving NC II | D10: 45615 | E10: 45674 | F10: 45677 | G10: 45678 | H10: 45678 | I10: 45679 | J10: 45679
A11: Cebu | B11: Regional Training Center - Cebu | C11: Digital Marketing Level III | D11: 45617 | E11: 45672 | F11: 45678 | G11: 45679 | H11: 45679 | I11: 45680 | J11: 45680
A12: Cebu | B12: Team AK English Inc. | C12: English as a Second Language Beginner (A1 and A2) Level | D12: 45518 | E12: 45680 | F12: 45687 | G12: 45688 | H12: 45688 | I12: 45691 | J12: 45691
A13: Siquijor | B13: Lazi Technical Institute | C13: Food and Beverage Services NC III | D13: 45659 | E13: 45666 | F13: 45692 | G13: 45692 | H13: 45692 | I13: 45693 | J13: 45694
A14: Cebu | B14: Uni Eco-Agri Farm Learning Institute, Inc. | C14: Organic Agriculture Production NC II-MTP | D14: 45645 | E14: 45695 | F14: 45698 | G14: N/A | H14: N/A | I14: 45699 | J14: 45700
A15: Cebu | B15: Sto. Niño Skills Development and Assessment Center Inc. | C15: Bread and Pastry Production NC II | D15: 45575 | E15: 45696 | F15: 45698 | G15: 45699 | H15: 45699 | I15: 45700 | J15: 45700
A16: Bohol | B16: Tagbilaran City College | C16: Events Management Services NC III | D16: 45546 | E16: 45699 | F16: 45700 | G16: 45701 | H16: 45701 | I16: 45702 | J16: 45702
A17: Cebu | B17: Crossxroad English Academy Corp. | C17: English as a Second Language Beginner (A1 and A2) Level | D17: 45568 | E17: 45700 | F17: 45700 | G17: 45701 | H17: 45701 | I17: 45336 | J17: 45336
A18: Negros Oriental | B18: Silliman University | C18: Agroentrepreneurship NC II | D18: 45572 | E18: 45701 | F18: 45701 | G18: 45702 | H18: 45702 | I18: 45705 | J18: 45705
A19: Negros Oriental | B19: Silliman University | C19: Trainers Methodology Level I (Trainer/Assessor) | D19: 45572 | E19: 45701 | F19: 45701 | G19: 45702 | H19: 45702 | I19: 45705 | J19: 45705
A20: Negros Oriental | B20: Silliman University | C20: Bookkeeping NC III | D20: 45572 | E20: 45701 | F20: 45702 | G20: 45705 | H20: 45705 | I20: 45706 | J20: 45706
A21: Cebu | B21: Saint Roch Institute Inc. | C21: Driving NC II | D21: 45649 | E21: 45706 | F21: 45707 | G21: 45707 | H21: 45707 | I21: 45708 | J21: 45709
A22: Cebu | B22: Saint Roch Institute Inc. | C22: Driving (Passenger Bus / Straight Truck) NC III | D22: 45649 | E22: 45706 | F22: 45707 | G22: 45707 | H22: 45707 | I22: 45708 | J22: 45709
A23: Cebu | B23: Zeo and Zoe Training and Assessment Center Inc. | C23: Shielded Metal Arc Welding (SMAW) NC I-MTP | D23: 45713 | E23: 45713 | F23: 45713 | G23: N/A | H23: N/A | I23: 45714 | J23: 45715
A24: Cebu | B24: Zeo and Zoe Training and Assessment Center Inc. | C24: Shielded Metal Arc Welding (SMAW) NC II-MTP | D24: 45713 | E24: 45713 | F24: 45713 | G24: N/A | H24: N/A | I24: 45714 | J24: 45715
A25: Cebu | B25: Can-Care Technical Vocational Education Training Assessment and Review Center Institute, Inc. | C25: Caregiving NC II | D25: 45568 | E25: 45694 | F25: 45713 | G25: 45714 | H25: 45714 | I25: 45715 | J25: 45715
A26: Negros Oriental | B26: Silliman University Farm | C26: Agroentrepreneurship NC II | D26: 45642 | E26: 45712 | F26: 45713 | G26: 45714 | H26: 45714 | I26: 45715 | J26: 45715
A27: Negros Oriental | B27: Silliman University Farm | C27: Animal Production (Poultry-Chicken) NC II | D27: 45642 | E27: 45712 | F27: 45713 | G27: 45714 | H27: 45714 | I27: 45715 | J27: 45715
A28: Negros Oriental | B28: Silliman University | C28: Events Management Services NC III | D28: 45642 | E28: 45712 | F28: 45713 | G28: 45714 | H28: 45714 | I28: 45715 | J28: 45715
A29: Cebu | B29: SMEA-AG Global Education Inc. | C29: English as a Second Language Beginner (A1 and A2) Level | D29: 45518 | E29: 45709 | F29: 45715 | G29: 45716 | H29: 45716 | I29: 45719 | J29: 45719
A30: Negros Oriental | B30: Silliman University Farm | C30: Animal Production (Swine) NC II | D30: 45642 | E30: 45713 | F30: 45715 | G30: 45716 | H30: 45716 | I30: 45719 | J30: 45719
A31: Negros Oriental | B31: Silliman University Farm | C31: Animal Production (Ruminants) NC II | D31: 45642 | E31: 45713 | F31: 45715 | G31: 45716 | H31: 45716 | I31: 45719 | J31: 45719
A32: Negros Oriental | B32: Silliman University Farm | C32: Organic Agriculture Production NC II | D32: 45642 | E32: 45713 | F32: 45715 | G32: 45716 | H32: 45716 | I32: 45719 | J32: 45719
A33: Cebu | B33: Skillsbuild Training and Assessment Center Corp. | C33: Housekeeping NC II-MTP | D33: 45699 | E33: 45716 | F33: 45719 | G33: N/A | H33: N/A | I33: 45720 | J33: 45721
A34: Bohol | B34: IWH Bohol Resort Corp. Doing Business Under the Name and Style of Best Western Plus the Ivywall Resort, Panglao | C34: Develop and Food Safety Program (Leading to Food Production (Professional Cookery) NC IV | D34: 45695 | E34: 45715 | F34: 45716 | G34: 45719 | H34: 45719 | I34: 45720 | J34: 45720 | M34: Industry
A35: Cebu | B35: Happy Learning Academy, Inc. | C35: English as a Second Language Intermediate (B1 and B2) Level | D35: 45518 | E35: 45720 | F35: 45720 | G35: 45721 | H35: 45721 | I35: 45722 | J35: 45722
A36: Cebu | B36: HNSA-TVET and Assessment Center Inc. | C36: Housekeeping NC II-MTP | D36: 45699 | E36: 45716 | F36: 45722 | G36: N/A | H36: N/A | I36: 45723 | J36: 45724
A37: Cebu | B37: JRJ Solution Enterprise | C37: Computer Security Incident Handling Level I | D37: 45708 | E37: 45721 | F37: 45721 | G37: 45722 | H37: 45722 | I37: 45723 | J37: 45723 | M37: Industry
A38: Cebu | B38: JRJ Solution Enterprise | C38: Cyber Riks Assessment Level III | D38: 45708 | E38: 45721 | F38: 45721 | G38: 45722 | H38: 45722 | I38: 45723 | J38: 45723 | M38: Industry
A39: Cebu | B39: JRJ Solution Enterprise | C39: Cyber Threat Mitigation Level II | D39: 45708 | E39: 45721 | F39: 45721 | G39: 45722 | H39: 45722 | I39: 45723 | J39: 45723 | M39: Industry
A40: Cebu | B40: JRJ Solution Enterprise | C40: Cyber Threat Intelligence Analysis Level III | D40: 45708 | E40: 45721 | F40: 45721 | G40: 45722 | H40: 45722 | I40: 45723 | J40: 45723 | M40: Industry
A41: Cebu | B41: JRJ Solution Enterprise | C41: Ethical Hacking Level IV | D41: 45708 | E41: 45721 | F41: 45721 | G41: 45722 | H41: 45722 | I41: 45723 | J41: 45723 | M41: Industry
A42: Cebu | B42: Stacktrek Enterprise Inc. | C42: Ensure Compliance with Data Privacy and Ethics | D42: 45708 | E42: 45723 | F42: 45723 | G42: 45723 | H42: 45723 | I42: 45726 | J42: 45727 | M42: Industry
A43: Cebu | B43: Stacktrek Enterprise Inc. | C43: Implement Basic Automation Techniques Using AI Tools | D43: 45708 | E43: 45723 | F43: 45723 | G43: 45723 | H43: 45723 | I43: 45726 | J43: 45727 | M43: Industry
A44: Cebu | B44: Stacktrek Enterprise Inc. | C44: Utilize Generative AI | D44: 45708 | E44: 45723 | F44: 45723 | G44: 45723 | H44: 45723 | I44: 45726 | J44: 45727 | M44: Industry
A45: Cebu | B45: Lamac Multipurpose Cooperative | C45: Driving NC II | D45: 45708 | E45: 45720 | F45: 45722 | G45: 45723 | H45: 45723 | I45: 45726 | J45: 45726
A46: Cebu | B46: Colimargo Agricultural and Technical Institute Inc. | C46: Agroentrepreneurship NC II | D46: 45649 | E46: 45723 | F46: 45726 | G46: 45727 | H46: 45727 | I46: 45728 | J46: 45728
A47: Cebu | B47: Colimargo Agricultural and Technical Institute Inc. | C47: Bookkeeping NC III | D47: 45649 | E47: 45723 | F47: 45726 | G47: 45727 | H47: 45727 | I47: 45728 | J47: 45728
A48: Cebu | B48: Maayo Hotels Corporation Doing business under the name/s and style/s of Maayo Hotel, Maayo Stay, Maayo Leisure Group and Homm Mandaue Cebu Hotel | C48: Prepare Food and Beverage Services to Customers in a Quick Service Restaurant (QSR) | D48: 45688 | E48: 45727 | F48: 45727 | G48: 45728 | H48: 45728 | I48: 45729 | J48: 45729
A49: Cebu | B49: AMATO IND OPC | C49: Create Garment Designs and Calculate and Procure Garment Materials Leading to Fashion Design (Apparel) NC III | D49: 45714 | E49: 45728 | F49: 45729 | G49: 45729 | H49: 45729 | I49: 45730 | J49: 45733
A50: Cebu | B50: AMATO IND OPC | C50: Supervise Garment Prototype Preparation and Mass Production and Evaluate Finished Product Leading to Fashion Design (Apparel) NC III | D50: 45714 | E50: 45728 | F50: 45729 | G50: 45729 | H50: 45729 | I50: 45730 | J50: 45733
A51: Cebu | B51: AMATO IND OPC | C51: Supervise Packaging & Dispatching of Finished Garment and Perform Promotional Activities for Fashion Products and/or Services Leading to Fashion Design (Apparel) NC III | D51: 45714 | E51: 45728 | F51: 45729 | G51: 45729 | H51: 45729 | I51: 45730 | J51: 45733
A52: Cebu | B52: Tsuneishi Technical Services (Phils.) Inc. | C52: Prepare Data Visualization Leading to Data Analytics Level III | D52: 45688 | E52: 45729 | F52: 45729 | G52: 45729 | H52: 45729 | I52: 45730 | J52: 45733
A53: Cebu | B53: Hotel, Resort & Restaurant Association of Cebu, Inc. | C53: Provide Food and Beverage Services to Guests Leading to Food and Beverage Services NC II | D53: 45688 | E53: 45729 | F53: 45729 | G53: 45729 | H53: 45729 | I53: 45730 | J53: 45733
A54: Cebu | B54: Mandaue Institute of Developing Skills, Inc. | C54: Bread and Pastry Production NC II-MTP | D54: 45720 | E54: 45729 | F54: 45729 | G54: N/A | H54: N/A | I54: 45730 | J54: 45733
A55: Cebu | B55: Happy Learning Academy, Inc. | C55: English as a Second Language Advanced (C1) Level | D55: 45518 | E55: 45728 | F55: 45728 | G55: 45729 | H55: 45729 | I55: 45730 | J55: 45730
A56: Cebu | B56: Empower U Edu Inc. | C56: Bookkeeping NC III | D56: 45708 | E56: 45706 | F56: 45729 | G56: 45730 | H56: 45730 | I56: 45733 | J56: 45733
A57: Cebu | B57: Empower U Edu Inc. | C57: Contact Center Services NC II | D57: 45708 | E57: 45706 | F57: 45729 | G57: 45730 | H57: 45730 | I57: 45733 | J57: 45733
A58: Cebu | B58: Empower U Edu Inc. | C58: Driving NC II | D58: 45708 | E58: 45706 | F58: 45729 | G58: 45730 | H58: 45730 | I58: 45733 | J58: 45733
A59: Cebu | B59: Empower U Edu Inc. | C59: Events Management Services NC III | D59: 45708 | E59: 45706 | F59: 45729 | G59: 45730 | H59: 45730 | I59: 45733 | J59: 45733
A60: Siquijor | B60: SBR Technical Education Training Center Inc. | C60: Heavy Equipment Operation (Hydraulic Excavator) NC II | D60: 45677 | E60: 45731 | F60: 45733 | G60: 45734 | H60: 45734 | I60: 45735 | J60: 45735
A61: Bohol | B61: Provincial Training Center - Bilar | C61: Process Foods by Salting, Curing and Smoking Leading to Food Processing NC II | D61: 45705 | E61: 45734 | F61: 45735 | G61: 45736 | H61: 45736 | I61: 45737 | J61: 45737
A62: Cebu | B62: Star Gate Global Education Inc. | C62: English as a Second Language Beginner (A1 and A2) Level | D62: 45737 | E62: 45730 | F62: 45737 | G62: 45740 | H62: 45740 | I62: 45741 | J62: 45741
A63: Cebu | B63: TMJ Technology Skills Training Institute and Assessment Center, Inc. | C63: Cyber Threat Monitoring Level I | D63: 45708 | E63: 45733 | F63: 45737 | G63: 45740 | H63: 45740 | I63: 45741 | J63: 45741
A64: Cebu | B64: TMJ Technology Skills Training Institute and Assessment Center, Inc. | C64: Cyber Threat Mitigation Level II | D64: 45708 | E64: 45733 | F64: 45737 | G64: 45740 | H64: 45740 | I64: 45741 | J64: 45741
A65: Cebu | B65: TMJ Technology Skills Training Institute and Assessment Center, Inc. | C65: Cyber Threat Intelligence Analysis Level III | D65: 45708 | E65: 45733 | F65: 45737 | G65: 45740 | H65: 45740 | I65: 45741 | J65: 45741
A66: Cebu | B66: Assemble Training and Assessment Center Inc. | C66: Dressmaking NC II-MTP | D66: 45700 | E66: 45722 | F66: 45744 | G66: N/A | H66: N/A | I66: 45747 | J66: 45749
A67: Cebu | B67: Assemble Training and Assessment Center Inc. | C67: Housekeeping NC II-MTP | D67: 45700 | E67: 45722 | F67: 45744 | G67: N/A | H67: N/A | I67: 45747 | J67: 45749
A68: Cebu | B68: College of Technological Sciences-Cebu, Inc. | C68: Automotive Servicing NC I | D68: 45708 | E68: 45721 | F68: 45743 | G68: 45744 | H68: 45744 | I68: 45747 | J68: 45747
A69: Cebu | B69: KM100 Skills and Training Center Inc. | C69: Contact Center Services NC II | D69: 45001 | E69: 45743 | F69: 45743 | G69: 45744 | H69: 45744 | I69: 45747 | J69: 45747
A70: Bohol | B70: Gazebo de Loondon Food House | C70: Coconut Production Level II | D70: 45596 | E70: 45744 | F70: 45747 | G70: 45749 | H70: 45749 | I70: 45750 | J70: 45750
A71: Cebu | B71: Center for Healthcare Professions Cebu, Inc. | C71: Tourism Promotion Services NC II | D71: 45649 | E71: 45721 | F71: 45749 | G71: 45750 | H71: 45750 | I71: 45751 | J71: 45751
A72: Cebu | B72: HNSA-TVET & Assessment Center Inc. | C72: Events Management Services NC III | D72: 45337 | E72: 45737 | F72: 45749 | G72: 45750 | H72: 45750 | I72: 45751 | J72: 45751
A73: Cebu | B73: Saint Homobonus Academy Inc. | C73: Hilot (Wellness Massage) NC II | D73: 45309 | E73: 45737 | F73: 45749 | G73: 45750 | H73: 45750 | I73: 45751 | J73: 45751
A74: Bohol | B74: Treetopz Farm Escapade Diversified Farm | C74: Agricultural Crops Production NC II | D74: 45672 | E74: 45758 | F74: 45761 | G74: 45762 | H74: 45762 | I74: 45763 | J74: 45763
A75: Bohol | B75: Gentle Family Home Training Center Inc. | C75: Caregiving NC II | D75: 45504 | E75: 45762 | F75: 45763 | G75: 45768 | H75: 45768 | I75: 45769 | J75: 45769
A76: Bohol | B76: Bow and Arrow Institute of Technology Inc. | C76: Organic Agriculture Production NC II | D76: 45685 | E76: 45772 | F76: 45775 | G76: 45776 | H76: 45776 | I76: 45777 | J76: 45777
A77: Cebu | B77: Pilipinas ang Galing Training and Assessment Center Inc. | C77: Shoemaking Level I | D77: 45736 | E77: 45772 | F77: 45772 | G77: 45775 | H77: 45775 | I77: 45776 | J77: 45776
A78: Cebu | B78: Emunah Computer Training Center Corp. | C78: Computer Systems Servicing NC II-MTP | D78: 45758 | E78: 45776 | F78: 45779 | G78: N/A | H78: N/A | I78: 45782 | J78: 45783
A79: Cebu | B79: Dew Pima Training and Assessment Center Inc. | C79: Computer Systems Servicing NC II | D79: 45648 | E79: 45751 | F79: 45779 | G79: 45782 | H79: 45782 | I79: 45783 | J79: 45783
A80: Bohol | B80: Don Alberto's Farm Rice-Based Farm | C80: Coconut Production Level II | D80: 45733 | E80: 45779 | F80: 45782 | G80: 45783 | H80: 45783 | I80: 45784 | J80: 45784
A81: Cebu | B81: Cebu Call Center Academy Inc. | C81: Cyber Threat Intelligence Analysis Level III | D81: 45064 | E81: 45783 | F81: 45783 | G81: 45784 | H81: 45784 | I81: 45785 | J81: 45785
A82: Cebu | B82: Cebu Call Center Academy Inc. | C82: Virtual Assistant Services Level III | D82: 45064 | E82: 45783 | F82: 45783 | G82: 45784 | H82: 45784 | I82: 45785 | J82: 45785
A83: Cebu | B83: Jacob Institute of Science and Technology Inc. | C83: Caregiving NC II | D83: 45463 | E83: 45737 | F83: 45784 | G83: 45785 | H83: 45785 | I83: 45786 | J83: 45786
A84: Cebu | B84: Jacob Institute of Science and Technology Inc. | C84: Local Guiding Services NC II | D84: 45463 | E84: 45737 | F84: 45784 | G84: 45785 | H84: 45785 | I84: 45786 | J84: 45786
A85: Cebu | B85: Jacob Institute of Science and Technology Inc. | C85: Tourism Promotion Services NC II | D85: 45463 | E85: 45737 | F85: 45784 | G85: 45785 | H85: 45785 | I85: 45786 | J85: 45786
A86: Cebu | B86: University of the Visayas, Inc. | C86: Cookery NC II | D86: 45519 | E86: 45761 | F86: 45784 | G86: 45785 | H86: 45785 | I86: 45786 | J86: 45786
A87: Cebu | B87: University of the Visayas, Inc. | C87: Events Management Services NC III | D87: 45519 | E87: 45761 | F87: 45784 | G87: 45785 | H87: 45785 | I87: 45786 | J87: 45786
A88: Cebu | B88: University of the Visayas, Inc. | C88: Front Office Services NC II | D88: 45519 | E88: 45761 | F88: 45784 | G88: 45785 | H88: 45785 | I88: 45786 | J88: 45786
A89: Cebu | B89: Regional Training Center - Cebu | C89: Bookkeeping NC III | D89: 45617 | E89: 45785 | F89: 45786 | G89: 45790 | H89: 45790 | I89: 45791 | J89: 45791
A90: Cebu | B90: First English G-Net, Inc. | C90: English as a Second Language Intermediate (B1 and B2) Level | D90: 45518 | E90: 45790 | F90: 45791 | G90: 45792 | H90: 45792 | I90: 45793 | J90: 45793
A91: Cebu | B91: Banana Kids Care Service Corp. under the name of BK Academy | C91: English as a Second Language Beginner (A1 and A2) Level | D91: 45736 | E91: 45790 | F91: 45791 | G91: 45792 | H91: 45792 | I91: 45793 | J91: 45793
A92: Cebu | B92: Jacob Institute of Science and Technology Inc. | C92: Beauty Care (Nail Care) Services NC II-MTP | D92: 45702 | E92: 45736 | F92: 45793 | G92: N/A | H92: N/A | I92: 45796 | J92: 45797
A93: Cebu | B93: Jacob Institute of Science and Technology Inc. | C93: Hilot (Wellness Massage) NC II-MTP | D93: 45702 | E93: 45736 | F93: 45793 | G93: N/A | H93: N/A | I93: 45796 | J93: 45797
A94: Negros Oriental | B94: Masters School of Maritime Studies Inc. | C94: Hilot (Wellness Massage) NC II | D94: 45644 | E94: 45784 | F94: 45795 | G94: 45796 | H94: 45796 | I94: 45797 | J94: 45797
A95: Negros Oriental | B95: Upfuture Technical Vocational Institute Inc. | C95: Carpentry NC II | D95: 45525 | E95: 45793 | F95: 45796 | G95: 45797 | H95: 45797 | I95: 45798 | J95: 45798
A96: Negros Oriental | B96: Guihulngan Satellite Skills Development Center | C96: Dressmaking NC II-MTP | D96: 45040 | E96: 45799 | F96: 45800 | G96: N/A | H96: N/A | I96: 45803 | J96: 45804
A97: Cebu | B97: Saint Peter Academy of Alegria Foundation Inc. | C97: Cookery NC II | D97: 45309 | E97: 45796 | F97: 45803 | G97: 45804 | H97: 45804 | I97: 45805 | J97: 45805
A98: Cebu | B98: Argao Seabreeze Technical Education Training and Assessment Center Inc. | C98: Hilot (Wellness Massage) NC II | D98: 45708 | E98: 45772 | F98: 45805 | G98: 45806 | H98: 45806 | I98: 45807 | J98: 45807
A99: Negros Oriental | B99: Upfuture Technical Vocational Institute Inc. | C99: Gas Metal Arc Welding (GMAW) NC II | D99: 45525 | E99: 45803 | F99: 45810 | G99: 45810 | H99: 45810 | I99: 45811 | J99: 45812
A100: Cebu | B100: Primetech Skills Institute Inc. | C100: Bread and Pastry Production NC II | D100: 45708 | E100: 45786 | F100: 45803 | G100: 45804 | H100: 45804 | I100: 45812 | J100: 45812 | L100: 5 working days to comply with the deficiencies
...

Sheet NEW 2025 F08
A1: Province | B1: Name of Applicant Institution (a) | C1: Qualification Title (b) | D1: Conducts Orientation to Applicant Institution/ Prospective Institution (c) | E1: Reviews and Check Program Registration Application Documents and Provision of Feedback to Applicant Institution (d) | F1: Conducts of Ocular Inspection/ Visitation and Preparation and Submission of Inspection Report (e) | G1: Conducts Evaluation of the completeness, correctness and validity of all program registration application documents (Day 1) (f) | H1: Prepares Recommendation and Submits Complete Documents to RO (Day 2) (g) | I1: Transmits the Application Documents, and Recommendations to RO (1-2 days) (h) | J1: Approves and Issuances of CTPR (Day 3) (i) | K1: Transmits approved documents and CTPR to applicant institution through PO/DO (1-2 days) (j) | L1: TOTAL NUMBER OF DAYS (3 DAYS) | M1: RO REMARKS
A2: Cebu | B2: Sidlakan Training Center Inc. | C2: Housekeeping NC II | D2: 45708 | F2: 45859 | G2: 45902 | H2: 45903 | I2: 45903 | J2: 45904 | K2: 45904
A3: Cebu | B3: EliteCraft Education Corp. | C3: Telecom OSP Installation (Fiber Optic Cable) NC II | D3: 45889 | E3: 45889 | F3: 45903 | G3: 45903 | H3: 45904 | I3: 45904 | J3: 45905 | K3: 45905
A4: Cebu | B4: St. Cecilia's College - Cebu, Inc. | C4: Driving NC II | D4: 45889 | E4: 45889 | F4: 45904 | G4: 45905 | H4: 45908 | I4: 45908 | J4: 45910 | K4: 45910
A5: Cebu | B5: St. Cecilia's College - Cebu, Inc. | C5: Electrical Installation and Maintenance NC II | D5: 45889 | E5: 45889 | F5: 45904 | G5: 45905 | H5: 45908 | I5: 45908 | J5: 45910 | K5: 45910
A6: Cebu | B6: Global Power Skills Development Center Inc. | C6: Housekeeping NC II-MTP | D6: 45051 | E6: 45860 | F6: 45884 | G6: 45911 | H6: N/A | I6: N/A | J6: 45912 | K6: 45915
A7: Cebu | B7: Cella English Academy Inc. | C7: English as as Second Language Beginner (A1 and A2) Level | D7: 45898 | E7: 45901 | F7: 45910 | G7: 45911 | H7: 45912 | I7: 45912 | J7: 45915 | K7: 45915
A8: Cebu | B8: Worldwide ESL Tutorial Academy Corp | C8: English as as Second Language Beginner (A1 and A2) Level | D8: 45898 | E8: 45901 | F8: 45910 | G8: 45911 | H8: 45912 | I8: 45912 | J8: 45915 | K8: 45915
A9: Cebu | B9: Balamban Extensive Skills Technology Inc. | C9: Agricultural Crops Production NC II | D9: 45889 | E9: 45908 | F9: 45912 | G9: 45915 | H9: 45916 | I9: 45916 | J9: 45917 | K9: 45917
A10: Cebu | B10: Balamban Extensive Skills Technology Inc. | C10: Computer Systems Servicing NC II | D10: 45889 | E10: 45908 | F10: 45912 | G10: 45915 | H10: 45916 | I10: 45916 | J10: 45917 | K10: 45917
A11: Cebu | B11: Balamban Extensive Skills Technology Inc. | C11: Dressmaking NC II | D11: 45889 | E11: 45908 | F11: 45912 | G11: 45915 | H11: 45916 | I11: 45916 | J11: 45917 | K11: 45917
A12: Cebu | B12: Opportunities Today Training and Assessment Center Inc. | C12: Bread and Pastry Production NC II-MTP | D12: 45589 | E12: 45889 | F12: 45917 | G12: 45917 | H12: N/A | I12: N/A | J12: 45918 | K12: 45919
A13: Cebu | B13: Opportunities Today Training and Assessment Center Inc. | C13: Cookery NC II-MTP | D13: 45589 | E13: 45889 | F13: 45917 | G13: 45917 | H13: N/A | I13: N/A | J13: 45918 | K13: 45919
A14: Cebu | B14: Dew Pima Training and Assessment Center | C14: Computer Systems Servicing NC II-MTP | D14: 45589 | E14: 45887 | F14: 45917 | G14: 45919 | H14: N/A | I14: N/A | J14: 45922 | K14: 45923
A15: Cebu | B15: GFG Assessment & Training Center Corp. | C15: Computer Systems Servicing NC II | D15: 45898 | E15: 45916 | F15: 45917 | G15: 45918 | H15: 45918 | I15: 45918 | J15: 45922 | K15: 45923
A16: Cebu | B16: GFG Assessment & Training Center Corp. | C16: Content Creation (Social Media) Level III | D16: 45898 | E16: 45916 | F16: 45917 | G16: 45918 | H16: 45918 | I16: 45918 | J16: 45922 | K16: 45923
A17: Cebu | B17: GFG Assessment & Training Center Corp. | C17: Cyber Threat Monitoring Level I | D17: 45898 | E17: 45916 | F17: 45917 | G17: 45918 | H17: 45918 | I17: 45918 | J17: 45922 | K17: 45923
A18: Cebu | B18: GFG Assessment & Training Center Corp. | C18: Data Analytics Level III | D18: 45898 | E18: 45916 | F18: 45917 | G18: 45918 | H18: 45918 | I18: 45918 | J18: 45922 | K18: 45923
A19: Cebu | B19: Opportunities Today Training and Assessment Center Inc. | C19: Computer Systems Servicing NC II | D19: 45889 | E19: 45908 | F19: 45922 | G19: 45923 | H19: 45924 | I19: 45924 | J19: 45925 | K19: 45925
A20: Negros Oriental | B20: RAMS Art Training and Assessment Center Inc. | C20: Bread and Pastry Production NC II-MTP | D20: 45040 | E20: 45881 | F20: 45912 | G20: 45926 | H20: N/A | I20: N/A | J20: 45929 | K20: 45930
A21: Negros Oriental | B21: RAMS Art Training and Assessment Center Inc. | C21: Bookkeeping NC III-MTP | D21: 45040 | E21: 45881 | F21: 45912 | G21: 45926 | H21: N/A | I21: N/A | J21: 45929 | K21: 45930
A22: Negros Oriental | B22: RAMS Art Training and Assessment Center Inc. | C22: Electrical Installation and Maintenance NC II-MTP | D22: 45040 | E22: 45881 | F22: 45912 | G22: 45926 | H22: N/A | I22: N/A | J22: 45929 | K22: 45930
A23: Cebu | B23: R & K Watanabe Skills Training Institute Inc. | C23: Food and Beverage Services NC II-MTP | D23: 45839 | E23: 45876 | F23: 45932 | G23: 45932 | H23: N/A | I23: N/A | J23: 45933 | K23: 45936
A24: Cebu | B24: Green International Technological College, Inc. doing business under the name and style of Green International Technological College | C24: English as a Second Language Beginner (A1 and A2) Level | D24: 45898 | E24: 45923 | F24: 45931 | G24: 45933 | H24: 45934 | I24: 45934 | J24: 45936 | K24: 45936
A25: Cebu | B25: N Blessing Infinite Education and Development Inc. | C25: Coconut Production Level II | D25: 45918 | E25: 45933 | F25: 45937 | G25: 45938 | H25: 45939 | I25: 45939 | J25: 45940 | K25: 45940
A26: Cebu | B26: KLN Skills & Management Training and Assessment Center, Inc. | C26: Computer Systems Servicing NC II | D26: 45898 | E26: 45937 | F26: 45938 | G26: 45939 | H26: 45940 | I26: 45940 | J26: 45943 | K26: 45943
A27: Cebu | B27: KLN Skills & Management Training and Assessment Center, Inc. | C27: Hilot (Wellness Massage) NC II | D27: 45898 | E27: 45898 | F27: 45929 | G27: 45938 | H27: 45938 | I27: 45939 | J27: 45939 | K27: 45940 | L27: 45940 | M27: 45940 | N27: 45940 | O27: 45943 | P27: 45944 | Q27: 45944
A28: Cebu | B28: Mantawi Technical Institute Inc. | C28: Digital Marketing Level III | D28: 45918 | E28: 45937 | F28: 45943 | G28: 45943 | H28: 45944 | I28: 45944 | J28: 45945 | K28: 45945
A29: Cebu | B29: Cebu Eastern College Inc. | C29: Cookery NC II | D29: 45898 | E29: 45933 | F29: 45945 | G29: 45945 | H29: 45946 | I29: 45946 | J29: 45947 | K29: 45947
A30: Cebu | B30: Cebu Eastern College Inc. | C30: Food and Beverage Services NC III | D30: 45889 | E30: 45936 | F30: 45945 | G30: 45945 | H30: 45946 | I30: 45946 | J30: 45947 | K30: 45947
A31: Cebu | B31: Cebu Eastern College Inc. | C31: Housekeeping NC II | D31: 45889 | E31: 45936 | F31: 45945 | G31: 45945 | H31: 45946 | I31: 45946 | J31: 45947 | K31: 45947
A32: Cebu | B32: Nexus Global Techvoc Solutions Inc. | C32: Heavy Equipment Operation (Forklift) NC II | D32: 45889 | E32: 45939 | F32: 45944 | G32: 45947 | H32: 45950 | I32: 45950 | J32: 45951 | K32: 45951
A33: Cebu | B33: Lyceum of Cebu, Inc. | C33: Bread and Pastry Production NC II | D33: 45898 | E33: 45933 | F33: 45940 | G33: 45947 | H33: 45950 | I33: 45950 | J33: 45951 | K33: 45951
A34: Cebu | B34: Lyceum of Cebu, Inc. | C34: Bookkeeping NC III | D34: 45898 | E34: 45936 | F34: 45943 | G34: 45947 | H34: 45950 | I34: 45950 | J34: 45951 | K34: 45951
A35: Cebu | B35: Lyceum of Cebu, Inc. | C35: Events Management Services NC III | D35: 45898 | E35: 45936 | F35: 45943 | G35: 45947 | H35: 45950 | I35: 45950 | J35: 45951 | K35: 45951
A36: Cebu | B36: Lyceum of Cebu, Inc. | C36: Cooperative Development Management Level IV | D36: 45898 | E36: 45936 | F36: 45944 | G36: 45947 | H36: 45950 | I36: 45950 | J36: 45951 | K36: 45951
A37: Cebu | B37: Balamban Extensive Skills and Technology Inc. | C37: Trainers Methodology Level (Trainer/Assessor) | D37: 45889 | E37: 45936 | F37: 45936 | G37: 45940 | H37: 45940 | I37: 45951 | J37: 45951 | K37: 45952
A38: Cebu | B38: Hanas Training and Assessment Center Inc. | C38: Hilot (Wellness Massage) NC II-MTP | D38: 45889 | E38: 45929 | F38: 45954 | G38: 45957 | H38: N/A | I38: N/A | J38: 45958 | K38: 45959
A39: Bohol | B39: Philippine School of Healthcare Professions Inc. | C39: Food and Beverage Services NC II | D39: 45923 | E39: 45916 | F39: 45954 | G39: 45957 | H39: 47054 | I39: 47054 | J39: 45959 | K39: 45959
A40: Cebu | B40: Technical Training Center of South Cebu, Inc. | C40: Heavy Equipment Operation (Hydraulic Excavator) NC II | D40: 45918 | E40: 45950 | F40: 45954 | G40: 45957 | H40: 45958 | I40: 45958 | J40: 45959 | K40: 45959
A41: Cebu | B41: Technical Training Center of South Cebu, Inc. | C41: Heavy Equipment Operation (Forklift) NC II | D41: 45918 | E41: 45950 | F41: 45954 | G41: 45957 | H41: 45958 | I41: 45958 | J41: 45959 | K41: 45959
A42: Cebu | B42: Worldwide ESL Tutorial Academy Corp. | C42: English as a Second Language Intermediate (B1 and B2) Level | D42: 45898 | E42: 45950 | F42: 45957 | G42: 45957 | H42: 45958 | I42: 45958 | J42: 45959 | K42: 45959
A43: Cebu | B43: Bacalso Academy Inc. | C43: Health Care Services NC II | D43: 45946 | E43: 45853 | F43: 45937 | G43: 45939 | H43: 45954 | I43: 45959 | J43: 45959 | K43: 45960
A44: Bohol | B44: CMC Institute of Business Management, Skills Training and Assessment Center Inc. | C44: Front Office Services NC II | D44: 45803 | E44: 45947 | F44: 45961 | G44: 45964 | H44: 45966 | I44: 45966 | J44: 45967 | K44: 45968
A45: Bohol | B45: SBR Technical Education Training Center Inc. | C45: Heavy Equipment Operation (Hydraulic Excavator) NC II | D45: 45898 | E45: 45902 | F45: 45960 | G45: 45964 | H45: 45966 | I45: 45966 | J45: 45967 | K45: 45968
A46: Negros Oriental | B46: Integrated Development Training and Assessment Center Inc. | C46: Agroentrepreneurship NC II-MTP | D46: 45715 | E46: 45881 | F46: 45924 | G46: 45967 | H46: N/A | I46: N/A | J46: 45968 | K46: 45971
A47: Negros Oriental | B47: Integrated Development Training and Assessment Center Inc. | C47: Bookkeeping NC III-MTP | D47: 45715 | E47: 45881 | F47: 45924 | G47: 45967 | H47: N/A | I47: N/A | J47: 45968 | K47: 45971
A48: Negros Oriental | B48: Integrated Development Training and Assessment Center Inc. | C48: Driving NC II-MTP | D48: 45715 | E48: 45881 | F48: 45924 | G48: 45967 | H48: N/A | I48: N/A | J48: 45968 | K48: 45971
A49: Cebu | B49: Worldwide ESL Tutorial Academy Corp. | C49: English as a Second Language Advanced (C1) Level | D49: 45898 | E49: 45961 | F49: 45967 | G49: 45967 | H49: 45968 | I49: 45968 | J49: 45971 | K49: 45972
A50: Siquijor | B50: Elnard Integrated Farm | C50: Agroentrepreneurship NC II | D50: 45933 | E50: 45959 | F50: 45967 | G50: 45973 | H50: 45974 | I50: 45974 | J50: 45975 | K50: 45978
A51: Cebu | B51: Assemble Training and Assessment Center Inc. | C51: Caregiving NC II | F51: 45960 | G51: 45974 | H51: 45975 | I51: 45975 | J51: 45978 | K51: 45979
A52: Cebu | B52: 3A Prime Hospitality Training and Assessment Center Inc. | C52: Trainers Methodology Level I (Trainer/Assessor) | D52: 45889 | E52: 45895 | F52: 45958 | G52: 45978 | H52: 45979 | I52: 45979 | J52: 45980 | K52: 45981
A53: Negros Oriental | B53: Metrologyx Training and Assessment Center Inc. Doing business under the name/s and style/s of Metrologyx Institute of Technology (MIT) | C53: Mechatronics Servicing NC II | D53: 45971 | E53: 45967 | F53: 45975 | G53: 45980 | H53: 45981 | I53: 45981 | J53: 45982 | K53: 45985
A54: Cebu | B54: Philasia Maritime Services Training Center Inc. | C54: Ship' Catering Services NC I | D54: 45889 | E54: 45972 | F54: 45979 | G54: 45981 | H54: 45982 | I54: 45982 | J54: 45985 | K54: 45986
A55: Cebu | B55: Provincial Training Center - Cebu (Daanbantayan) | C55: Agroentrepreneurship NC II-MTP | D55: 45771 | E55: 45946 | F55: 45982 | G55: 45982 | H55: N/A | I55: N/A | J55: 45985 | K55: 45986
A56: Cebu | B56: ABQ International Health Caregiver Program & Consultancy, Inc. | C56: Hilot (Wellness Massage) NC II-MTP | D56: 45030 | E56: 45973 | F56: 45985 | G56: 45985 | H56: N/A | I56: N/A | J56: 45986 | K56: 45987
A57: Bohol | B57: Provincial Training Center - Tubigon | C57: Driving NC II - MTP | D57: 45040 | E57: 45959 | F57: 45979 | G57: 45987 | H57: N/A | I57: N/A | J57: 45988 | K57: 45989
A58: Bohol | B58: Provincial Training Center - Tubigon | C58: Masonry NC II - MTP | D58: 45040 | E58: 45959 | F58: 45979 | G58: 45987 | H58: N/A | I58: N/A | J58: 45988 | K58: 45989
A59: Bohol | B59: CMC Institute of Business Management, Skills Training and Assessment Center Inc. | C59: Early Childhood Care Development Services NC III | D59: 45803 | E59: 45978 | F59: 45986 | G59: 45987 | H59: 45988 | I59: 45988 | J59: 45989 | K59: 45992
A60: Bohol | B60: SBR Technical Education Training Center Inc. | C60: Heavy Equipment Operation (Forklift) NC II | D60: 45878 | E60: 45954 | F60: 45987 | G60: 45988 | H60: 45989 | I60: 45989 | J60: 45992 | K60: 45993
A61: Cebu | B61: St. Isidore Labrador Child Development Center, Inc. | C61: Bread and Pastry Production NC II | D61: 45898 | E61: 45980 | F61: 45982 | G61: 45988 | H61: 45989 | I61: 45989 | J61: 45992 | K61: 45993
A62: Cebu | B62: St. Isidore Labrador Child Development Center, Inc. | C62: Driving NC II | D62: 45898 | E62: 45980 | F62: 45982 | G62: 45988 | H62: 45989 | I62: 45989 | J62: 45992 | K62: 45993
A63: Cebu | B63: St. Isidore Labrador Child Development Center, Inc. | C63: Shielded Metal Arc Welding (SMAW) NC I | D63: 45898 | E63: 45980 | F63: 45982 | G63: 45988 | H63: 45989 | I63: 45989 | J63: 45992 | K63: 45993
A64: Cebu | B64: St. Isidore Labrador Child Development Center, Inc. | C64: Shielded Metal Arc Welding (SMAW) NC II | D64: 45898 | E64: 45980 | F64: 45982 | G64: 45988 | H64: 45989 | I64: 45989 | J64: 45992 | K64: 45993
A65: Cebu | B65: Provincial Training Center - Cebu (Daanbantayan) | C65: Agroentrepreneurship NC III | D65: 45918 | E65: 45980 | F65: 45982 | G65: 45995 | H65: 45996 | I65: 45996 | J65: 46000 | K65: 46001
A66: Negros Oriental | B66: Southern Tech College Foundation Incorporated | C66: Bookkeeping NC III-MTP | D66: 45040 | E66: 45881 | F66: 45964 | G66: 46000 | H66: N/A | I66: N/A | J66: 46001 | K66: 46002
A67: Negros Oriental | B67: Southern Tech College Foundation Incorporated | C67: Bookkeeping NC III-MTP | D67: 45040 | E67: 45881 | F67: 45964 | G67: 46000 | H67: N/A | I67: N/A | J67: 46001 | K67: 46002
A68: Negros Oriental | B68: Sto. Nino Skills Training & Assessment Center Incorporated | C68: Agroentrepreneurship NC II-MTP | D68: 45040 | E68: 45881 | F68: 45938 | G68: 46000 | H68: N/A | I68: N/A | J68: 46001 | K68: 46002
A69: Negros Oriental | B69: Teamskills Technological Institute Inc. | C69: Trainers Methodology Level I (Trainer/Assessor) - MTP | D69: 45040 | E69: 45943 | F69: 45973 | G69: 46000 | H69: N/A | I69: N/A | J69: 46001 | K69: 46002
A70: Cebu | B70: School of Knoweldge for Industrial Labor, Leadership and Service Inc. | C70: Carpentry NC III | D70: 45918 | E70: 45971 | F70: 45974 | G70: 46000 | H70: 46001 | I70: 46001 | J70: 46002 | K70: 46003
A71: Cebu | B71: School of Knoweldge for Industrial Labor, Leadership and Service Inc. | C71: Masonry NC III | D71: 45918 | E71: 45973 | F71: 45973 | G71: 46000 | H71: 46001 | I71: 46001 | J71: 46002 | K71: 46003
A72: Cebu | B72: School of Knoweldge for Industrial Labor, Leadership and Service Inc. | C72: Heavy Equipment Operation (Forklift) NC II | D72: 45918 | E72: 45971 | F72: 45974 | G72: 46000 | H72: 46001 | I72: 46001 | J72: 46002 | K72: 46003
A73: Cebu | B73: School of Knoweldge for Industrial Labor, Leadership and Service Inc. | C73: Heavy Equipment Operation (Rough Terrain Crane) NC III | D73: 45918 | E73: 45971 | F73: 45974 | G73: 46000 | H73: 46001 | I73: 46001 | J73: 46002 | K73: 46003
A74: Cebu | B74: School of Knoweldge for Industrial Labor, Leadership and Service Inc. | C74: Heavy Equipment Operation (Tower Crane) NC III | D74: 45918 | E74: 45971 | F74: 45974 | G74: 46000 | H74: 46001 | I74: 46001 | J74: 46002 | K74: 46003
A75: Cebu | B75: School of Knoweldge for Industrial Labor, Leadership and Service Inc. | C75: Plumbing NC III | D75: 45918 | E75: 45971 | F75: 45974 | G75: 46000 | H75: 46001 | I75: 46001 | J75: 46002 | K75: 46003
A76: Cebu | B76: Jedam Academy English Language, Inc. | C76: English as a Second Language Beginner (A1 and A2) Level | D76: 45918 | E76: 45996 | F76: 46000 | G76: 46000 | H76: 46001 | I76: 46001 | J76: 46002 | K76: 46003
A77: Bohol | B77: Provincial Training Center - Bilar | C77: Early Childhood Care and Development Services NC III-MTP | D77: 45040 | E77: 45994 | F77: 46002 | G77: 46002 | H77: N/A | I77: N/A | J77: 46003 | K77: 46006
A78: Bohol | B78: Provincial Training Center - Jagna | C78: Shielded Metal Arc Welding (SMAW) NC II-MTP | D78: 45040 | E78: 45993 | F78: 46002 | G78: 46002 | H78: N/A | I78: N/A | J78: 46003 | K78: 46006
A79: Bohol | B79: Provincial Training Center - Pilar | C79: Bread and Pastry Production NC II-MTP | D79: 45040 | E79: 45992 | F79: 46002 | G79: 46002 | H79: N/A | I79: N/A | J79: 46003 | K79: 46006
A80: Bohol | B80: Provincial Training Center - Pilar | C80: Electrical Installation and Maintenance NC III-MTP | D80: 45040 | E80: 45992 | F80: 46002 | G80: 46002 | H80: N/A | I80: N/A | J80: 46003 | K80: 46006
A81: Siquijor | B81: Lazi Technical Institute | C81: Establish Agronomic Crops Leading to Agricultural Crops Production NC III | D81: 45988 | E81: 45987 | F81: 46002 | G81: 46002 | H81: 46002 | I81: 46002 | J81: 46003 | K81: 46006
A82: Siquijor | B82: Lazi Technical Institute | C82: Implement Post-harvest Program Leading to Agricultural Crops Production NC III | D82: 45988 | E82: 45987 | F82: 46002 | G82: 46002 | H82: 46002 | I82: 46002 | J82: 46003 | K82: 46006
A83: Cebu | B83: Armson Polytechnic Institute Inc. | C83: Hilot (Wellness Massage) NC II-MTP | D83: 45589 | E83: 45960 | F83: 46003 | G83: 46003 | H83: N/A | I83: N/A | J83: 46006 | K83: 46007
A84: Cebu | B84: Provincial Training Center - Cebu (Samboan) | C84: Entrepreneurship PQF Level IV | D84: 45946 | E84: 45964 | F84: 46001 | G84: 46002 | H84: 46003 | I84: 46003 | J84: 46006 | K84: 46007
A85: Cebu | B85: Three H Redwood International School, Inc. | C85: Early Childhood Care and Development Services NC III | D85: 45981 | E85: 45996 | F85: 46000 | G85: 46006 | H85: 46007 | I85: 46007 | J85: 46008 | K85: 46009
A86: Cebu | B86: TMJ Technology Skills Training Institute and Assessment Center, Inc. | C86: Trainers Methodology Level I (Trainer/Assessor) | D86: 45981 | E86: 45996 | F86: 46006 | G86: 46006 | H86: 46007 | I86: 46007 | J86: 46008 | K86: 46009
A87: Negros Oriental | B87: We Will Learn Languages, Inc. | C87: English as a Second Language Beginner (A1 and A2) Level | D87: 45967 | E87: 45978 | F87: 45993 | G87: 46007 | H87: 46008 | I87: 46008 | J87: 46009 | K87: 46010
A88: Cebu | B88: BIG Dev't Training & Assessment Center, Inc. | C88: Beauty Care (Nail Care) Services NC II-MTP | D88: 45947 | E88: 45974 | F88: 46009 | G88: 46009 | H88: N/A | I88: N/A | J88: 46010 | K88: 46013
A89: Negros Oriental | B89: Evolve Learning Center Corp. | C89: Computer Systems Servicing NC II | D89: 45968 | E89: 45968 | F89: 45994 | G89: 46008 | H89: 46009 | I89: 46009 | J89: 46010 | K89: 46013
A90: Cebu | B90: Provincial Training Center - Cebu (Minglanilla) | C90: Bookkeeping NC III | D90: 45981 | E90: 45981 | F90: 46000 | G90: 46001 | H90: 46002 | I90: 46002 | J90: 46010 | K90: 46013 | M90: with 5 working days to comply
A91: Bohol | B91: Provincial Training Center - Inabanga | C91: Electrical Installation and Maintenance NC III-MTP | D91: 45040 | E91: 46003 | F91: 46007 | G91: 46009 | H91: N/A | I91: N/A | J91: 46010 | K91: 46013
A92: Bohol | B92: Provincial Training Center - Inabanga | C92: Shielded Metal Arc Welding (SMAW) NC III-MTP | D92: 45040 | E92: 46003 | F92: 46007 | G92: 46009 | H92: N/A | I92: N/A | J92: 46010 | K92: 46013
A93: Bohol | B93: Provincial Training Center - Inabanga | C93: Early Childhood Care and Development Services NC III | D93: 45978 | E93: 45993 | F93: 46008 | G93: 46009 | H93: 46010 | I93: 46010 | J93: 46013 | K93: 46014
A94: Bohol | B94: Provincial Training Center - Jagna | C94: Early Childhood Care and Development Services NC III | D94: 45978 | E94: 46003 | F94: 46008 | G94: 46009 | H94: 46010 | I94: 46010 | J94: 46013 | K94: 46014
A95: Bohol | B95: Provincial Training Center - Pilar | C95: Early Childhood Care and Development Services NC III | D95: 45978 | E95: 46002 | F95: 46008 | G95: 46009 | H95: 46010 | I95: 46010 | J95: 46013 | K95: 46014
A96: Bohol | B96: Provincial Training Center - Tubigon | C96: Early Childhood Care and Development Services NC III | D96: 45978 | E96: 45995 | F96: 46008 | G96: 46009 | H96: 46010 | I96: 46010 | J96: 46013 | K96: 46014
A97: Cebu | B97: Oriental Capital Holdings, Inc. | C97: Perform Productive Operation for Container Stacker using Ship to Shore (Quay) Crane | D97: 45852 | E97: 45996 | F97: 46009 | G97: 46009 | H97: 46010 | I97: 46010 | J97: 46013 | K97: 46014
A98: Negros Oriental | B98: Provincial Training Center - Dumaguete | C98: Agroentrepreneurship NC III | D98: 45972 | E98: 45987 | F98: 46005 | G98: 46013 | H98: 46013 | I98: 46013 | J98: 46014 | K98: 46017
A99: Negros Oriental | B99: Provincial Training Center - Dumaguete | C99: Events Management Services NC III | D99: 45972 | E99: 45987 | F99: 46005 | G99: 46013 | H99: 46013 | I99: 46013 | J99: 46014 | K99: 46017
A100: Bohol | B100: CMC Institute of Business Management, Skills Training and Assessment Center Inc. | C100: Tourism Promotion Services NC II-MTP | D100: 45803 | E100: 46003 | F100: 46007 | G100: 46013 | H100: N/A | I100: N/A | J100: 46014 | K100: 46017
...

Sheet UIID
A1: REGION | B1: PROVINCE | C1: CONGRESSIONAL DISTRICT | D1: Municipality | E1: Municipality Class | F1: Unique Instittution Identification | G1: NAME OF INSTITUTION | H1: ADDRESS | I1: Region_Province Code | J1: SEQUENCE NUMBER | K1: UIID | L1: TVI STATUS
A2: VII | B2: Bohol | C2: 1st | D2: Tubigon | E2: 1st | G2: Provincial Training Center - Tubigon | H2: Potohan, Tubigon, Bohol | I2: 712 | J2: 1 | K2: =CONCATENATE(TEXT(I2,"0000"),"-",TEXT(J2,"0000")) -> 0712-0001
A3: VII | B3: Bohol | C3: 2nd | D3: Ubay | E3: 1st | G3: Bohol Northern Star College, Inc. | H3: Poblacion, Ubay, Bohol | I3: 712 | J3: 2 | K3: =CONCATENATE(TEXT(I3,"0000"),"-",TEXT(J3,"0000")) -> 0712-0002
A4: VII | B4: Bohol | C4: 3rd | D4: Bilar | E4: 4th | G4: Provincial Training Center - Bilar | H4: Poblacion, Bilar, Bohol | I4: 712 | J4: 3 | K4: =CONCATENATE(TEXT(I4,"0000"),"-",TEXT(J4,"0000")) -> 0712-0003
A5: VII | B5: Bohol | C5: 2nd | D5: Inabanga | E5: 3rd | G5: Provincial Training Center - Inabanga | H5: Cagayan, Inabanga, Bohol | I5: 712 | J5: 4 | K5: =CONCATENATE(TEXT(I5,"0000"),"-",TEXT(J5,"0000")) -> 0712-0004
A6: VII | B6: Bohol | C6: 3rd | D6: Pilar | E6: 4th | G6: Provincial Training Center - Pilar | H6: Poblacion, Pilar, Bohol | I6: 712 | J6: 5 | K6: =CONCATENATE(TEXT(I6,"0000"),"-",TEXT(J6,"0000")) -> 0712-0005
A7: VII | B7: Bohol | C7: 1st | D7: Tagbilaran City | E7: Component | G7: Crispa Technical Training Center, Inc. | H7: P. Cabalit St., Taloto Dist., Tagbilaran City, Bohol | I7: 712 | J7: 6 | K7: =CONCATENATE(TEXT(I7,"0000"),"-",TEXT(J7,"0000")) -> 0712-0006
A8: VII | B8: Bohol | C8: 1st | D8: Tagbilaran City | E8: Component | G8: Asian Divine Light College, Inc. | H8: 0053 F. Bustrillos Street Dao District Tagbilaran City Bohol | I8: 712 | J8: 7 | K8: =CONCATENATE(TEXT(I8,"0000"),"-",TEXT(J8,"0000")) -> 0712-0007
A9: VII | B9: Bohol | C9: 1st | D9: Tagbilaran City | E9: Component | G9: Bohol Tech Voc, Inc. | H9: Zamora St., Dao District, Tagbilaran City, Bohol | I9: 712 | J9: 8 | K9: =CONCATENATE(TEXT(I9,"0000"),"-",TEXT(J9,"0000")) -> 0712-0008
A10: VII | B10: Bohol | C10: 1st | D10: Tagbilaran City | E10: Component | G10: Fil-Canadian Training & Dev't. Center for Caregivers, Inc. | H10: Tamblot St., Tagbilaran City, Bohol | I10: 712 | J10: 9 | K10: =CONCATENATE(TEXT(I10,"0000"),"-",TEXT(J10,"0000")) -> 0712-0009
A11: VII | B11: Bohol | C11: 1st | D11: Tagbilaran City | E11: Component | G11: SBR Technical Education Training Center Inc. | H11: 4932-A1 CPG North Ave., Manga Dist. Tagbilaran City | I11: 712 | J11: 10 | K11: =CONCATENATE(TEXT(I11,"0000"),"-",TEXT(J11,"0000")) -> 0712-0010
A12: VII | B12: Bohol | C12: 3rd | D12: Lila | E12: 5th | G12: Taug Technical Institute and Assessment Center, Inc. | H12: Purok Bayabas, Taug, Lila, Bohol | I12: 712 | J12: 11 | K12: =CONCATENATE(TEXT(I12,"0000"),"-",TEXT(J12,"0000")) -> 0712-0011
A13: VII | B13: Bohol | C13: 1st | D13: Baclayon | E13: 4th | G13: CA-LIM Tech Training and Assessment Center, Inc. | H13: San Isidro, Baclayon, Bohol | I13: 712 | J13: 12 | K13: =CONCATENATE(TEXT(I13,"0000"),"-",TEXT(J13,"0000")) -> 0712-0012
... A49: VII | B49: Bohol | C49: 1st | D49: Tagbilaran City | E49: Component | G49: Global Voyage Assessment and Learning Center Inc. | H49: 0382 Venancio Inting Street Mansasa, Tagbilaran City (Capital), Bohol, Region VII (Central Visayas), 6300 | I49: 712 | J49: 46 | K49: =CONCATENATE(TEXT(I49,"0000"),"-",TEXT(J49,"0000")) -> 0712-0046
A50: VII | B50: Bohol | C50: 1st | D50: Tagbilaran City | E50: Component | G50: Gentle Family Home Training Center Inc. | H50: 3/F GZ Building Tamblot Cogon Tagbilaran City (Capital), Bohol, Region VII, Philippines, 6300 | I50: 712 | J50: 47 | K50: =CONCATENATE(TEXT(I50,"0000"),"-",TEXT(J50,"0000")) -> 0712-0047 | L50: 1
A51: VII | B51: Bohol | C51: 3rd | D51: Duero | E51: 4th | F51: {=IFERROR(INDEX(UIID!$K$2:$K1107, MATCH(CONCATENATE(B51,D51,G51,J51), UIID!$B$2:$B1107&UIID!$D$2:$D1107&UIID!$G$2:$G1107&UIID!$H$2:$H1107, 0),), "Not Found")} -> Not Found | G51: Hexagon Technological Institute Inc. | H51: Purok 4 Langkis, Duero, Bohol, Region VII (Central Visayas), 6309 | I51: 712 | J51: 48 | K51: =CONCATENATE(TEXT(I51,"0000"),"-",TEXT(J51,"0000")) -> 0712-0048
A52: VII | B52: Bohol | C52: 2nd | D52: San Isidro | E52: 5th | F52: {=IFERROR(INDEX(UIID!$K$2:$K1107, MATCH(CONCATENATE(B52,D52,G52,J52), UIID!$B$2:$B1107&UIID!$D$2:$D1107&UIID!$G$2:$G1107&UIID!$H$2:$H1107, 0),), "Not Found")} -> Not Found | G52: TFK Elite 888 Corp. | H52: Purok Tundan, Poblacion, San Isidro, Bohol | I52: 712 | J52: 49 | K52: =CONCATENATE(TEXT(I52,"0000"),"-",TEXT(J52,"0000")) -> 0712-0049
A53: VII | B53: Bohol | C53: 1st | D53: Tagbilaran City | E53: Component | F53: {=IFERROR(INDEX(UIID!$K$2:$K1107, MATCH(CONCATENATE(B53,D53,G53,J53), UIID!$B$2:$B1107&UIID!$D$2:$D1107&UIID!$G$2:$G1107&UIID!$H$2:$H1107, 0),), "Not Found")} -> Not Found | G53: Tagbilaran City College | H53: Satellite Road, Dampas District, Tagbilaran City, Bohol 6300 | I53: 712 | J53: 50 | K53: =CONCATENATE(TEXT(I53,"0000"),"-",TEXT(J53,"0000")) -> 0712-0050
A54: VII | B54: Bohol | C54: 1st | D54: Panglao | E54: 4th | G54: IWH Bohol Resort Corp. Doing Business Under the Name and Style of Best Western Plus the Ivywall Resort, Panglao | H54: Alona Beach, Danao, Panglao, Bohol, Philippines | I54: 712 | J54: 51 | K54: =CONCATENATE(TEXT(I54,"0000"),"-",TEXT(J54,"0000")) -> 0712-0051
A55: VII | B55: Bohol | C55: 1st | D55: Loon | E55: 2nd | F55: {=IFERROR(INDEX(UIID!$K$2:$K1107, MATCH(CONCATENATE(B55,D55,G55,J55), UIID!$B$2:$B1107&UIID!$D$2:$D1107&UIID!$G$2:$G1107&UIID!$H$2:$H1107, 0),), "Not Found")} -> Not Found | G55: Gazebo de Loondon Food House | H55: Purok 3, Basac, Loon, Bohol | I55: 712 | J55: 52 | K55: =CONCATENATE(TEXT(I55,"0000"),"-",TEXT(J55,"0000")) -> 0712-0052
A56: VII | B56: Bohol | C56: 2nd | D56: Talibon | E56: 1st | F56: {=IFERROR(INDEX(UIID!$K$2:$K1107, MATCH(CONCATENATE(B56,D56,G56,J56), UIID!$B$2:$B1107&UIID!$D$2:$D1107&UIID!$G$2:$G1107&UIID!$H$2:$H1107, 0),), "Not Found")} -> Not Found | G56: Gentle Family Home Training Center Inc. | H56: 2nd Floor Talibon Pension Puracan Bldg., CPG Ave., Poblacion, Talibon Bohol Philippines | I56: 712 | J56: 53 | K56: =CONCATENATE(TEXT(I56,"0000"),"-",TEXT(J56,"0000")) -> 0712-0053
A57: VII | B57: Bohol | C57: 3rd | D57: Garcia Hernandez | E57: 4th | F57: {=IFERROR(INDEX(UIID!$K$2:$K1107, MATCH(CONCATENATE(B57,D57,G57,J57), UIID!$B$2:$B1107&UIID!$D$2:$D1107&UIID!$G$2:$G1107&UIID!$H$2:$H1107, 0),), "Not Found")} -> Not Found | G57: Bow and Arrow Integrated Organic Farm | H57: Dahay St. Tabuan, Garcia Hernandez, Bohol | I57: 712 | J57: 54 | K57: =CONCATENATE(TEXT(I57,"0000"),"-",TEXT(J57,"0000")) -> 0712-0054
A58: VII | B58: Bohol | C58: 1st | D58: Dauis | E58: 4th | F58: {=IFERROR(INDEX(UIID!$K$2:$K1107, MATCH(CONCATENATE(B58,D58,G58,J58), UIID!$B$2:$B1107&UIID!$D$2:$D1107&UIID!$G$2:$G1107&UIID!$H$2:$H1107, 0),), "Not Found")} -> Not Found | G58: Bohol Island Tour Guides Association of the Philippines, Inc. | H58: Purok 1, Barangay Totolan, Municipality of Dauis, Bohol | I58: 712 | J58: 55 | K58: =CONCATENATE(TEXT(I58,"0000"),"-",TEXT(J58,"0000")) -> 0712-0055
A59: VII | B59: Bohol | C59: 1st | D59: Balilihan | E59: 4th | F59: {=IFERROR(INDEX(UIID!$K$2:$K1107, MATCH(CONCATENATE(B59,D59,G59,J59), UIID!$B$2:$B1107&UIID!$D$2:$D1107&UIID!$G$2:$G1107&UIID!$H$2:$H1107, 0),), "Not Found")} -> Not Found | G59: Green Garden of Hope Integrated Farm | H59: Brgy. 5, San Roque, Balilihan, Bohol | I59: 712 | J59: 56 | K59: =CONCATENATE(TEXT(I59,"0000"),"-",TEXT(J59,"0000")) -> 0712-0056
A60: VII | B60: Bohol | D60: Mabini | G60: Philippine School of Healthcare Professions Inc. | H60: Mabini, Bohol | I60: 712 | J60: 57 | K60: =CONCATENATE(TEXT(I60,"0000"),"-",TEXT(J60,"0000")) -> 0712-0057
A61: VII | B61: Bohol | C61: 2nd | D61: San Miguel | E61: 4th | F61: {=IFERROR(INDEX(UIID!$K$2:$K1107, MATCH(CONCATENATE(B61,D61,G61,J61), UIID!$B$2:$B1107&UIID!$D$2:$D1107&UIID!$G$2:$G1107&UIID!$H$2:$H1107, 0),), "Not Found")} -> Not Found | G61: Czarbeez Integrated Farm | H61: Purok 6, Cantagum, Tomoc, San Miguel, Bohol | I61: 712 | J61: 58 | K61: =CONCATENATE(TEXT(I61,"0000"),"-",TEXT(J61,"0000")) -> 0712-0058
A62: VII | B62: Bohol | C62: 1st | D62: Dauis | G62: International Academe of Ensciema, Inc. | H62: Totolan, Dauis, Bohol | I62: 712 | J62: 59 | K62: =CONCATENATE(TEXT(I62,"0000"),"-",TEXT(J62,"0000")) -> 0712-0059
A63: VII | B63: Cebu | C63: North | D63: Cebu City | E63: HUC | G63: CITE (Center for Industrial Technology and Enterprise) Technical Institute, Inc. | H63: San Jose, Talamban, Cebu City | I63: 722 | J63: 1 | K63: =CONCATENATE(TEXT(I63,"0000"),"-",TEXT(J63,"0000")) -> 0722-0001 | L63: 1 | M63: 722 | N63: Cebu
A64: VII | B64: Cebu | C64: 6th | D64: Mandaue City | E64: HUC | G64: Center for Healthcare Professions Cebu, Inc. | H64: Mezzanine Floor, First Consolidated Bank Bldg. Corner P.Burgos St. and A.C. Cortes Ave., Brgy. Alang-Alang, Mandaue City, Cebu | I64: 722 | J64: 2 | K64: =CONCATENATE(TEXT(I64,"0000"),"-",TEXT(J64,"0000")) -> 0722-0002 | L64: 1
A65: VII | B65: Cebu | C65: 3rd | D65: Toledo City | E65: Component | G65: Provincial Training Center - Cebu (Toledo) | H65: Ilijan, Toledo City | I65: 722 | J65: 3 | K65: =CONCATENATE(TEXT(I65,"0000"),"-",TEXT(J65,"0000")) -> 0722-0003 | L65: 1 | M65: 761 | N65: Siquijor
A66: VII | B66: Cebu | C66: 5th | D66: Carmen | E66: 3rd | G66: Provincial Training Center - Cebu (Carmen) | H66: Poblacion, Carmen, Cebu | I66: 722 | J66: 4 | K66: =CONCATENATE(TEXT(I66,"0000"),"-",TEXT(J66,"0000")) -> 0722-0004 | L66: 1
A67: VII | B67: Cebu | C67: Lone | D67: Lapu-lapu City | E67: HUC | G67: Regent Pacific College, Inc. | H67: Barangay Agus, Lapulapu City, Cebu | I67: 722 | J67: 5 | K67: =CONCATENATE(TEXT(I67,"0000"),"-",TEXT(J67,"0000")) -> 0722-0005 | L67: 1
A68: VII | B68: Cebu | C68: 1st | D68: Minglanilla | E68: 1st | G68: Mary Our Help Technical Institute for Women (Cebu), Inc. | H68: Km. 17, Tungha-an, Minglanilla, Cebu | I68: 722 | J68: 6 | K68: =CONCATENATE(TEXT(I68,"0000"),"-",TEXT(J68,"0000")) -> 0722-0006 | L68: 1
A69: VII | B69: Cebu | C69: 5th | D69: Liloan | E69: 1st | G69: Cebu Science of Welding and Skills Technology Inc. | H69: Bag-ong Daan, Yati, Liloan, Cebu | I69: 722 | J69: 7 | K69: =CONCATENATE(TEXT(I69,"0000"),"-",TEXT(J69,"0000")) -> 0722-0007 | L69: 1
A70: VII | B70: Cebu | C70: North | D70: Cebu City | E70: HUC | G70: Academy of Eskrima Martial Arts, Inc. | H70: 31 Eagle Street. Sto. Niño Village, Banilad, Cebu City, Cebu | I70: 722 | J70: 8 | K70: =CONCATENATE(TEXT(I70,"0000"),"-",TEXT(J70,"0000")) -> 0722-0008 | L70: 1
A71: VII | B71: Cebu | C71: 3rd | D71: Balamban | E71: 1st | G71: Balamban Community Trng. Center | H71: Balamban, Cebu | I71: 722 | J71: 9 | K71: =CONCATENATE(TEXT(I71,"0000"),"-",TEXT(J71,"0000")) -> 0722-0009 | L71: 1
A72: VII | B72: Cebu | C72: North | D72: Cebu City | E72: HUC | G72: Fil-Canadian Training & Dev't. Center for Caregivers, Inc. | H72: G/F Oftana Bldg., Cor. Don Mariano Cui & Jasmin Sts. Osemeña Blvd., Cebu City | I72: 722 | J72: 10 | K72: =CONCATENATE(TEXT(I72,"0000"),"-",TEXT(J72,"0000")) -> 0722-0010 | L72: 1
A73: VII | B73: Cebu | C73: North | D73: Cebu City | E73: HUC | G73: BMC Training Center for Welding andFabrication, Inc. | H73: C. Borces St., Mabolo, Cebu City | I73: 722 | J73: 11 | K73: =CONCATENATE(TEXT(I73,"0000"),"-",TEXT(J73,"0000")) -> 0722-0011 | L73: 1
A74: VII | B74: Cebu | C74: South | D74: Cebu City | E74: HUC | G74: St. Paul College Foundation, Inc. - Cebu City | H74: 279 Bulacao, Pardo, Cebu City | I74: 722 | J74: 12 | K74: =CONCATENATE(TEXT(I74,"0000"),"-",TEXT(J74,"0000")) -> 0722-0012 | L74: 1
A75: VII | B75: Cebu | C75: 1st | D75: Talisay City | E75: Component | G75: Sisters of Mary Technical Education Institute, Cebu, Inc. | H75: J.P. Rizal St., Talisay City, Cebu | I75: 722 | J75: 13 | K75: =CONCATENATE(TEXT(I75,"0000"),"-",TEXT(J75,"0000")) -> 0722-0013 | L75: 1
A76: VII | B76: Cebu | C76: 1st | D76: Minglanilla | E76: 1st | G76: Sisters of Mary Technical Education Institute, Cebu, Inc. | H76: Tungkop, Minglanilla,Cebu | I76: 722 | J76: 14 | K76: =CONCATENATE(TEXT(I76,"0000"),"-",TEXT(J76,"0000")) -> 0722-0014 | L76: 1
A77: VII | B77: Cebu | C77: 5th | D77: Compostela | E77: 3rd | G77: Saint James Academy of Skills Technology, Inc. | H77: Poblacion, Compostela, Cebu | I77: 722 | J77: 15 | K77: =CONCATENATE(TEXT(I77,"0000"),"-",TEXT(J77,"0000")) -> 0722-0015 | L77: 1
... A79: VII | B79: Cebu | C79: 4th | D79: Tabogon | E79: 3rd | G79: Tabogon Technical Skills Development Center | H79: Daantabogon, Tabogon, Cebu | I79: 722 | J79: 17 | K79: =CONCATENATE(TEXT(I79,"0000"),"-",TEXT(J79,"0000")) -> 0722-0017 | L79: 1
A80: VII | B80: Cebu | C80: North | D80: Cebu City | E80: HUC | G80: Cebu Call Center Academy Inc. | H80: #79 VEG Bldg., Gen. Maxilom Avenue, Cebu City | I80: 722 | J80: 18 | K80: =CONCATENATE(TEXT(I80,"0000"),"-",TEXT(J80,"0000")) -> 0722-0018 | L80: 1a
A81: VII | B81: Cebu | C81: North | D81: Cebu City | E81: HUC | G81: Cebu Call Center Academy Inc. | H81: #79 VEG Building, General Maxilom Ave., Cebu City, Cebu | I81: 722 | J81: 18 | K81: =CONCATENATE(TEXT(I81,"0000"),"-",TEXT(J81,"0000")) -> 0722-0018 | L81: 1a
A82: VII | B82: Cebu | C82: 1st | D82: Minglanilla | E82: 1st | G82: Provincial Training Center - Cebu (Minglanilla) | H82: Calajo-an, Minglanilla, Cebu | I82: 722 | J82: 19 | K82: =CONCATENATE(TEXT(I82,"0000"),"-",TEXT(J82,"0000")) -> 0722-0019 | L82: 1
A83: VII | B83: Cebu | C83: 1st | D83: Talisay City | E83: Component | G83: ABQ International Health Caregiver Program & Consultancy, Inc. | H83: Z1085 Miami Homes Subdivision, San Isidro, Talisay City, Cebu | I83: 722 | J83: 20 | K83: =CONCATENATE(TEXT(I83,"0000"),"-",TEXT(J83,"0000")) -> 0722-0020 | L83: 1
A84: VII | B84: Cebu | C84: North | D84: Cebu City | E84: HUC | G84: University of Cebu Banilad, Inc. | H84: Banilad, Cebu City | I84: 722 | J84: 21 | K84: =CONCATENATE(TEXT(I84,"0000"),"-",TEXT(J84,"0000")) -> 0722-0021 | L84: 1
A85: VII | B85: Cebu | C85: 1st | D85: Carcar City | E85: Component | G85: Carcar Community Skills Training and Assessment Center | H85: Luan-Luan, Carcar City, Cebu | I85: 722 | J85: 22 | K85: =CONCATENATE(TEXT(I85,"0000"),"-",TEXT(J85,"0000")) -> 0722-0022 | L85: 1
A86: VII | B86: Cebu | C86: 4th | D86: Madridejos | E86: HUC | G86: Salazar Colleges of Science and Institute of Technology, Inc. | H86: Poblacion, Madridejos, Cebu | I86: 722 | J86: 23 | K86: =CONCATENATE(TEXT(I86,"0000"),"-",TEXT(J86,"0000")) -> 0722-0023 | L86: 1
A87: VII | B87: Cebu | C87: 4th | D87: Madridejos | E87: 4th | G87: Madridejos Community College | H87: Bunakan, Madridejos, Cebu | I87: 722 | J87: 24 | K87: =CONCATENATE(TEXT(I87,"0000"),"-",TEXT(J87,"0000")) -> 0722-0024 | L87: 1
A88: VII | B88: Cebu | C88: North | D88: Cebu City | E88: HUC | G88: Asian College of Technology International Educational Foundation, Inc. | H88: Corner Leon Kilat and P. del Rosario Sts. Cebu City | I88: 722 | J88: 25 | K88: =CONCATENATE(TEXT(I88,"0000"),"-",TEXT(J88,"0000")) -> 0722-0025 | L88: 1
A89: VII | B89: Cebu | C89: North | D89: Cebu City | E89: HUC | G89: English Fella Educational Corporation | H89: Tigbao, Talamban, Cebu City | I89: 722 | J89: 26 | K89: =CONCATENATE(TEXT(I89,"0000"),"-",TEXT(J89,"0000")) -> 0722-0026 | L89: 1
A90: VII | B90: Cebu | C90: North | D90: Cebu City | E90: HUC | G90: English Fella Educational Corporation | H90: Highway 11, Talamban Cebu | I90: 722 | J90: 27 | K90: =CONCATENATE(TEXT(I90,"0000"),"-",TEXT(J90,"0000")) -> 0722-0027 | L90: 1
A91: VII | B91: Cebu | C91: South | D91: Cebu City | E91: HUC | G91: Racdaes Japanese Language Training Center, Inc. | H91: 72 B Andres Abellana Extension, Guadalupe, Cebu City | I91: 722 | J91: 28 | K91: =CONCATENATE(TEXT(I91,"0000"),"-",TEXT(J91,"0000")) -> 0722-0028 | L91: 1
A92: VII | B92: Cebu | C92: North | D92: Cebu City | E92: HUC | G92: Foundation for Advancement of Skills & Technology (FAST), Inc. | H92: Eagle Bldg., Don Gil Garcia Street, Capitol Site, Cebu City | I92: 722 | J92: 29 | K92: =CONCATENATE(TEXT(I92,"0000"),"-",TEXT(J92,"0000")) -> 0722-0029 | L92: 1
A93: VII | B93: Cebu | C93: 3rd | D93: Balamban | E93: 1st | G93: West Cebu Foundation, Inc. | H93: Buanoy, Balamban, Cebu | I93: 722 | J93: 30 | K93: =CONCATENATE(TEXT(I93,"0000"),"-",TEXT(J93,"0000")) -> 0722-0030 | L93: 1
A94: VII | B94: Cebu | C94: North | D94: Cebu City | E94: HUC | G94: E-mo Language Studies Corporation | H94: 3/F Samantabhadra Institute cor. Arch. Reyes & J. Luna Sts., Mabolo, Cebu City | I94: 722 | J94: 31 | K94: =CONCATENATE(TEXT(I94,"0000"),"-",TEXT(J94,"0000")) -> 0722-0031 | L94: 1
A95: VII | B95: Cebu | C95: North | D95: Cebu City | E95: HUC | G95: Regional Training Center - Cebu | H95: Archbishop Reyes Ave., Cor. Salinas Drive, Lahug, Cebu City | I95: 722 | J95: 32 | K95: =CONCATENATE(TEXT(I95,"0000"),"-",TEXT(J95,"0000")) -> 0722-0032 | L95: 1k
A96: VII | B96: Cebu | C96: Cebu City | D96: Cebu City | E96: HUC | G96: Regional Training Center VII | H96: TESDA 7 Compound Archbishop Reyes Avenue, Cebu City | I96: 722 | J96: 32 | K96: =CONCATENATE(TEXT(I96,"0000"),"-",TEXT(J96,"0000")) -> 0722-0032 | L96: 1k
A97: VII | B97: Cebu | C97: North | D97: Cebu City | E97: HUC | G97: TESDA Technology Institute - RTC VII | H97: Archbishop Reyes Ave., Salinas Drive , Lahug , Cebu City | I97: 722 | J97: 32 | K97: =CONCATENATE(TEXT(I97,"0000"),"-",TEXT(J97,"0000")) -> 0722-0032 | L97: 1k
A98: VII | B98: Cebu | C98: North | D98: Cebu City | E98: HUC | G98: MGB Skills Development and Assessment Center, Inc. | H98: MGB Bldg., Salinas Drive Ext., Lahug, Cebu City | I98: 722 | J98: 33 | K98: =CONCATENATE(TEXT(I98,"0000"),"-",TEXT(J98,"0000")) -> 0722-0033 | L98: 1
A99: VII | B99: Cebu | C99: South | D99: Cebu City | E99: HUC | G99: University of San Jose-Recoletos, Inc. | H99: St. Ezekiel Moreno Building, Basak Campus, Pardo, Cebu City | I99: 722 | J99: 34 | K99: =CONCATENATE(TEXT(I99,"0000"),"-",TEXT(J99,"0000")) -> 0722-0034 | L99: 1
A100: VII | B100: Cebu | C100: North | D100: Cebu City | E100: HUC | G100: Cebu American English Academy Corporation | H100: 11 Don Jose Avila St., Capitol Site, Cebu City | I100: 722 | J100: 35 | K100: =CONCATENATE(TEXT(I100,"0000"),"-",TEXT(J100,"0000")) -> 0722-0035 | L100: 1
A101: VII | B101: Cebu | C101: North | D101: Cebu City | E101: HUC | G101: International School for Culinary Arts and Hotel Management Cebu Inc. | H101: G/F, Synergis I.T. Center, F. Cabahug Street, Kasambagan, Cebu City | I101: 722 | J101: 36 | K101: =CONCATENATE(TEXT(I101,"0000"),"-",TEXT(J101,"0000")) -> 0722-0036 | L101: 1
A102: VII | B102: Cebu | C102: North | D102: Cebu City | E102: HUC | G102: Universe English School Cebu Inc. | H102: 5th Floor, Jesa IT Center, 90 General Maxilom Ave., Cebu City | I102: 722 | J102: 37 | K102: =CONCATENATE(TEXT(I102,"0000"),"-",TEXT(J102,"0000")) -> 0722-0037 | L102: 1
A103: VII | B103: Cebu | C103: North | D103: Cebu City | E103: HUC | G103: Wonderful English for Outstanding Students WEFOS Corporation | H103: Rm. 420 Krizia Bldg., Gonzales Compound, Lahug, Cebu City | I103: 722 | J103: 38 | K103: =CONCATENATE(TEXT(I103,"0000"),"-",TEXT(J103,"0000")) -> 0722-0038 | L103: 1
A104: VII | B104: Cebu | C104: North | D104: Cebu City | E104: HUC | G104: Best of Cebu English Academy Inc. | H104: 5 Storey Dormitory cor. St. Michael Street, Old Banilad Barangay Kasambagan Cebu City Philippines | I104: 722 | J104: 39 | K104: =CONCATENATE(TEXT(I104,"0000"),"-",TEXT(J104,"0000")) -> 0722-0039 | L104: 1
A105: VII | B105: Cebu | C105: North | D105: Cebu City | E105: HUC | G105: Center for Premier Int'l. Language Studies Inc. | H105: Benedicto Building, M.J. Cuenco Avenue, Cebu City | I105: 722 | J105: 40 | K105: =CONCATENATE(TEXT(I105,"0000"),"-",TEXT(J105,"0000")) -> 0722-0040 | L105: 1
A106: VII | B106: Cebu | C106: Lone | D106: Lapu-lapu City | E106: HUC | G106: Joinus English Language Academe, Inc. | H106: Mustang, Ceniza St., Pusok, Lapu-lapu City | I106: 722 | J106: 41 | K106: =CONCATENATE(TEXT(I106,"0000"),"-",TEXT(J106,"0000")) -> 0722-0041 | L106: 1
A107: VII | B107: Cebu | C107: North | D107: Cebu City | E107: HUC | G107: Cebu English Global Academy Inc. | H107: Britech Interface College, Angelica Bldg., Osmeña Blvd. Cebu City | I107: 722 | J107: 42 | K107: =CONCATENATE(TEXT(I107,"0000"),"-",TEXT(J107,"0000")) -> 0722-0042 | L107: 1
A108: VII | B108: Cebu | C108: South | D108: Cebu City | E108: HUC | G108: University of Cebu, Inc. - Main | H108: Sanciangco St., Cor. Osmeña Blvd., Cebu City | I108: 722 | J108: 43 | K108: =CONCATENATE(TEXT(I108,"0000"),"-",TEXT(J108,"0000")) -> 0722-0043 | L108: 1
A109: VII | B109: Cebu | C109: 6th | D109: Mandaue City | E109: HUC | G109: Zoie Skills Training and Assessment Center, Inc. | H109: MC Briones St., Highway Barangay Baklid, Mandaue City (former address: Blk 5 Lot 6 Warehouse 34 Mandaue North Central, Cabancalan, Mandaue City) | I109: 722 | J109: 44 | K109: =CONCATENATE(TEXT(I109,"0000"),"-",TEXT(J109,"0000")) -> 0722-0044 | L109: 1
... A127: VII | B127: Cebu | C127: North | D127: Cebu City | E127: HUC | G127: University of the Visayas-Main | H127: Colon St., Cebu City | I127: 722 | J127: 62 | K127: =CONCATENATE(TEXT(I127,"0000"),"-",TEXT(J127,"0000")) -> 0722-0062 | L127: 1
A128: VII | B128: Cebu | C128: North | D128: Cebu City | E128: HUC | G128: University of the Visayas, Inc. | H128: Colon St., Cebu City | I128: 722 | J128: 62 | K128: =CONCATENATE(TEXT(I128,"0000"),"-",TEXT(J128,"0000")) -> 0722-0062
A129: VII | B129: Cebu | C129: South | D129: Cebu City | E129: HUC | G129: B.I.G. Dev't Training & Assessment Center, Inc. | H129: 22 Virgo St., Guadalupe, Osmeña Village, Punta Princesa, Cebu City | I129: 722 | J129: 63 | K129: =CONCATENATE(TEXT(I129,"0000"),"-",TEXT(J129,"0000")) -> 0722-0063 | L129: 1
A130: VII | B130: Cebu | C130: North | D130: Cebu City | E130: HUC | G130: American International Culinary & Hospitality Institute Inc. | H130: Corner Leon Kilat and P. del Rosario Streets, Cebu City | I130: 722 | J130: 64 | K130: =CONCATENATE(TEXT(I130,"0000"),"-",TEXT(J130,"0000")) -> 0722-0064 | L130: 1
A131: VII | B131: Cebu | C131: Lone | D131: Lapu-lapu City | E131: HUC | G131: ELE Technical Training & Assessment Center Corp. | H131: 4308 Osmeña St., Gunob, Lapu-Lapu City | I131: 722 | J131: 65 | K131: =CONCATENATE(TEXT(I131,"0000"),"-",TEXT(J131,"0000")) -> 0722-0065 | L131: 1
A132: VII | B132: Cebu | C132: 3rd | D132: Asturias | E132: 3rd | G132: Cebu Southwest Technical College, Inc. | H132: Owak, Asturias, Cebu | I132: 722 | J132: 66 | K132: =CONCATENATE(TEXT(I132,"0000"),"-",TEXT(J132,"0000")) -> 0722-0066 | L132: 1
A133: VII | B133: Cebu | C133: 1st | D133: Cebu City | E133: HUC | G133: Cebu Globalization ESL Center Incorporated | H133: 1st to 3rd Floor Academy Building CG Base Camp, Ma. Luisa Rd. Banilad, Cebu City | I133: 722 | J133: 67 | K133: =CONCATENATE(TEXT(I133,"0000"),"-",TEXT(J133,"0000")) -> 0722-0067 | L133: 1
A134: VII | B134: Cebu | C134: 5th | D134: Danao City | E134: Component | G134: Colegio De San Antonio De Padua, Inc. | H134: Brgy. Guinsay, Danao City, Cebu | I134: 722 | J134: 68 | K134: =CONCATENATE(TEXT(I134,"0000"),"-",TEXT(J134,"0000")) -> 0722-0068 | L134: 1
A135: VII | B135: Cebu | C135: North | D135: Cebu City | E135: HUC | G135: International Skills Republic Academy, Inc. | H135: 0755 Jasmin Street, Barangay Capitol Site, Cebu City | I135: 722 | J135: 69 | K135: =CONCATENATE(TEXT(I135,"0000"),"-",TEXT(J135,"0000")) -> 0722-0069 | L135: 1
A136: VII | B136: Cebu | C136: 3rd | D136: Pinamungajan | E136: 2nd | G136: Lamac Multipurpose Integrated Farm School, Lamac Pinamungajan | H136: Lamac, Pinamungajan, Cebu | I136: 722 | J136: 70 | K136: =CONCATENATE(TEXT(I136,"0000"),"-",TEXT(J136,"0000")) -> 0722-0070 | L136: 1f
A137: VII | B137: Cebu | C137: 3rd | D137: Pinamungajan | E137: 2nd | G137: Lamac Multipurpose Cooperative | H137: Lamac, Pinamungajan, Cebu | I137: 722 | J137: 70 | K137: =CONCATENATE(TEXT(I137,"0000"),"-",TEXT(J137,"0000")) -> 0722-0070 | L137: 1f
A138: VII | B138: Cebu | C138: 1st | D138: Naga City | E138: Component | G138: Technical Training Center of South Cebu, Inc. | H138: DLV5 Commercial Bldg. Rizal Street Central Poblacion City of Naga, Cebu, Region VII, Philippines, 6037 | I138: 722 | J138: 71 | K138: =CONCATENATE(TEXT(I138,"0000"),"-",TEXT(J138,"0000")) -> 0722-0071 | L138: 1
A139: VII | B139: Cebu | C139: 6th | D139: Mandaue City | E139: HUC | G139: Metrologyx Training & Assessment Center Inc. | H139: 4/F Magkono Bldg. A.C. Cortes Avenue Mandaue City | I139: 722 | J139: 72 | K139: =CONCATENATE(TEXT(I139,"0000"),"-",TEXT(J139,"0000")) -> 0722-0072 | L139: 1
A140: VII | B140: Cebu | C140: 4th | D140: Bogo City | E140: Component | G140: Sto. Niño Skills Development and Assessment Center Inc. | H140: 2 Northomes Building Proper Dakit, Bogo City, Dakit City of Bogo, Cebu, Region VII, Philippines, 6010 | I140: 722 | J140: 73 | K140: =CONCATENATE(TEXT(I140,"0000"),"-",TEXT(J140,"0000")) -> 0722-0073 | L140: 1
A141: VII | B141: Cebu | C141: 4th | D141: Bogo City | E141: Component | G141: Sto. Niño Skills Development and Assessment Center Inc. | H141: Purok Canor, Dakit Bogo City, Cebu Philippines | I141: 722 | J141: 73 | K141: =CONCATENATE(TEXT(I141,"0000"),"-",TEXT(J141,"0000")) -> 0722-0073
A142: VII | B142: Cebu | C142: 5th | D142: Liloan | E142: 1st | G142: Don Bosco Boy's Home, Inc. | H142: Cotcot, Liloan, Cebu | I142: 722 | J142: 74 | K142: =CONCATENATE(TEXT(I142,"0000"),"-",TEXT(J142,"0000")) -> 0722-0074 | L142: 1
A143: VII | B143: Cebu | C143: 3rd | D143: Balamban | E143: 1st | G143: Don Bosco Technical Vocational Education and Training Center-Balamban, Inc. | H143: Bldg. No. 0188, Prenza, Balamban, Cebu, Philippines 6041 | I143: 722 | J143: 75 | K143: =CONCATENATE(TEXT(I143,"0000"),"-",TEXT(J143,"0000")) -> 0722-0075 | L143: 1
A144: VII | B144: Cebu | C144: 4th | D144: Daanbantayan | E144: 1st | G144: Provincial Training Center - Cebu (Daanbantayan) | H144: Guimbawi-an, Poblacion, Daanbantayan, Cebu | I144: 722 | J144: 76 | K144: =CONCATENATE(TEXT(I144,"0000"),"-",TEXT(J144,"0000")) -> 0722-0076 | L144: 1
A145: VII | B145: Cebu | C145: North | D145: Cebu City | E145: HUC | G145: 3A Prime Hospitality Training and Assessment Center Inc. | H145: 362 Don Mariano Cui St. corner N. Escario St. Capitol Site, Cebu City | I145: 722 | J145: 77 | K145: =CONCATENATE(TEXT(I145,"0000"),"-",TEXT(J145,"0000")) -> 0722-0077 | L145: 1
A146: VII | B146: Cebu | C146: 3rd | D146: Balamban | E146: 1st | G146: BEST Inc. Integrated-Diversified Farm | H146: Brgy. Cantuod, Balamban, Cebu | I146: 722 | J146: 78 | K146: =CONCATENATE(TEXT(I146,"0000"),"-",TEXT(J146,"0000")) -> 0722-0078 | L146: 1
A147: VII | B147: Cebu | C147: North | D147: Cebu City | E147: HUC | G147: Don Bosco Technical Vocational Education and Training Center-Pasil, Inc. | H147: Lot. 128 Blk.2, L. Flores St., Pasil, Cebu City 6000 | I147: 722 | J147: 79 | K147: =CONCATENATE(TEXT(I147,"0000"),"-",TEXT(J147,"0000")) -> 0722-0079 | L147: 1b
A148: VII | B148: Cebu | C148: South | D148: Cebu City | E148: HUC | G148: Don Bosco Technical Vocational Education and Training Center-Pasil, Inc. | H148: L. Flores St., Pasil, Cebu City | I148: 722 | J148: 79 | K148: =CONCATENATE(TEXT(I148,"0000"),"-",TEXT(J148,"0000")) -> 0722-0079 | L148: 1b
A149: VII | B149: Cebu | C149: North | D149: Cebu City | E149: HUC | G149: SICES Institute of Healtcare And Vocational Studies Inc. | H149: Rm. 201 Lim`s Brotherhood, Osmeña Blvd., Cor. J. Llorente St., Capitol Site Cebu City | I149: 722 | J149: 80 | K149: =CONCATENATE(TEXT(I149,"0000"),"-",TEXT(J149,"0000")) -> 0722-0080 | L149: 1
A150: VII | B150: Cebu | C150: 1st | D150: Cebu City | E150: HUC | G150: Reignite Philippines Inc. | H150: 78 Pres. Magsaysay Ext., Kasambagan Cebu City (Capital) Cebu, Philippines | I150: 722 | J150: 81 | K150: =CONCATENATE(TEXT(I150,"0000"),"-",TEXT(J150,"0000")) -> 0722-0081 | L150: 1
A151: VII | B151: Cebu | C151: 5th | D151: Liloan | E151: 1st | G151: Industrial Education Learning Center and Technologies, Inc. | H151: House No. 02-440, Purok Luy-a, Calero, Lilo-an, Cebu | I151: 722 | J151: 82 | K151: =CONCATENATE(TEXT(I151,"0000"),"-",TEXT(J151,"0000")) -> 0722-0082 | L151: 1d
A152: VII | B152: Cebu | C152: 5th | D152: Liloan | E152: 1st | G152: Industrial Education Learning Center and Technologies, Inc. (Formerly: Industrial Education Learning Technologies, Inc.) | H152: House No. 02-440, Purok Luy-a, Calero, Lilo-an, Cebu | I152: 722 | J152: 82 | K152: =CONCATENATE(TEXT(I152,"0000"),"-",TEXT(J152,"0000")) -> 0722-0082 | L152: 1d
A153: VII | B153: Cebu | C153: 3rd | D153: Balamban | E153: 1st | G153: Balamban Extensive Skills and Technology Inc. | H153: Lot 2140, Brgy. Cantuod, Balamban, Cebu | I153: 722 | J153: 83 | K153: =CONCATENATE(TEXT(I153,"0000"),"-",TEXT(J153,"0000")) -> 0722-0083 | L153: 1
...

Sheet 2026 Bohol
A1: REGION | B1: PROVINCE | C1: CONGRESSIONAL DISTRICT | D1: Municipality | E1: Municipality Class | F1: Unique Instittution Identification | G1: NAME OF INSTITUTION | H1: FORMERLY NAME of TVI | I1: Name of Institution's Head | J1: ADDRESS | K1: Latitude Point | L1: Longitude Point | M1: TEL. NO. | N1: E-mail Address | O1: TYPE OF INSTITUTION | P1: CLASSIFICATION OF INSTITUTION | Q1: STATUS | R1: SECTOR | S1: COURSE/REGISTERED PROGRAM (WTR/CoC) | T1: PQF Level | U1: DURATION | V1: PROGRAM REG. NO. | W1: DATE ISSUED | X1: EXPIRATION DATE | Y1: Trainer | Z1: NTTC | AA1: Date Conducted | AB1: Result | AC1: ORIGINAL DATE OF REGISTRATION
A2: VII | B2: Bohol | C2: 1st | D2: Tagbilaran City | E2: Component | F2: {=IFERROR(INDEX(UIID!$K$2:$K354, MATCH(CONCATENATE(B2,D2,G2,J2), UIID!$B$2:$B354&UIID!$D$2:$D354&UIID!$G$2:$G354&UIID!$H$2:$H354, 0),), "Not Found")} -> 0712-0038 | G2: Advance School for International Hospitality Services, Inc. | I2: Jay Q. Fernandez | J2: Purok 3, Espuelas St. Ext., Poblacion III, Tagbilaran City | K2: 9.642205 | L2: 123.86241 | M2: (038) 411-5266, 09396582563 | N2: advancehospitality5@gmail.com | O2: Private | P2: TVI | Q2: WTR | R2: Tourism | S2: Events Management Services NC III | T2: NC III | U2: 108 hours | V2: 20210712TRSEVM307008 | W2: 45329 | X2: 47157 | Y2: Annamae M. Sayon Agnes I. Estrera | Z2: 211907121300332 221807121300112 | AA2: 45387 | AB2: C | AC2: 44204
A3: VII | B3: Bohol | C3: 1st | D3: Tagbilaran City | E3: Component | F3: {=IFERROR(INDEX(UIID!$K$2:$K354, MATCH(CONCATENATE(B3,D3,G3,J3), UIID!$B$2:$B354&UIID!$D$2:$D354&UIID!$G$2:$G354&UIID!$H$2:$H354, 0),), "Not Found")} -> 0712-0038 | G3: Advance School for International Hospitality Services, Inc. | I3: Jay Q. Fernandez | J3: Purok 3, Espuelas St. Ext., Poblacion III, Tagbilaran City | K3: 9.642205 | L3: 123.86241 | M3: (038) 411-5266, 09396582563 | N3: advancehospitality5@gmail.com | O3: Private | P3: TVI | Q3: WTR | R3: Tourism | S3: Food and Beverage Services NC II | T3: NC II | U3: 356 Hours | V3: WTR No. 20180712TRSFBS213033 | W3: 45329 | X3: 47157 | Y3: Marivic C. Acosta | Z3: NTTC No. 221707121200158 | AC3: 43196
A4: VII | B4: Bohol | C4: 1st | D4: Tagbilaran City | E4: Component | F4: {=IFERROR(INDEX(UIID!$K$2:$K354, MATCH(CONCATENATE(B4,D4,G4,J4), UIID!$B$2:$B354&UIID!$D$2:$D354&UIID!$G$2:$G354&UIID!$H$2:$H354, 0),), "Not Found")} -> 0712-0038 | G4: Advance School for International Hospitality Services, Inc. | I4: Jay Q. Fernandez | J4: Purok 3, Espuelas St. Ext., Poblacion III, Tagbilaran City | K4: 9.642205 | L4: 123.86241 | M4: (038) 411-5266, 09396582563 | N4: advancehospitality5@gmail.com | O4: Private | P4: TVI | Q4: WTR | R4: Tourism | S4: Tourism Promotion Services NC II | T4: NC II | U4: 76 hours | V4: 20190712TRSTPS215010 | W4: 45329 | X4: 47157 | Y4: Alfie D. Mahumot Agnes I. Estrera | Z4: NTTC No. 191407121200012 NTTC No. 191807121200180 | AA4: 45387 | AB4: C | AC4: 43517
A5: VII | B5: Bohol | C5: 1st | D5: Tagbilaran City | E5: Component | F5: {=IFERROR(INDEX(UIID!$K$2:$K354, MATCH(CONCATENATE(B5,D5,G5,J5), UIID!$B$2:$B354&UIID!$D$2:$D354&UIID!$G$2:$G354&UIID!$H$2:$H354, 0),), "Not Found")} -> 0712-0007 | G5: Asian Divine Light College, Inc. | I5: Francisca R. Opog, Ph.D. / School Director | J5: 0053 F. Bustrillos Street Dao District Tagbilaran City Bohol | K5: 9.6696704 | L5: 123.86622 | M5: (038) 427-2225 / 411-0939 | N5: asiandivinelightcollege@gmail.com | O5: Private | P5: TVI | Q5: WTR | R5: Tourism | S5: Cookery NC II | T5: NC II | U5: 316 hours | V5: 201407012146 | W5: 45204 | X5: 47032 | Y5: Vianney Rose V. Requirme | Z5: NTTC No. 191907121200077 | AA5: 45730 | AB5: C | AC5: 41890
A6: VII | B6: Bohol | C6: 1st | D6: Tagbilaran City | E6: Component | F6: {=IFERROR(INDEX(UIID!$K$2:$K354, MATCH(CONCATENATE(B6,D6,G6,J6), UIID!$B$2:$B354&UIID!$D$2:$D354&UIID!$G$2:$G354&UIID!$H$2:$H354, 0),), "Not Found")} -> 0712-0007 | G6: Asian Divine Light College, Inc. | I6: Francisca R. Opog, Ph.D. / School Director | J6: 0053 F. Bustrillos Street Dao District Tagbilaran City Bohol | K6: 9.6696704 | L6: 123.86622 | M6: (038) 427-2225 / 411-0939 | N6: asiandivinelightcollege@gmail.com | O6: Private | P6: TVI | Q6: WTR | R6: Tourism | S6: Housekeeping NC II | T6: NC II | U6: 436 hours | V6: 20180712TRSHSK213103 | W6: 45005 | X6: 46961 | Y6: Vianney Rose V. Requirme Feab Juyad | Z6: NTTC No. 171407121200059 NTTC No. 201907121200174 | AA6: 45730 | AB6: C | AC6: 43283
A7: VII | B7: Bohol | C7: 1st | D7: Tagbilaran City | E7: Component | F7: {=IFERROR(INDEX(UIID!$K$2:$K354, MATCH(CONCATENATE(B7,D7,G7,J7), UIID!$B$2:$B354&UIID!$D$2:$D354&UIID!$G$2:$G354&UIID!$H$2:$H354, 0),), "Not Found")} -> 0712-0007 | G7: Asian Divine Light College, Inc. | I7: Francisca R. Opog, Ph.D. / School Director | J7: 0053 F. Bustrillos Street Dao District Tagbilaran City Bohol | K7: 9.6696704 | L7: 123.86622 | M7: (038) 427-2225 / 411-0939 | N7: asiandivinelightcollege@gmail.com | O7: Private | P7: TVI | Q7: WTR | R7: Tourism | S7: Bread and Pastry Production NC II | T7: NC II | U7: 141 hours | V7: 201407012172 | W7: 45204 | X7: 47032 | Y7: Ritchell R. Tabel Vianney Rose V. Requirme Theresa Mhae Garay Cherrybelle T. Mangaya-ay Evangeline B. Samputon | Z7: NTTC No. 211907121200035 NTTC No. 141407011236042 NTTC No. 201607121200208 NTTC No. 181407121200217 NTTC No. 191907121200441 | AA7: 45730 | AB7: C | AC7: 41915
A8: VII | B8: Bohol | C8: 1st | D8: Cortes | E8: 5th | F8: {=IFERROR(INDEX(UIID!$K$2:$K354, MATCH(CONCATENATE(B8,D8,G8,J8), UIID!$B$2:$B354&UIID!$D$2:$D354&UIID!$G$2:$G354&UIID!$H$2:$H354, 0),), "Not Found")} -> 0712-0034 | G8: Bohol International Learning College, Inc. | H8: Bohol International Learning Center Inc. | I8: Rex Fernan Uy | J8: De La Paz, Cortes, Bohol | K8: 9.6955985 | L8: 123.87494 | M8: (038) 503-9403, 09197686236 | N8: bilcph@gmail.com | O8: Private | P8: TVI | Q8: WTR | R8: Tourism | S8: Bread and Pastry Production NC II | T8: NC II | U8: 141 hours | V8: WTR No. 201607012040 | W8: 45365 | X8: 47192 | Y8: Theresa Mhae Garay Evangeline B. Samputon Ezra A. Guadalquiver | Z8: NTTC No. 201607121200208 NTTC No. 211907121200388 NTTC No. 201907121200296 | AC8: 42447
A9: VII | B9: Bohol | C9: 1st | D9: Cortes | E9: 5th | F9: {=IFERROR(INDEX(UIID!$K$2:$K354, MATCH(CONCATENATE(B9,D9,G9,J9), UIID!$B$2:$B354&UIID!$D$2:$D354&UIID!$G$2:$G354&UIID!$H$2:$H354, 0),), "Not Found")} -> 0712-0034 | G9: Bohol International Learning College, Inc. | H9: Bohol International Learning Center Inc. | I9: Rex Fernan Uy | J9: De La Paz, Cortes, Bohol | K9: 9.6955985 | L9: 123.87494 | M9: (038) 503-9403, 09197686236 | N9: bilcph@gmail.com | O9: Private | P9: TVI | Q9: WTR | R9: Tourism | S9: Food and Beverage Services NC II | T9: NC II | U9: 356 Hours | V9: 201507012093 | W9: 45365 | X9: 47192 | Y9: Marco Joshua Sarigumba | Z9: NTTC No. 191907121200311 | AA9: 45387 | AB9: C | AC9: 42156
A10: VII | B10: Bohol | C10: 1st | D10: Cortes | E10: 5th | F10: {=IFERROR(INDEX(UIID!$K$2:$K354, MATCH(CONCATENATE(B10,D10,G10,J10), UIID!$B$2:$B354&UIID!$D$2:$D354&UIID!$G$2:$G354&UIID!$H$2:$H354, 0),), "Not Found")} -> 0712-0034 | G10: Bohol International Learning College, Inc. | H10: Bohol International Learning Center Inc. | I10: Rex Fernan Uy | J10: De La Paz, Cortes, Bohol | K10: 9.6955985 | L10: 123.87494 | M10: (038) 503-9403, 09197686236 | N10: bilcph@gmail.com | O10: Private | P10: TVI | Q10: WTR | R10: Tourism | S10: Cookery NC II | T10: NC II | U10: 316 hours | V10: WTR No. 20170712TRSCOKK214177 | W10: 45365 | X10: 47192 | Y10: Editha R. Sarigumba Marco Joshua Sarigumba | Z10: NTTC No. 191907121200088 NTTC No. 191907121200316 | AA10: 45387 | AB10: C | AC10: 43007
A11: VII | B11: Bohol | C11: 2nd | D11: Ubay | E11: 1st | F11: {=IFERROR(INDEX(UIID!$K$2:$K354, MATCH(CONCATENATE(B11,D11,G11,J11), UIID!$B$2:$B354&UIID!$D$2:$D354&UIID!$G$2:$G354&UIID!$H$2:$H354, 0),), "Not Found")} -> 0712-0002 | G11: Bohol Northern Star College, Inc. | I11: Leonarda D. Loayon,Ed.D. | J11: Poblacion, Ubay, Bohol | K11: 10.05404 | L11: 124.47083 | M11: (038) 510-1226 | N11: bnsc.inc@gmail.com | O11: Private | P11: TVI | Q11: WTR | R11: Metals and Engineering | S11: Shielded Metal Arc Welding (SMAW) NC II | T11: NC II | U11: 304 Hours | V11: 807012047 | W11: 45365 | X11: 47192 | Y11: Maximo O. Torrentira | Z11: NTTC No. 222107121200010 | AC11: 39650
A12: VII | B12: Bohol | C12: 2nd | D12: Ubay | E12: 1st | F12: {=IFERROR(INDEX(UIID!$K$2:$K354, MATCH(CONCATENATE(B12,D12,G12,J12), UIID!$B$2:$B354&UIID!$D$2:$D354&UIID!$G$2:$G354&UIID!$H$2:$H354, 0),), "Not Found")} -> 0712-0002 | G12: Bohol Northern Star College, Inc. | I12: Leonarda D. Loayon,Ed.D. | J12: Poblacion, Ubay, Bohol | K12: 10.05404 | L12: 124.47083 | M12: (038) 510-1226 | N12: bnsc.inc@gmail.com | O12: Private | P12: TVI | Q12: WTR | R12: Electrical and Electronics | S12: Electrical Installation and Maintenance NC II | T12: NC II | U12: 196 hours | V12: WTR No. 20180712ELCEIM215006 | W12: 45365 | X12: 47192 | Y12: Elmer A. Lopena | Z12: 222207121200331 | AC12: 43111
A13: VII | B13: Bohol | C13: 2nd | D13: Ubay | E13: 1st | F13: {=IFERROR(INDEX(UIID!$K$2:$K354, MATCH(CONCATENATE(B13,D13,G13,J13), UIID!$B$2:$B354&UIID!$D$2:$D354&UIID!$G$2:$G354&UIID!$H$2:$H354, 0),), "Not Found")} -> 0712-0002 | G13: Bohol Northern Star College, Inc. | I13: Leonarda D. Loayon,Ed.D. | J13: Poblacion, Ubay, Bohol | K13: 10.05404 | L13: 124.47083 | M13: (038) 510-1226 | N13: bnsc.inc@gmail.com | O13: Private | P13: TVI | Q13: WTR | R13: Tourism | S13: Cookery NC II | T13: NC II | U13: 316 hours | V13: 201507012058 | W13: 45365 | X13: 47192 | Y13: Jasmin A. Zarco | Z13: NTTC No. 191907121200115 | AA13: 45387 | AB13: C | AC13: 42109
A14: VII | B14: Bohol | C14: 2nd | D14: Ubay | E14: 1st | F14: {=IFERROR(INDEX(UIID!$K$2:$K354, MATCH(CONCATENATE(B14,D14,G14,J14), UIID!$B$2:$B354&UIID!$D$2:$D354&UIID!$G$2:$G354&UIID!$H$2:$H354, 0),), "Not Found")} -> 0712-0002 | G14: Bohol Northern Star College, Inc. | I14: Leonarda D. Loayon,Ed.D. | J14: Poblacion, Ubay, Bohol | K14: 10.05404 | L14: 124.47083 | M14: (038) 510-1226 | N14: bnsc.inc@gmail.com | O14: Private | P14: TVI | Q14: WTR | R14: Metals and Engineering | S14: Shielded Metal Arc Welding (SMAW) NC I | T14: NC I | U14: 268 Hours | V14: WTR No. 20170712MEEEAW106207 | W14: 45365 | X14: 47192 | Y14: Maximo O. Torrentira | Z14: NTTC No. 222107121200010 | AA14: 45387 | AB14: C | AC14: 43066
A15: VII | B15: Bohol | C15: 1st | D15: Tagbilaran City | E15: Component | F15: {=IFERROR(INDEX(UIID!$K$2:$K354, MATCH(CONCATENATE(B15,D15,G15,J15), UIID!$B$2:$B354&UIID!$D$2:$D354&UIID!$G$2:$G354&UIID!$H$2:$H354, 0),), "Not Found")} -> 0712-0008 | G15: Bohol Tech Voc, Inc. | I15: Ma. Sarah P. Gordoncillo | J15: Zamora St., Dao District, Tagbilaran City, Bohol | K15: 9.6588669 | L15: 123.87243 | M15: (038) 5013040/ 501-3041 | N15: boholtechvoc@gmaiil.com | O15: Private | P15: TVI | Q15: WTR | R15: Tourism | S15: Cookery NC II | T15: NC II | U15: 316 hours | V15: 201507012007 | W15: 45348 | X15: 47176 | Y15: Ligaya B. Soltes Judith A. Balaba | Z15: NTTC No. 211807121200063 NTTC No. 202007121200284 | AA15: 45387 | AB15: C | AC15: 42036
A16: VII | B16: Bohol | C16: 1st | D16: Tagbilaran City | E16: Component | F16: {=IFERROR(INDEX(UIID!$K$2:$K354, MATCH(CONCATENATE(B16,D16,G16,J16), UIID!$B$2:$B354&UIID!$D$2:$D354&UIID!$G$2:$G354&UIID!$H$2:$H354, 0),), "Not Found")} -> 0712-0008 | G16: Bohol Tech Voc, Inc. | I16: Ma. Sarah P. Gordoncillo | J16: Zamora St., Dao District, Tagbilaran City, Bohol | K16: 9.6588669 | L16: 123.87243 | M16: (038) 5013040/ 501-3041 | N16: boholtechvoc@gmaiil.com | O16: Private | P16: TVI | Q16: WTR | R16: Tourism | S16: Food and Beverage Services NC II | T16: NC II | U16: 356 Hours | V16: 201507012125 | W16: 45348 | X16: 47176 | Y16: Mark Gerald S. Tesorio Reymund Y. Hurboda | Z16: NTTC No. 222207121200203 NTTC No. 222207121200387 | AA16: 45387 | AB16: C | AC16: 42212
A17: VII | B17: Bohol | C17: 3rd | D17: Garcia Hernandez | E17: 4th | F17: {=IFERROR(INDEX(UIID!$K$2:$K354, MATCH(CONCATENATE(B17,D17,G17,J17), UIID!$B$2:$B354&UIID!$D$2:$D354&UIID!$G$2:$G354&UIID!$H$2:$H354, 0),), "Not Found")} -> 0712-0037 | G17: Bow and Arrow Institute of Technology, Inc. | I17: Ramonito B. Endozo | J17: East Lungsodaan, Garcia Hernandez, Bohol, Philippines 6307 | K17: 9.607597 | L17: 124.28668 | M17: 9308033037 | N17: bowandarrowit_edu.ph@yahoo.com | O17: Private | P17: TVI | Q17: WTR | R17: Automotive and Land Transportation | S17: Driving NC II | T17: NC II | U17: 174 hours | V17: 20220712ALTDRV204001 | W17: 45309 | X17: 47137 | Y17: Ramonito B. Endozo | Z17: NTTC No.212016021200065
A18: VII | B18: Bohol | C18: 3rd | D18: Garcia Hernandez | E18: 4th | F18: {=IFERROR(INDEX(UIID!$K$2:$K354, MATCH(CONCATENATE(B18,D18,G18,J18), UIID!$B$2:$B354&UIID!$D$2:$D354&UIID!$G$2:$G354&UIID!$H$2:$H354, 0),), "Not Found")} -> 0712-0037 | G18: Bow and Arrow Institute of Technology, Inc. | I18: Ramonito B. Endozo | J18: East Lungsodaan, Garcia Hernandez, Bohol, Philippines 6307 | K18: 9.607597 | L18: 124.28668 | M18: 9308033037 | N18: bowandarrowit_edu.ph@yahoo.com | O18: Private | P18: TVI | Q18: WTR | R18: Metals and Engineering | S18: Shielded Metal Arc Welding (SMAW) NC I | T18: NC I | U18: 268 Hours | V18: WTR No.20200712MEEEAW106011 | W18: 45309 | X18: 47137 | Y18: Joland S. Dejacto | Z18: NTTC No. 191907121200086 | AC18: 43857
A19: VII | B19: Bohol | C19: 3rd | D19: Garcia Hernandez | E19: 4th | F19: {=IFERROR(INDEX(UIID!$K$2:$K354, MATCH(CONCATENATE(B19,D19,G19,J19), UIID!$B$2:$B354&UIID!$D$2:$D354&UIID!$G$2:$G354&UIID!$H$2:$H354, 0),), "Not Found")} -> 0712-0037 | G19: Bow and Arrow Institute of Technology, Inc. | I19: Ramonito B. Endozo | J19: East Lungsodaan, Garcia Hernandez, Bohol, Philippines 6307 | K19: 9.607597 | L19: 124.28668 | M19: 9308033037 | N19: bowandarrowit_edu.ph@yahoo.com | O19: Private | P19: TVI | Q19: WTR | R19: Metals and Engineering | S19: Shielded Metal Arc Welding (SMAW) NC II | T19: NC II | U19: 268 Hours | V19: WTR No.20200712MEEEAW206012 | W19: 45309 | X19: 47137 | Y19: Joland S. Dejacto | Z19: NTTC No. 191907121300087 | AC19: 43857
A20: VII | B20: Bohol | C20: 3rd | D20: Garcia Hernandez | E20: 4th | F20: {=IFERROR(INDEX(UIID!$K$2:$K354, MATCH(CONCATENATE(B20,D20,G20,J20), UIID!$B$2:$B354&UIID!$D$2:$D354&UIID!$G$2:$G354&UIID!$H$2:$H354, 0),), "Not Found")} -> 0712-0037 | G20: Bow and Arrow Institute of Technology, Inc. | I20: Jellian Jade P. Carpio | J20: Dahay St., Tabuan, Garcia Hernandez, Bohol | K20: 9.668132 | L20: 124.29157 | M20: 9308033037 | N20: bowandarrowit_edu.ph@yahoo.com | O20: Private | P20: TVI | Q20: WTR | R20: Tourism | S20: Cookery NC II | T20: NC II | U20: 316 hours | V20: WTR No. 20180712TRSCOK214060 | W20: 45309 | X20: 47137 | Y20: Jellian Jade P. Carpio | Z20: NTTC No. 212007121200384 | AC20: 43235
A21: VII | B21: Bohol | C21: 1st | D21: Baclayon | E21: 4th | F21: {=IFERROR(INDEX(UIID!$K$2:$K354, MATCH(CONCATENATE(B21,D21,G21,J21), UIID!$B$2:$B354&UIID!$D$2:$D354&UIID!$G$2:$G354&UIID!$H$2:$H354, 0),), "Not Found")} -> 0712-0012 | G21: CA-LIM Tech Training and Assessment Center, Inc. | I21: Venerando O. Limpot | J21: San Isidro, Baclayon, Bohol | K21: 9.6306066 | L21: 123.90154 | M21: 09077991075/ 09088979828 | N21: calimtech2017@gmail.com | O21: Private | P21: TVI | Q21: WTR | R21: Tourism | S21: Housekeeping NC II | T21: NC II | U21: 436 Hours | V21: 20190712TRSHSK213088 | W21: 45348 | X21: 47176 | Y21: Marcelita C. Timbal | Z21: NTTC No. 221907121200160 | AA21: 45415 | AB21: C | AC21: 43647
A22: VII | B22: Bohol | C22: 1st | D22: Baclayon | E22: 4th | F22: {=IFERROR(INDEX(UIID!$K$2:$K354, MATCH(CONCATENATE(B22,D22,G22,J22), UIID!$B$2:$B354&UIID!$D$2:$D354&UIID!$G$2:$G354&UIID!$H$2:$H354, 0),), "Not Found")} -> 0712-0012 | G22: CA-LIM Tech Training and Assessment Center, Inc. | I22: Venerando O. Limpot | J22: San Isidro, Baclayon, Bohol | K22: 9.6306066 | L22: 123.90154 | M22: 09077991075/ 09088979828 | N22: calimtech2017@gmail.com | O22: Private | P22: TVI | Q22: WTR | R22: Tourism | S22: Bread and Pastry Production NC II | T22: NC II | U22: 141 hours | V22: 20170712TRSBPP209197 | W22: 45348 | X22: 47176 | Y22: Marcelita C. Timbal | Z22: NTTC No. 191907121200089 | AA22: 45415 | AB22: C | AC22: 43038
A23: VII | B23: Bohol | C23: 1st | D23: Tagbilaran City | E23: Component | F23: {=IFERROR(INDEX(UIID!$K$2:$K354, MATCH(CONCATENATE(B23,D23,G23,J23), UIID!$B$2:$B354&UIID!$D$2:$D354&UIID!$G$2:$G354&UIID!$H$2:$H354, 0),), "Not Found")} -> 0712-0022 | G23: Can-Care Technical Vocational Education Training Assessment and Review Center Institute, Inc. | H23: (Formerly: Can-Care Technical Vocational Education Training Institute, Inc. ) (Formerly: Can-Care Caregiver Training and Development Center, Inc.) (Formerly: Can-Care Caregiver Training Assessment and Development Center, Inc.) | I23: Feliciano C. Agta, CPA - President | J23: 0229 Gallares Street, Poblacion II, Tagbilaran City, Bohol Philippines 6300 | K23: 9.6473124 | L23: 123.85178 | M23: (038) 5019722/ 411-4948/ 2915 | N23: cancarecaregiver2001@gmail.com | O23: Private | P23: TVI | Q23: WTR | R23: Human Health/ Health Care | S23: Caregiving NC II | T23: NC II | U23: 1074 Hours | V23: 20230712HHCCGV207001 | W23: 45225 | X23: 47053 | Y23: Rossini C. Birad Lhea D. Agta Jennifer L. Baldapan | Z23: NTTC No. 202007121200210 NTTC No. 191907121200272 NTTC No. 212107221200452 | AA23: 45387 | AB23: C | AC23: 44927
A24: VII | B24: Bohol | C24: 1st | D24: Tagbilaran City | E24: Component | F24: {=IFERROR(INDEX(UIID!$K$2:$K354, MATCH(CONCATENATE(B24,D24,G24,J24), UIID!$B$2:$B354&UIID!$D$2:$D354&UIID!$G$2:$G354&UIID!$H$2:$H354, 0),), "Not Found")} -> 0712-0022 | G24: Can-Care Technical Vocational Education Training Assessment and Review Center Institute, Inc. | H24: (Formerly: Can-Care Technical Vocational Education Training Institute, Inc. ) (Formerly: Can-Care Caregiver Training and Development Center, Inc.) (Formerly: Can-Care Caregiver Training Assessment and Development Center, Inc.) | I24: Feliciano C. Agta, CPA - President | J24: 0229 Gallares Street, Poblacion II, Tagbilaran City, Bohol Philippines 6300 | K24: 9.6473124 | L24: 123.85178 | M24: (038) 427-5117, 09199377243, 09195862870 | N24: cancarecaregiver2001@gmail.com | O24: Private | P24: TVI | Q24: RTP | R24: Others (Languages) | S24: Japanese Language | T24: N/A | U24: 800 hours | V24: NTR No. 202207120015 | W24: 44809 | X24: 46634 | Y24: Jervin Kenneth M. Balignasay | Z24: TMC No. 16043401000098 | AA24: 45146 | AB24: C
A25: VII | B25: Bohol | C25: 1st | D25: Tagbilaran City | E25: Component | F25: {=IFERROR(INDEX(UIID!$K$2:$K354, MATCH(CONCATENATE(B25,D25,G25,J25), UIID!$B$2:$B354&UIID!$D$2:$D354&UIID!$G$2:$G354&UIID!$H$2:$H354, 0),), "Not Found")} -> 0712-0022 | G25: Can-Care Technical Vocational Education Training Assessment and Review Center Institute, Inc. | H25: (Formerly: Can-Care Technical Vocational Education Training Institute, Inc. ) (Formerly: Can-Care Caregiver Training and Development Center, Inc.) (Formerly: Can-Care Caregiver Training Assessment and Development Center, Inc.) | I25: Feliciano C. Agta, CPA - President | J25: 0229 Gallares Street, Poblacion II, Tagbilaran City, Bohol Philippines 6300 | K25: 9.6473124 | L25: 123.85178 | M25: (038) 5019722/ 411-4948 | N25: cancarecaregiver2001@gmail.com | O25: Private | P25: TVI | Q25: WTR | R25: Human Health/ Health Care | S25: Health Care Services NC II | T25: NC II | U25: 996 hours | V25: 20220712HHCHCS205032 | W25: 45289 | X25: 47120 | Y25: Rossini C. Birad | Z25: 151407121200174 | AA25: 45146 | AB25: C
A26: VII | B26: Bohol | C26: 1st | D26: Tagbilaran City | E26: Component | F26: {=IFERROR(INDEX(UIID!$K$2:$K354, MATCH(CONCATENATE(B26,D26,G26,J26), UIID!$B$2:$B354&UIID!$D$2:$D354&UIID!$G$2:$G354&UIID!$H$2:$H354, 0),), "Not Found")} -> 0712-0035 | G26: Eldecare Institute of Technology, Inc. | I26: Lhea D. Agta | J26: Brgy. Taloto, Tagbilaran City, Bohol | K26: 9.6820803 | L26: 123.85744 | M26: (038)427-5117; 09199377243; 09195862870 | N26: eldecareinstitute@gmail.com | O26: Private | P26: TVI | Q26: WTR | R26: Tourism | S26: Cookery NC II | T26: NC II | U26: 316 hours | V26: WTR No. 201607122140 | W26: 45289 | X26: 47120 | Y26: Alfie D. Mahumot Bernard P. Tacumba Judith A. Balaba | Z26: NTTC No. 151407121200391 NTTC No. 191907121200212 NTTC No. 202007121200284 | AA26: 45751 | AB26: C | AC26: 42572
A27: VII | B27: Bohol | C27: 1st | D27: Tagbilaran City | E27: Component | F27: {=IFERROR(INDEX(UIID!$K$2:$K354, MATCH(CONCATENATE(B27,D27,G27,J27), UIID!$B$2:$B354&UIID!$D$2:$D354&UIID!$G$2:$G354&UIID!$H$2:$H354, 0),), "Not Found")} -> 0712-0035 | G27: Eldecare Institute of Technology, Inc. | I27: Lhea D. Agta | J27: Brgy. Taloto, Tagbilaran City, Bohol | K27: 9.6820803 | L27: 123.85744 | M27: (038)427-5117; 09199377243; 09195862870 | N27: eldecareinstitute@gmail.com | O27: Private | P27: TVI | Q27: WTR | R27: Tourism | S27: Food and Beverage Services NC II | T27: NC II | U27: 356 hours | V27: WTR No. 201607122141 | W27: 45524 | X27: 47351 | Y27: Leah D. Agta Ma. Riza T. Gajelan Maria Minda C. Dehing | Z27: Not indicated | AC27: 42572
A28: VII | B28: Bohol | C28: 3rd | D28: Garcia Hernandez | E28: 4th | F28: {=IFERROR(INDEX(UIID!$K$2:$K354, MATCH(CONCATENATE(B28,D28,G28,J28), UIID!$B$2:$B354&UIID!$D$2:$D354&UIID!$G$2:$G354&UIID!$H$2:$H354, 0),), "Not Found")} -> 0712-0031 | G28: Joanne School of Technology Inc. | I28: Anflorina S. Naldoza, Ph.D | J28: Tabuan, Garcia Hernandez, Bohol | K28: 9.6636951 | L28: 124.29107 | M28: 9092712102 | N28: jstitabuan@gmail.com | O28: Private | P28: TVI | Q28: WTR | R28: Tourism | S28: Food and Beverage Services NC II | T28: NC II | U28: 356 Hours | V28: WTR No. 201507012203 | W28: 45316 | X28: 47144 | Y28: Jomar R. Lectana | Z28: 211907121200002 | AA28: 45387 | AB28: C | AC28: 42326
A29: VII | B29: Bohol | C29: 3rd | D29: Garcia Hernandez | E29: 4th | F29: {=IFERROR(INDEX(UIID!$K$2:$K354, MATCH(CONCATENATE(B29,D29,G29,J29), UIID!$B$2:$B354&UIID!$D$2:$D354&UIID!$G$2:$G354&UIID!$H$2:$H354, 0),), "Not Found")} -> 0712-0031 | G29: Joanne School of Technology Inc. | I29: Anflorina S. Naldoza, Ph.D | J29: Tabuan, Garcia Hernandez, Bohol | K29: 9.6636951 | L29: 124.29107 | M29: 9092712102 | N29: jstitabuan@gmail.com | O29: Private | P29: TVI | Q29: WTR | R29: Tourism | S29: Cookery NC II | T29: NC II | U29: 316 hours | V29: 20180712TRSCOK214038 | W29: 45316 | X29: 47144 | Y29: Jomar R. Lectana Mark Anthony A. Ocleda | Z29: NTTC No. 201907121200198 NTTC No. 211907121200225 | AC29: 43203
A30: VII | B30: Bohol | C30: 3rd | D30: Garcia Hernandez | E30: 4th | F30: {=IFERROR(INDEX(UIID!$K$2:$K354, MATCH(CONCATENATE(B30,D30,G30,J30), UIID!$B$2:$B354&UIID!$D$2:$D354&UIID!$G$2:$G354&UIID!$H$2:$H354, 0),), "Not Found")} -> 0712-0031 | G30: Joanne School of Technology Inc. | I30: Anflorina S. Naldoza, Ph.D | J30: Tabuan, Garcia Hernandez, Bohol | K30: 9.6636951 | L30: 124.29107 | M30: 9092712102 | N30: jstitabuan@gmail.com | O30: Private | P30: TVI | Q30: WTR | R30: Metals and Engineering | S30: Shielded Metal Arc Welding (SMAW) NC II | T30: NC II | U30: 268 Hours | V30: WTR No. 201607012072 | W30: 45316 | X30: 47144 | Y30: JC Keyness T. Gunday Jay T. Valentos Domingo L. Ocmeja | Z30: NTTC No. 201607121200228 NTTC No. 221807121200463 NTTC No. 191707121200262 | AC30: 42479
A31: VII | B31: Bohol | C31: 3rd | D31: Garcia Hernandez | E31: 4th | F31: {=IFERROR(INDEX(UIID!$K$2:$K354, MATCH(CONCATENATE(B31,D31,G31,J31), UIID!$B$2:$B354&UIID!$D$2:$D354&UIID!$G$2:$G354&UIID!$H$2:$H354, 0),), "Not Found")} -> 0712-0031 | G31: Joanne School of Technology Inc. | I31: Anflorina S. Naldoza, Ph.D | J31: Tabuan, Garcia Hernandez, Bohol | K31: 9.6636951 | L31: 124.29107 | M31: 9092712102 | N31: jstitabuan@gmail.com | O31: Private | P31: TVI | Q31: WTR | R31: Metals and Engineering | S31: Shielded Metal Arc Welding (SMAW) NC I | T31: NC I | U31: 268 Hours | V31: WTR No. 20170712MEEEAW106168 | W31: 45316 | X31: 47144 | Y31: JC Keyness T. Gunday Jay T. Valentos Domingo L. Ocmeja | Z31: NTTC No. 201607121200228 NTTC No. 221807121200463 NTTC No. 191707121200262 | AA31: 45387 | AB31: C | AC31: 43000
A32: VII | B32: Bohol | C32: 2nd | D32: Talibon | E32: 1st | F32: {=IFERROR(INDEX(UIID!$K$2:$K354, MATCH(CONCATENATE(B32,D32,G32,J32), UIID!$B$2:$B354&UIID!$D$2:$D354&UIID!$G$2:$G354&UIID!$H$2:$H354, 0),), "Not Found")} -> 0712-0036 | G32: North Coast Bohol Institute Inc. | I32: Grace Artiaga | J32: San Francisco, Talibon, Bohol | K32: 10.142418 | L32: 124.31639 | M32: (038) 515-5207/09206320930/ 09098822924 | N32: louiegrace_tiags@yahoo.com.ph | O32: Private | P32: TVI | Q32: WTR | R32: Information and Communication Technology | S32: Visual Graphic Design NC III | T32: NC III | U32: 541 hours | V32: 20210712ICTVGD318097 | W32: 45261 | X32: 47091 | Y32: Glenn L. Huraño | Z32: NTTC No. 191607121300146 | AA32: 45387 | AB32: C | AC32: 44543
A33: VII | B33: Bohol | C33: 2nd | D33: Talibon | E33: 1st | F33: {=IFERROR(INDEX(UIID!$K$2:$K354, MATCH(CONCATENATE(B33,D33,G33,J33), UIID!$B$2:$B354&UIID!$D$2:$D354&UIID!$G$2:$G354&UIID!$H$2:$H354, 0),), "Not Found")} -> 0712-0036 | G33: North Coast Bohol Institute Inc. | I33: Grace Artiaga | J33: San Francisco, Talibon, Bohol | K33: 10.142418 | L33: 124.31639 | M33: (038) 515-5207/09206320930/ 09098822924 | N33: louiegrace_tiags@yahoo.com.ph | O33: Private | P33: TVI | Q33: WTR | R33: Social, Community Development and Other Services | S33: Bookkeeping NC III | T33: NC III | U33: 292 hours | V33: WTR No. 20170712SOCBKP308188 | W33: 45261 | X33: 47091 | Y33: Cristor N. Langamen Joanne Greg C. Ayag | Z33: NTTC No. 201907121300066 NTTC No. 222207121300598 | AA33: 45387 | AB33: C | AC33: 43021
A34: VII | B34: Bohol | C34: 2nd | D34: Talibon | E34: 1st | F34: {=IFERROR(INDEX(UIID!$K$2:$K354, MATCH(CONCATENATE(B34,D34,G34,J34), UIID!$B$2:$B354&UIID!$D$2:$D354&UIID!$G$2:$G354&UIID!$H$2:$H354, 0),), "Not Found")} -> 0712-0036 | G34: North Coast Bohol Institute Inc. | I34: Grace Artiaga | J34: San Francisco, Talibon, Bohol | K34: 10.142418 | L34: 124.31639 | M34: (038) 515-5633 | N34: louiegrace_tiags@yahoo.com.ph | O34: Private | P34: TVI | Q34: WTR | R34: TVET | S34: Trainers Methodology Level I (Trainer/Assessor) | T34: Level I | U34: 264 Hours | V34: WTR No.20190712TVETRM111063 | W34: 45261 | X34: 47091 | Y34: Raul S. Ambe | Z34: TMC No.19071201019857 | AA34: 45387 | AB34: C | AC34: 43608
A35: VII | B35: Bohol | C35: 2nd | D35: Talibon | E35: 1st | F35: {=IFERROR(INDEX(UIID!$K$2:$K354, MATCH(CONCATENATE(B35,D35,G35,J35), UIID!$B$2:$B354&UIID!$D$2:$D354&UIID!$G$2:$G354&UIID!$H$2:$H354, 0),), "Not Found")} -> 0712-0036 | G35: North Coast Bohol Institute Inc. | I35: Grace Artiaga | J35: San Francisco, Talibon, Bohol | K35: 10.142418 | L35: 124.31639 | M35: (038) 515-5207/09206320930/ 09098822924 | N35: louiegrace_tiags@yahoo.com.ph | O35: Private | P35: TVI | Q35: WTR | R35: Electrical and Electronics | S35: Computer Systems Servicing NC II | T35: NC II | U35: 260 hours | V35: WTR No. 20171712ELCCSS213189 | W35: 45261 | X35: 47091 | Y35: Claudio S> Melencion Jr. Julito B. Judilla Raul S. Ambe | Z35: NTTC No. 151417121200205 NTTC No. 181607121200087 NTTC No. 201907121200224 | AA35: 45387 | AB35: C | AC35: 43021
A36: VII | B36: Bohol | C36: 1st | D36: Tagbilaran City | E36: Component | F36: {=IFERROR(INDEX(UIID!$K$2:$K354, MATCH(CONCATENATE(B36,D36,G36,J36), UIID!$B$2:$B354&UIID!$D$2:$D354&UIID!$G$2:$G354&UIID!$H$2:$H354, 0),), "Not Found")} -> 0712-0024 | G36: PBB Culinary Tutorial Center Inc. | I36: Charles Henry O. Bayonas | J36: Purok 3, Peñaflor Street, Taloto, Tagbilaran City, Bohol | K36: 9.6723878 | L36: 123.8536 | M36: (038)412-4781 / 0919-879-5683 | N36: pbb.culinary@gmail.com | O36: Private | P36: TVI | Q36: RTP | R36: Tourism | S36: Finishing Course for International Cooks | T36: N/A | U36: 120 hours | V36: NTR 201507010138 | W36: 45083 | X36: 46911 | Y36: Evangeline B. Samputon | Z36: NTTC No. 191907121200441 | AA36: 45516 | AB36: C | AC36: 42220
A37: VII | B37: Bohol | C37: 1st | D37: Tagbilaran City | E37: Component | F37: {=IFERROR(INDEX(UIID!$K$2:$K354, MATCH(CONCATENATE(B37,D37,G37,J37), UIID!$B$2:$B354&UIID!$D$2:$D354&UIID!$G$2:$G354&UIID!$H$2:$H354, 0),), "Not Found")} -> 0712-0033 | G37: Philippine Call Center Institute Inc. | I37: Kristelle Lynne P. Ong | J37: 2/F, QVC Building, CPG North Ave., Tagbilaran City, Bohol | K37: 9.6485037 | L37: 123.85523 | M37: (038)4175734 | N37: pcci.bohol1@gmail.com | O37: Private | P37: TVI | Q37: WTR | R37: Information and Communication Technology | S37: Contact Center Services NC II | T37: NC II | U37: 144 Hours | V37: WTR No. 201607012032 | W37: 45434 | X37: 47261 | Y37: Marlis L. Badiang Alexia Kaye A. Bansale Harold C. Guivencan Jandy Lee K. Dahunog Michael E. Morcozo Vida B. Molina | Z37: TMC No. 15070201000275 TMC No. 21130701024356 TMC No. 21130701024348 TMC No. 19072201036345 TMC No. 19083701000170 TMC No. 19083701000169 | AC37: 42444
A38: VII | B38: Bohol | C38: 3rd | D38: Bilar | E38: 4th | F38: {=IFERROR(INDEX(UIID!$K$2:$K354, MATCH(CONCATENATE(B38,D38,G38,J38), UIID!$B$2:$B354&UIID!$D$2:$D354&UIID!$G$2:$G354&UIID!$H$2:$H354, 0),), "Not Found")} -> 0712-0003 | G38: Provincial Training Center - Bilar | I38: Rochelle I. Delos Reyes, Center Administrator | J38: Poblacion, Bilar, Bohol | K38: 9.7021431 | L38: 124.10275 | M38: (038) 411-5228; 09302443241 | N38: ptcbilar@tesda.gov.ph | O38: Public | P38: TTI | Q38: WTR | R38: Social, Community Development and Other Services | S38: Bookkeeping NC III | T38: NC III | U38: 452 hours | V38: 20220712SOCBKP307015 | W38: 45342 | X38: 47170 | Y38: Christine N. Ollamina | Z38: NTTC No.222107121300004
A39: VII | B39: Bohol | C39: 3rd | D39: Bilar | E39: 4th | F39: {=IFERROR(INDEX(UIID!$K$2:$K354, MATCH(CONCATENATE(B39,D39,G39,J39), UIID!$B$2:$B354&UIID!$D$2:$D354&UIID!$G$2:$G354&UIID!$H$2:$H354, 0),), "Not Found")} -> 0712-0003 | G39: Provincial Training Center - Bilar | I39: Rochelle I. Delos Reyes, Center Administrator | J39: Poblacion, Bilar, Bohol | K39: 9.7021431 | L39: 124.10275 | M39: (038) 411-5228; 09302443241 | N39: ptcbilar@tesda.gov.ph | O39: Public | P39: TTI | Q39: WTR | R39: Tourism | S39: Events Management Services NC III | T39: NC III | U39: 358 hours | V39: 20210712TRSEVM307082 | W39: 45342 | X39: 47170 | Y39: Alfie D. Mahumot | Z39: NTTC No. 211907121300361 | AA39: 45418 | AB39: C | AC39: 44473
A40: VII | B40: Bohol | C40: 3rd | D40: Bilar | E40: 4th | F40: {=IFERROR(INDEX(UIID!$K$2:$K354, MATCH(CONCATENATE(B40,D40,G40,J40), UIID!$B$2:$B354&UIID!$D$2:$D354&UIID!$G$2:$G354&UIID!$H$2:$H354, 0),), "Not Found")} -> 0712-0003 | G40: Provincial Training Center - Bilar | I40: Rochelle I. Delos Reyes, Center Administrator | J40: Poblacion, Bilar, Bohol | K40: 9.7021431 | L40: 124.10275 | M40: (038) 411-5228; 09302443241 | N40: ptcbilar@tesda.gov.ph | O40: Public | P40: TTI | Q40: WTR | R40: Electrical and Electronics | S40: Electrical Installation and Maintenance NC III | T40: NC III | U40: 160 Hours | V40: 20200712ELCEIM315074 | W40: 45342 | X40: 47170 | Y40: Jesus M. Galan | Z40: NTTC No. 232307121300076 | AC40: 44168
A41: VII | B41: Bohol | C41: 3rd | D41: Bilar | E41: 4th | F41: {=IFERROR(INDEX(UIID!$K$2:$K354, MATCH(CONCATENATE(B41,D41,G41,J41), UIID!$B$2:$B354&UIID!$D$2:$D354&UIID!$G$2:$G354&UIID!$H$2:$H354, 0),), "Not Found")} -> 0712-0003 | G41: Provincial Training Center - Bilar | I41: Rochelle I. Delos Reyes, Center Administrator | J41: Poblacion, Bilar, Bohol | K41: 9.7021431 | L41: 124.10275 | M41: (038) 411-5228; 09302443241 | N41: ptcbilar@tesda.gov.ph | O41: Public | P41: TTI | Q41: WTR | R41: Agriculture, Forestry and Fishery | S41: Rice Machinery Operations NC II | T41: NC II | U41: 232 Hours | V41: 20190712AFFRMO207127 | W41: 45342 | X41: 46833 | Y41: Ramil P. Parojinog | Z41: NTTC No. 191907121200197 | AA41: 45418 | AB41: C | AC41: 43752
A42: VII | B42: Bohol | C42: 3rd | D42: Bilar | E42: 4th | F42: {=IFERROR(INDEX(UIID!$K$2:$K354, MATCH(CONCATENATE(B42,D42,G42,J42), UIID!$B$2:$B354&UIID!$D$2:$D354&UIID!$G$2:$G354&UIID!$H$2:$H354, 0),), "Not Found")} -> 0712-0003 | G42: Provincial Training Center - Bilar | I42: Rochelle I. Delos Reyes, Center Administrator | J42: Poblacion, Bilar, Bohol | K42: 9.7021431 | L42: 124.10275 | M42: (038) 411-5228; 09302443241 | N42: ptcbilar@tesda.gov.ph | O42: Public | P42: TTI | Q42: WTR | R42: Automotive and Land Transportation | S42: Motorcycle/Small Engine Servicing NC II | T42: NC II | U42: 650 hours | V42: 20180712ALTMSE215118 | W42: 45342 | X42: 47170 | Y42: Benito A. Requillo | Z42: NTTC No. 211807121200363 | AC42: 43334
A43: VII | B43: Bohol | C43: 3rd | D43: Bilar | E43: 4th | F43: {=IFERROR(INDEX(UIID!$K$2:$K354, MATCH(CONCATENATE(B43,D43,G43,J43), UIID!$B$2:$B354&UIID!$D$2:$D354&UIID!$G$2:$G354&UIID!$H$2:$H354, 0),), "Not Found")} -> 0712-0003 | G43: Provincial Training Center - Bilar | I43: Rochelle I. Delos Reyes, Center Administrator | J43: Poblacion, Bilar, Bohol | K43: 9.7021431 | L43: 124.10275 | M43: (038) 411-5228; 09302443241 | N43: ptcbilar@tesda.gov.ph | O43: Public | P43: TTI | Q43: WTR | R43: Automotive and Land Transportation | S43: Driving NC II | T43: NC II | U43: 118 Hours | V43: 907012039 | W43: 45342 | X43: 47170 | Y43: Benito A. Requillo | Z43: NTTC No. 181807121200376 | AA43: 45418 | AB43: C | AC43: 39933
A44: VII | B44: Bohol | C44: 3rd | D44: Bilar | E44: 4th | F44: {=IFERROR(INDEX(UIID!$K$2:$K354, MATCH(CONCATENATE(B44,D44,G44,J44), UIID!$B$2:$B354&UIID!$D$2:$D354&UIID!$G$2:$G354&UIID!$H$2:$H354, 0),), "Not Found")} -> 0712-0003 | G44: Provincial Training Center - Bilar | I44: Rochelle I. Delos Reyes, Center Administrator | J44: Poblacion, Bilar, Bohol | K44: 9.7021431 | L44: 124.10275 | M44: (038) 411-5228; 09302443241 | N44: ptcbilar@tesda.gov.ph | O44: Public | P44: TTI | Q44: WTR | R44: Construction | S44: Carpentry NC II | T44: NC II | U44: 301 hours | V44: 20200712CONCAR218022 | W44: 45010 | X44: 46838 | Y44: Churchill P. Belano | Z44: NTTC No. 191907121200426 | AA44: 45821 | AB44: C | AC44: 43923
A45: VII | B45: Bohol | C45: 3rd | D45: Bilar | E45: 4th | F45: {=IFERROR(INDEX(UIID!$K$2:$K354, MATCH(CONCATENATE(B45,D45,G45,J45), UIID!$B$2:$B354&UIID!$D$2:$D354&UIID!$G$2:$G354&UIID!$H$2:$H354, 0),), "Not Found")} -> 0712-0003 | G45: Provincial Training Center - Bilar | I45: Rochelle I. Delos Reyes, Center Administrator | J45: Poblacion, Bilar, Bohol | K45: 9.7021431 | L45: 124.10275 | M45: (038) 411-5228; 09302443241 | N45: ptcbilar@tesda.gov.ph | O45: Public | P45: TTI | Q45: WTR | R45: Electrical and Electronics | S45: Electrical Installation and Maintenance NC II | T45: NC II | U45: 196 hours | V45: WTR No. 20180712ELCEIM215027 | W45: 45342 | X45: 47170 | Y45: Jesus M. Galan | Z45: NTTC No. 2323071200075 | AC45: 43174
A46: VII | B46: Bohol | C46: 3rd | D46: Bilar | E46: 4th | F46: {=IFERROR(INDEX(UIID!$K$2:$K354, MATCH(CONCATENATE(B46,D46,G46,J46), UIID!$B$2:$B354&UIID!$D$2:$D354&UIID!$G$2:$G354&UIID!$H$2:$H354, 0),), "Not Found")} -> 0712-0003 | G46: Provincial Training Center - Bilar | I46: Rochelle I. Delos Reyes, Center Administrator | J46: Poblacion, Bilar, Bohol | K46: 9.7021431 | L46: 124.10275 | M46: (038) 411-5228; 09302443241 | N46: ptcbilar@tesda.gov.ph | O46: Public | P46: TTI | Q46: WTR | R46: Tourism | S46: Cookery NC II | T46: NC II | U46: 316 hours | V46: 201407012115 | W46: 45342 | X46: 47170 | Y46: Alfie D. Mahumot Efrelyn L. Lapitan | Z46: NTTC No. 201907121200199 NTTC No. 191907121200486 | AC46: 41831
A47: VII | B47: Bohol | C47: 3rd | D47: Bilar | E47: 4th | F47: {=IFERROR(INDEX(UIID!$K$2:$K354, MATCH(CONCATENATE(B47,D47,G47,J47), UIID!$B$2:$B354&UIID!$D$2:$D354&UIID!$G$2:$G354&UIID!$H$2:$H354, 0),), "Not Found")} -> 0712-0003 | G47: Provincial Training Center - Bilar | I47: Rochelle I. Delos Reyes, Center Administrator | J47: Poblacion, Bilar, Bohol | K47: 9.7021431 | L47: 124.10275 | M47: (038) 411-5228; 09302443241 | N47: ptcbilar@tesda.gov.ph | O47: Public | P47: TTI | Q47: WTR | R47: Tourism | S47: Bread and Pastry Production NC II | T47: NC II | U47: 141 hours | V47: WTR No. 201707122038 | W47: 45342 | X47: 47170 | Y47: Efrelyn L. Lapitan | Z47: NTTC No. 181407121200242 | AA47: 45418 | AB47: C | AC47: 42809
A48: VII | B48: Bohol | C48: 2nd | D48: Inabanga | E48: 3rd | F48: {=IFERROR(INDEX(UIID!$K$2:$K354, MATCH(CONCATENATE(B48,D48,G48,J48), UIID!$B$2:$B354&UIID!$D$2:$D354&UIID!$G$2:$G354&UIID!$H$2:$H354, 0),), "Not Found")} -> 0712-0004 | G48: Provincial Training Center - Inabanga | I48: Jaminel A. Damolo, Center Administrator | J48: Cagayan, Inabanga, Bohol | K48: 10.05135 | L48: 124.07921 | M48: (038) 512-9012 | N48: ptcinabanga@tesda.gov.ph | O48: Public | P48: TTI | Q48: WTR | R48: Tourism | S48: Bread and Pastry Production NC II | T48: NC II | U48: 141 Hours | V48: 20200712TRSBPP209089 | W48: 45365 | X48: 47192 | Y48: Michelle P. Aranas | Z48: NTTC No. 222007121200579 | AC48: 44180
A49: VII | B49: Bohol | C49: 2nd | D49: Inabanga | E49: 3rd | F49: {=IFERROR(INDEX(UIID!$K$2:$K354, MATCH(CONCATENATE(B49,D49,G49,J49), UIID!$B$2:$B354&UIID!$D$2:$D354&UIID!$G$2:$G354&UIID!$H$2:$H354, 0),), "Not Found")} -> 0712-0004 | G49: Provincial Training Center - Inabanga | I49: Jaminel A. Damolo, Center Administrator | J49: Cagayan, Inabanga, Bohol | K49: 10.05135 | L49: 124.07921 | M49: (038) 512-9012 | N49: ptcinabanga@tesda.gov.ph | O49: Public | P49: TTI | Q49: WTR | R49: Electrical and Electronics | S49: Electrical Installation and Maintenance NC II | T49: NC II | U49: 196 hours | V49: 20170712ELCEIM215210 | W49: 45365 | X49: 47192 | Y49: Leonard Basil L. Algarme | Z49: NTTC No. 222207121200383 | AA49: 45406 | AB49: C | AC49: 43074
A50: VII | B50: Bohol | C50: 2nd | D50: Inabanga | E50: 3rd | F50: {=IFERROR(INDEX(UIID!$K$2:$K354, MATCH(CONCATENATE(B50,D50,G50,J50), UIID!$B$2:$B354&UIID!$D$2:$D354&UIID!$G$2:$G354&UIID!$H$2:$H354, 0),), "Not Found")} -> 0712-0004 | G50: Provincial Training Center - Inabanga | I50: Jaminel A. Damolo, Center Administrator | J50: Cagayan, Inabanga, Bohol | K50: 10.05135 | L50: 124.07921 | M50: (038) 512-9012 / 09219715252 | N50: ptcinabanga@tesda.gov.ph | O50: Public | P50: TTI | Q50: WTR | R50: Construction | S50: Masonry NC II | T50: NC II | U50: 181 Hours | V50: 20190712CONMAS218149 | W50: 45010 | X50: 46838 | Y50: Churchill P. Belano | Z50: NTTC No. 191907121200295 | AA50: 45405 | AB50: C | AC50: 43756
A51: VII | B51: Bohol | C51: 2nd | D51: Inabanga | E51: 3rd | F51: {=IFERROR(INDEX(UIID!$K$2:$K354, MATCH(CONCATENATE(B51,D51,G51,J51), UIID!$B$2:$B354&UIID!$D$2:$D354&UIID!$G$2:$G354&UIID!$H$2:$H354, 0),), "Not Found")} -> 0712-0004 | G51: Provincial Training Center - Inabanga | I51: Jaminel A. Damolo, Center Administrator | J51: Cagayan, Inabanga, Bohol | K51: 10.05135 | L51: 124.07921 | M51: (038) 512-9012 / 09219715252 | N51: ptcinabanga@tesda.gov.ph | O51: Public | P51: TTI | Q51: WTR | R51: Automotive and Land Transportation | S51: Driving NC II | T51: NC II | U51: 118 Hours | V51: 20190712ALTDRV204125 | W51: 45365 | X51: 47192 | Y51: Ronie T. Razona Jesus M. Galan Benito A. Requillo | Z51: NTTC No. 202007121200270 NTTC No. 181707121200052 NTTC No. 181807121200376 | AA51: 45405 | AB51: C | AC51: 43752
A52: VII | B52: Bohol | C52: 2nd | D52: Inabanga | E52: 3rd | F52: {=IFERROR(INDEX(UIID!$K$2:$K354, MATCH(CONCATENATE(B52,D52,G52,J52), UIID!$B$2:$B354&UIID!$D$2:$D354&UIID!$G$2:$G354&UIID!$H$2:$H354, 0),), "Not Found")} -> 0712-0004 | G52: Provincial Training Center - Inabanga | I52: Jaminel A. Damolo, Center Administrator | J52: Cagayan, Inabanga, Bohol | K52: 10.05135 | L52: 124.07921 | M52: (038) 512-9012 | N52: ptcinabanga@tesda.gov.ph | O52: Public | P52: TTI | Q52: WTR | R52: Electrical and Electronics | S52: Electrical Installation and Maintenance NC III | T52: NC III | U52: 160 hours | V52: WTR No. 20180712ELCEIM315050 | W52: 45010 | X52: 46838 | Y52: Leonard Basil Algarme | Z52: NTTC No. 222207121300384 | AA52: 45728 | AB52: C | AC52: 43217
A53: VII | B53: Bohol | C53: 2nd | D53: Inabanga | E53: 3rd | F53: {=IFERROR(INDEX(UIID!$K$2:$K354, MATCH(CONCATENATE(B53,D53,G53,J53), UIID!$B$2:$B354&UIID!$D$2:$D354&UIID!$G$2:$G354&UIID!$H$2:$H354, 0),), "Not Found")} -> 0712-0004 | G53: Provincial Training Center - Inabanga | I53: Jaminel A. Damolo, Center Administrator | J53: Cagayan, Inabanga, Bohol | K53: 10.05135 | L53: 124.07921 | M53: (038) 512-9012 | N53: ptcinabanga@tesda.gov.ph | O53: Public | P53: TTI | Q53: WTR | R53: Metals and Engineering | S53: Shielded Metal Arc Welding (SMAW) NC I | T53: NC I | U53: 268 hours | V53: 201407011198 | W53: 45365 | X53: 47192 | Y53: Diosdado A. Lofranco | Z53: NTTC No. 181407121200285 | AC53: 41955
A54: VII | B54: Bohol | C54: 2nd | D54: Inabanga | E54: 3rd | F54: {=IFERROR(INDEX(UIID!$K$2:$K354, MATCH(CONCATENATE(B54,D54,G54,J54), UIID!$B$2:$B354&UIID!$D$2:$D354&UIID!$G$2:$G354&UIID!$H$2:$H354, 0),), "Not Found")} -> 0712-0004 | G54: Provincial Training Center - Inabanga | I54: Jaminel A. Damolo, Center Administrator | J54: Cagayan, Inabanga, Bohol | K54: 10.05135 | L54: 124.07921 | M54: (038) 512-9012 | N54: ptcinabanga@tesda.gov.ph | O54: Public | P54: TTI | Q54: WTR | R54: Metals and Engineering | S54: Shielded Metal Arc Welding (SMAW) NC III | T54: NC II | U54: 120 hours | V54: 201807012MEEEAW306035 | W54: 45365 | X54: 47192 | Y54: Diosdado A. Lofranco, Jr. | Z54: 211907121300433 | AC54: 43201
A55: VII | B55: Bohol | C55: 2nd | D55: Inabanga | E55: 3rd | F55: {=IFERROR(INDEX(UIID!$K$2:$K354, MATCH(CONCATENATE(B55,D55,G55,J55), UIID!$B$2:$B354&UIID!$D$2:$D354&UIID!$G$2:$G354&UIID!$H$2:$H354, 0),), "Not Found")} -> 0712-0004 | G55: Provincial Training Center - Inabanga | I55: Jaminel A. Damolo, Center Administrator | J55: Cagayan, Inabanga, Bohol | K55: 10.05135 | L55: 124.07921 | M55: (038) 512-9012 | N55: ptcinabanga@tesda.gov.ph | O55: Public | P55: TTI | Q55: WTR | R55: Metals and Engineering | S55: Shielded Metal Arc Welding (SMAW) NC II | T55: NC II | U55: 268 hours | V55: WTR No. 201707122022 | W55: 45365 | X55: 47192 | Y55: Diosdado A. Lofranco, Jr. | Z55: NTTC No. 181407121200285 | AA55: 45406 | AB55: C | AC55: 42774
A56: VII | B56: Bohol | C56: 3rd | D56: Jagna | E56: 3rd | F56: {=IFERROR(INDEX(UIID!$K$2:$K354, MATCH(CONCATENATE(B56,D56,G56,J56), UIID!$B$2:$B354&UIID!$D$2:$D354&UIID!$G$2:$G354&UIID!$H$2:$H354, 0),), "Not Found")} -> 0712-0013 | G56: Provincial Training Center - Jagna | I56: Apolinar P. Cadeliña, Center Administrator | J56: Poblacion, Jagna, Bohol | K56: 9.6667975 | L56: 124.36827 | M56: (038) 412-7558; 09384140201 | N56: ptcjagna@tesda.gov.ph | O56: Public | P56: TTI | Q56: RTP | R56: TVET | S56: Community-Based Trainers Methodology Course | T56: N/A | U56: 40 Hours | V56: NTR No.202107120087 | W56: 45049 | X56: 47156 | Y56: Rogelio D. Suarez | Z56: NTTC No. 211807121300250 | AA56: 45418 | AB56: C | AC56: 44489
A57: VII | B57: Bohol | C57: 3rd | D57: Jagna | E57: 3rd | F57: {=IFERROR(INDEX(UIID!$K$2:$K354, MATCH(CONCATENATE(B57,D57,G57,J57), UIID!$B$2:$B354&UIID!$D$2:$D354&UIID!$G$2:$G354&UIID!$H$2:$H354, 0),), "Not Found")} -> 0712-0013 | G57: Provincial Training Center - Jagna | I57: Apolinar P. Cadeliña, Center Administrator | J57: Poblacion, Jagna, Bohol | K57: 9.6667975 | L57: 124.36827 | M57: (038) 412-7558; 09384140201 | N57: ptcjagna@tesda.gov.ph | O57: Public | P57: TTI | Q57: WTR | R57: TVET | S57: Trainers Methodology Level I (Trainer/Assessor) | T57: Level I | U57: 264 Hours | V57: 20190712TVETRM111165 | W57: 45010 | X57: 46838 | Y57: Glenn D. Magadan Rogelio D. Suarez Roldan L. Madera JC Keynness T. Gunday | Z57: TMC No. 19071201013215 TMC No. 18071201022818 TMC No. 1907120101576 TMC No. 2207101000048 | AA57: 45418 | AB57: C | AC57: 43768
A58: VII | B58: Bohol | C58: 3rd | D58: Jagna | E58: 3rd | F58: {=IFERROR(INDEX(UIID!$K$2:$K354, MATCH(CONCATENATE(B58,D58,G58,J58), UIID!$B$2:$B354&UIID!$D$2:$D354&UIID!$G$2:$G354&UIID!$H$2:$H354, 0),), "Not Found")} -> 0712-0013 | G58: Provincial Training Center - Jagna | I58: Apolinar P. Cadeliña, Center Administrator | J58: Poblacion, Jagna, Bohol | K58: 9.6667975 | L58: 124.36827 | M58: (038) 412-7558; 09384140201 | N58: ptcjagna@tesda.gov.ph | O58: Public | P58: TTI | Q58: WTR | R58: Social, Community Development and Other Services | S58: Bookkeeping NC III | T58: NC III | U58: 292 Hours | V58: 20190712SOCBKP307166 | W58: 45005 | X58: 46833 | Y58: Michelle S. Tadle | Z58: NTTC No. 232207121300015 | AA58: 45418 | AB58: C | AC58: 43768
A59: VII | B59: Bohol | C59: 3rd | D59: Jagna | E59: 3rd | F59: {=IFERROR(INDEX(UIID!$K$2:$K354, MATCH(CONCATENATE(B59,D59,G59,J59), UIID!$B$2:$B354&UIID!$D$2:$D354&UIID!$G$2:$G354&UIID!$H$2:$H354, 0),), "Not Found")} -> 0712-0013 | G59: Provincial Training Center - Jagna | I59: Apolinar P. Cadeliña, Center Administrator | J59: Poblacion, Jagna, Bohol | K59: 9.6667975 | L59: 124.36827 | M59: (038) 412-7558; 09384140201 | N59: ptcjagna@tesda.gov.ph | O59: Public | P59: TTI | Q59: WTR | R59: Agriculture, Forestry and Fishery | S59: Organic Agriculture Production NC II | T59: NC II | U59: 232 Hours | V59: 20190712AFFOAP212169 | W59: 45010 | X59: 46838 | Y59: Miller Nino L. Pechon Leane J. Bañados Roldan L. Madera JC Keyness T. Gunday | Z59: PNTTC-2207120200003 NTTC No. 211907121200249 PNTTC No. 2207120200010 PNTTC No. 2207460200012 | AA59: 45418 | AB59: C | AC59: 43769
A60: VII | B60: Bohol | C60: 3rd | D60: Jagna | E60: 3rd | F60: {=IFERROR(INDEX(UIID!$K$2:$K354, MATCH(CONCATENATE(B60,D60,G60,J60), UIID!$B$2:$B354&UIID!$D$2:$D354&UIID!$G$2:$G354&UIID!$H$2:$H354, 0),), "Not Found")} -> 0712-0013 | G60: Provincial Training Center - Jagna | I60: Apolinar P. Cadeliña, Center Administrator | J60: Poblacion, Jagna, Bohol | K60: 9.6667975 | L60: 124.36827 | M60: (038) 412-7558; 09384140201 | N60: ptcjagna@tesda.gov.ph | O60: Public | P60: TTI | Q60: WTR | R60: Automotive and Land Transportation | S60: Driving NC II | T60: NC II | U60: 118 Hours | V60: 20190712ALTDRV204128 | W60: 45342 | X60: 47170 | Y60: Rogelio D. Suarez | Z60: NTTC No. 181807121200438 | AA60: 45418 | AB60: C | AC60: 43752
A61: VII | B61: Bohol | C61: 3rd | D61: Jagna | E61: 3rd | F61: {=IFERROR(INDEX(UIID!$K$2:$K354, MATCH(CONCATENATE(B61,D61,G61,J61), UIID!$B$2:$B354&UIID!$D$2:$D354&UIID!$G$2:$G354&UIID!$H$2:$H354, 0),), "Not Found")} -> 0712-0013 | G61: Provincial Training Center - Jagna | I61: Apolinar P. Cadeliña, Center Administrator | J61: Poblacion, Jagna, Bohol | K61: 9.6667975 | L61: 124.36827 | M61: (038) 412-7558; 09384140201 | N61: ptcjagna@tesda.gov.ph | O61: Public | P61: TTI | Q61: WTR | R61: Metals and Engineering | S61: Shielded Metal Arc Welding (SMAW) NC I | T61: NC I | U61: 268 Hours | V61: 20190712MEEEAW106129 | W61: 45342 | X61: 47170 | Y61: JC Keynness T. Gunday | Z61: NTTC No. 201607121200228 | AA61: 45418 | AB61: C | AC61: 43752
A62: VII | B62: Bohol | C62: 3rd | D62: Jagna | E62: 3rd | F62: {=IFERROR(INDEX(UIID!$K$2:$K354, MATCH(CONCATENATE(B62,D62,G62,J62), UIID!$B$2:$B354&UIID!$D$2:$D354&UIID!$G$2:$G354&UIID!$H$2:$H354, 0),), "Not Found")} -> 0712-0013 | G62: Provincial Training Center - Jagna | I62: Apolinar P. Cadeliña, Center Administrator | J62: Poblacion, Jagna, Bohol | K62: 9.6667975 | L62: 124.36827 | M62: (038) 412-7558; 09384140201 | N62: ptcjagna@tesda.gov.ph | O62: Public | P62: TTI | Q62: WTR | R62: Electrical and Electronics | S62: Electrical Installation and Maintenance NC II | T62: NC II | U62: 196 hours | V62: 20180712ELCEIM215082 | W62: 43262 | X62: 46838 | Y62: Glenn D. Magadan | Z62: 221907121200263 | AA62: 45728 | AB62: C
A63: VII | B63: Bohol | C63: 3rd | D63: Jagna | E63: 3rd | F63: {=IFERROR(INDEX(UIID!$K$2:$K354, MATCH(CONCATENATE(B63,D63,G63,J63), UIID!$B$2:$B354&UIID!$D$2:$D354&UIID!$G$2:$G354&UIID!$H$2:$H354, 0),), "Not Found")} -> 0712-0013 | G63: Provincial Training Center - Jagna | I63: Apolinar P. Cadeliña, Center Administrator | J63: Poblacion, Jagna, Bohol | K63: 9.6667975 | L63: 124.36827 | M63: (038) 412-7558; 09384140201 | N63: ptcjagna@tesda.gov.ph | O63: Public | P63: TTI | Q63: WTR | R63: Tourism | S63: Bread and Pastry Production NC II | T63: NC II | U63: 141 hours | V63: WTR No. 20170712TRSBPP209053 | W63: 45010 | X63: 46838 | Y63: Roldan L. Madera | Z63: 191907121200206 | AA63: 45418 | AB63: C | AC63: 42831
A64: VII | B64: Bohol | C64: 3rd | D64: Pilar | E64: 4th | F64: {=IFERROR(INDEX(UIID!$K$2:$K354, MATCH(CONCATENATE(B64,D64,G64,J64), UIID!$B$2:$B354&UIID!$D$2:$D354&UIID!$G$2:$G354&UIID!$H$2:$H354, 0),), "Not Found")} -> 0712-0005 | G64: Provincial Training Center - Pilar | I64: Homer Lendie B. Magante, Center Administrator | J64: Poblacion, Pilar, Bohol | K64: 9.8567162 | L64: 124.33643 | M64: (038) 510-8237 / 09173164144 | N64: ptcpilar@tesda.gov.ph | O64: Public | P64: TTI | Q64: WTR | R64: Tourism | S64: Bread and Pastry Production NC II | T64: NC II | U64: 141 Hours | V64: 20200712TRSBPP209076 | W64: 45329 | X64: 47157 | Y64: Ailyn A. Baratas | Z64: NTTC No. 201807121200063 | AC64: 44175
A65: VII | B65: Bohol | C65: 3rd | D65: Pilar | E65: 4th | F65: {=IFERROR(INDEX(UIID!$K$2:$K354, MATCH(CONCATENATE(B65,D65,G65,J65), UIID!$B$2:$B354&UIID!$D$2:$D354&UIID!$G$2:$G354&UIID!$H$2:$H354, 0),), "Not Found")} -> 0712-0005 | G65: Provincial Training Center - Pilar | I65: Homer Lendie B. Magante, Center Administrator | J65: Poblacion, Pilar, Bohol | K65: 9.8567162 | L65: 124.33643 | M65: (038) 510-8237 / 09173164144 | N65: ptcpilar@tesda.gov.ph | O65: Public | P65: TTI | Q65: WTR | R65: Construction | S65: Masonry NC I | T65: NC I | U65: 123 Hours | V65: 20200712CONMAS118080 | W65: 45014 | X65: 46842 | Y65: Robert S. Ladeza | Z65: NTTC No. 211707121200331 | AA65: 45798 | AB65: C | AC65: 44176
A66: VII | B66: Bohol | C66: 3rd | D66: Pilar | E66: 4th | F66: {=IFERROR(INDEX(UIID!$K$2:$K354, MATCH(CONCATENATE(B66,D66,G66,J66), UIID!$B$2:$B354&UIID!$D$2:$D354&UIID!$G$2:$G354&UIID!$H$2:$H354, 0),), "Not Found")} -> 0712-0005 | G66: Provincial Training Center - Pilar | I66: Homer Lendie B. Maganet | J66: Poblacion, Pilar, Bohol | K66: 9.8567162 | L66: 124.33643 | M66: (038) 510-8237 / 09173164144 | N66: ptcpilar@tesda.gov.ph | O66: Public | P66: TTI | Q66: RTP | R66: Agriculture, Forestry and Fishery | S66: Production of High-Quality Inbred Rice, and Seed Certification, and Farm Mechanization | T66: N/A | U66: 96 hours | V66: NTR No.202007120032 | W66: 45014 | X66: 46842 | Y66: Luznevieve B. Paulines | Z66: ATI Certificate of Completion (TOT on Production of High-Quality Inbred Rice, Seed Certification and Farm Mechanization) | AA66: 45798 | AB66: C | AC66: 44042
